Workbook

Sheet 1008-403
A1: Date | B1: Journal | C1: Ref. | D1: Description | E1: Cost Center | F1: Debit | G1: Credit | H1: Balance
A2: Account Code : 1008/403 Account Name : SYNTHETICS LATEX
D3: Balance B/F | F3: 0 | G3: 0 | H3: 10139364
A4: 01-May-26 | B4: JV-26-05-0028 | C4: Beginning Stock Compound Latex, Dispersion, Production dept of May'26 | D4: Beginning Stock Compound latex in Compound dept of May'26 | F4: 0 | G4: 1687850.2 | H4: 8451513.4
A5: 01-May-26 | B5: JV-26-05-0028 | C5: Beginning Stock Compound Latex, Dispersion, Production dept of May'26 | D5: Beginning Stock Compound latex in Dipping lines of May'26 | F5: 0 | G5: 190811.58 | H5: 8260701.8
A6: 31-May-26 | B6: JV-26-05-0125 | C6: Trf NBR LATEX FROM P1,P2and P3 on May'26 | D6: Trf NBR LATEX FROM STORE-P2 TO COM-P1 128,030 KG on May'26 | F6: 6777780.2 | G6: 0 | H6: 15038482
A7: 31-May-26 | B7: JV-26-05-0125 | C7: Trf NBR LATEX FROM P1,P2and P3 on May'26 | D7: Trf NBR LATEX FROM STORE-P3 TO COM-P1 155,710 KG on May'26 | F7: 6804835.8 | G7: 0 | H7: 21843318
A8: 31-May-26 | B8: JV-26-05-0125 | C8: Trf NBR LATEX FROM P1,P2and P3 on May'26 | D8: Trf NBR LATEX FROM COM-P3 TO COM-P1 4,671 KG on May'26 | F8: 468421.56 | G8: 0 | H8: 22311739
A9: 31-May-26 | B9: JV-26-05-0125 | C9: Trf NBR LATEX FROM P1,P2and P3 on May'26 | D9: Trf NBR LATEX FROM COM-P2 TO COM-P1 35,945 KG on May'26 | F9: 1431570.1 | G9: 0 | H9: 23743310
A10: 31-May-26 | B10: JV-26-05-0125 | C10: Trf NBR LATEX FROM P1,P2and P3 on May'26 | D10: Trf NBR LATEX FROM COM-P1 TO COM-P2 30,760 KG on May'26 | F10: 0 | G10: 1205649.2 | H10: 22537660
A11: 31-May-26 | B11: JV-26-05-0125 | C11: Trf NBR LATEX FROM P1,P2and P3 on May'26 | D11: Trf NBR LATEX FROM COM-P1 TO COM-P3 29,879 KG on May'26 | F11: 0 | G11: 691743.98 | H11: 21845916
A12: 31-May-26 | B12: JV-26-05-0150 | C12: Ending Balance Stock NBR and Chemical and Use of Plant 1 on May'26 | D12: Balance Compound latex in Compound dept of May'26 | F12: 1920167.2 | G12: 0 | H12: 23766084
A13: 31-May-26 | B13: JV-26-05-0150 | C13: Ending Balance Stock NBR and Chemical and Use of Plant 1 on May'26 | D13: Balance Compound latex in Dipping lines of May'26 | F13: 328050.82 | G13: 0 | H13: 24094134
A14: 31-May-26 | B14: JV-26-05-0150 | C14: Ending Balance Stock NBR and Chemical and Use of Plant 1 on May'26 | D14: Record Issue NBR latex-Comp from stock card Com P1 of May'26 | F14: 0 | G14: 13082080 | H14: 11012054
E15: Total | F15: 17730826 | G15: 16858135
E16: Grand Total | F16: 17730826 | G16: 16858135
A17: Printed by Siriporn Boonrath On 05-Jun-2026 09:52:26 PM | B17: Page -1 of 1
F23: Balance stock Compound | H23: ='NBR Latex-Comp'!BB13 -> 8763836.2
F24: Balance stock Dip+Com | H24: =Used_before_Trf!AB174 -> 2248218
F25: Total | H25: =SUM(H23:H24) -> 11012054
F26: Diff | H26: =H14-H25 -> -0.08
F43: 0

Sheet 7000-131
A1: Date | B1: Journal | C1: Ref. | D1: Description | E1: Cost Center | F1: Debit | G1: Credit | H1: Balance
A2: Account Code : 7000/131 Account Name : PURCHASE SYNTHETICS LATEX
D3: Balance B/F | F3: 0 | G3: 0 | H3: 5797752.7
A4: 01-Feb-26 | B4: JV-26-02-0022 | C4: ฺBeginning Stock NBR Latex and Chemical of Plant 1 on Feb'26 | D4: Beginning Stock Compound latex in Compound dept of Feb'26 | E4: Compounding P1 | F4: 585463.38 | G4: 0 | H4: 6383216
A5: 01-Feb-26 | B5: JV-26-02-0022 | C5: ฺBeginning Stock NBR Latex and Chemical of Plant 1 on Feb'26 | D5: Beginning Stock Compound latex in Dipping lines of Feb'26 | E5: Compounding P1 | F5: 97513.91 | G5: 0 | H5: 6480729.9
A6: 28-Feb-26 | B6: JV-26-02-0126 | C6: Ending Balance Stock NBR and Chemical and Use of Plant 1 on Feb'26 | D6: Balance Compound latex in Compound dept of Feb'26 | E6: Compounding P1 | F6: 0 | G6: 709416.42 | H6: 5771313.5
A7: 28-Feb-26 | B7: JV-26-02-0126 | C7: Ending Balance Stock NBR and Chemical and Use of Plant 1 on Feb'26 | D7: Record Issue NBR latex-Comp from stock card Com P1 of Feb'26 | E7: Compounding P1 | F7: 5435567.4 | G7: 0 | H7: 11206881
A8: 28-Feb-26 | B8: JV-26-02-0126 | C8: Ending Balance Stock NBR and Chemical and Use of Plant 1 on Feb'26 | D8: Balance Compound latex in Dipping lines of Feb'26 | E8: Compounding P1 | F8: 0 | G8: 144751.7 | H8: 11062129
A9: 28-Feb-26 | B9: JV-26-02-0131 | C9: Transfer Compound latex and Dispersion between plants of Feb'26 | D9: Transfer Compound latex between plants of Feb'26 | E9: Compounding P1 | F9: 66456.8 | G9: 0 | H9: 11128586
E10: Total | F10: 6185001.5 | G10: 854168.12
E11: Grand Total | F11: 6185001.5 | G11: 854168.12
A12: Printed by Siriporn Boonrath On 06-Mar-2026 10:03:26 AM | B12: Page -1 of 1
F13: =F11-G11 -> 5330833.4

Sheet 1008-402
A1: Date | B1: Journal | C1: Ref. | D1: Description | E1: Cost Center | F1: Debit | G1: Credit | H1: Balance
A2: Account Code : 1008/402 Account Name : CHEMICAL FOR NR GLOVES
D3: Balance B/F | F3: 0 | G3: 0 | H3: 2577038.9
A4: 01-May-26 | B4: JV-26-05-0028 | C4: Beginning Stock Compound Latex, Dispersion, Production dept of May'26 | D4: Beginning Stock Compound latex in Compound dept of May'26 | F4: 0 | G4: 155765.77 | H4: 2421273.1
A5: 01-May-26 | B5: JV-26-05-0028 | C5: Beginning Stock Compound Latex, Dispersion, Production dept of May'26 | D5: Beginning Stock Dispersion in Compound dept of May'26 | F5: 0 | G5: 312388.52 | H5: 2108884.6
A6: 01-May-26 | B6: JV-26-05-0028 | C6: Beginning Stock Compound Latex, Dispersion, Production dept of May'26 | D6: Beginning Stock Compound latex in Dipping lines of May'26 | F6: 0 | G6: 17696.49 | H6: 2091188.1
A7: 01-May-26 | B7: JV-26-05-0028 | C7: Beginning Stock Compound Latex, Dispersion, Production dept of May'26 | D7: Beginning Stock Compound latex in Dipping lines of May'26 | F7: 0 | G7: 55899.52 | H7: 2035288.6
A8: 01-May-26 | B8: JV-26-05-0028 | C8: Beginning Stock Compound Latex, Dispersion, Production dept of May'26 | D8: Beginning Stock Chemical in Production May'26 | F8: 0 | G8: 67687.75 | H8: 1967600.8
A9: 06-May-26 | B9: MIJ-26-05-0086 | C9: MI-26-05-0092 | D9: TEXKLEEN P22 (225KG/DRUM)(ALKALINE CLEANER ),(TEST) KLEEN S21 (225KG/DRUM) (ALAKLINE CLEANNER) | F9: 0 | G9: 18000 | H9: 1949600.8
A10: 09-May-26 | B10: MIJ-26-05-0175 | C10: MI-26-05-0187 | D10: TEXKLEEN P22 (225KG/DRUM)(ALKALINE CLEANER ) | F10: 0 | G10: 9450 | H10: 1940150.8
A11: 11-May-26 | B11: MIJ-26-05-0176 | C11: MI-26-05-0188 | D11: TEXKLEEN P22 (225KG/DRUM)(ALKALINE CLEANER ) | F11: 0 | G11: 9450 | H11: 1930700.8
A12: 13-May-26 | B12: MIJ-26-05-0268 | C12: MI-26-05-0292 | D12: NITRIC ACID 68% (280 KGS/DRUM ) | F12: 0 | G12: 17360 | H12: 1913340.8
A13: 15-May-26 | B13: MIJ-26-05-0314 | C13: MI-26-05-0345 | D13: (TEST) SPECLEAN 10 (230KG/DRUM) - ALKALINE CLEANER | F13: 0 | G13: 8834.39 | H13: 1904506.4
A14: 18-May-26 | B14: MIJ-26-05-0420 | C14: MI-26-05-0469 | D14: (TEST) SPECLEAN 10 (230KG/DRUM) - ALKALINE CLEANER,TEXKLEEN P22 (225KG/DRUM)(ALKALINE CLEANER ) | F14: 0 | G14: 18284.39 | H14: 1886222
A15: 19-May-26 | B15: PUR-26-05-0879 | C15: PS-26-05-0649 | D15: INV.NU-INV-1065-B BIO-F20 (100KG) - NUECHEMIE | F15: 13709.36 | G15: 0 | H15: 1899931.4
... A34: 31-May-26 | B34: JV-26-05-0150 | C34: Ending Balance Stock NBR and Chemical and Use of Plant 1 on May'26 | D34: Record Issue Che-Comp from stock card Com P1 of May'26 | F34: 781.78 | G34: 0 | H34: 2816697.8
E35: Total | F35: 4487328.2 | G35: 4247669.2
E36: Grand Total | F36: 4487328.2 | G36: 4247669.2
A37: Printed by Siriporn Boonrath On 05-Jun-2026 09:52:59 PM | B37: Page -1 of 1
E38: Purchase | F38: =F36-F34-F32-F31-F30-F29-F28-F27-F25-F24-F23 -> 1303811.2
F40: Balance Stock Store | H40: ='Che-Store'!BC14 -> 1641528.2
F41: Balance Stock Compound | H41: ='Che-Comp'!BC30 -> 524568.67
F42: Balance stock Dip+Com | H42: =Used_before_Trf!AB172 -> 608636.2
F43: Balance stock production | H43: ='Che.-Prod'!R18 -> 41966
F44: Total | H44: =SUM(H40:H43) -> 2816699
F45: Diff | H45: =H34-H44 -> -1.22

Sheet 7000-122
A1: Date | B1: Journal | C1: Ref. | D1: Description | E1: Cost Center | F1: Debit | G1: Credit | H1: Balance
A2: Account Code : 7000/122 Account Name : PURCHASES - CHEMICAL
D3: Balance B/F | F3: 0 | G3: 0 | H3: 31410909
A4: 01-Feb-26 | B4: JV-26-02-0022 | C4: ฺBeginning Stock NBR Latex and Chemical of Plant 1 on Feb'26 | D4: Beginning Stock Compound latex in Compound dept of Feb'26 | E4: Compounding P1 | F4: 96744.25 | G4: 0 | H4: 31507653
A5: 01-Feb-26 | B5: JV-26-02-0022 | C5: ฺBeginning Stock NBR Latex and Chemical of Plant 1 on Feb'26 | D5: Beginning Stock Dispersion in Compound dept of Feb'26 | E5: Compounding P1 | F5: 100662.71 | G5: 0 | H5: 31608316
A6: 01-Feb-26 | B6: JV-26-02-0022 | C6: ฺBeginning Stock NBR Latex and Chemical of Plant 1 on Feb'26 | D6: Beginning Stock Compound latex in Dipping lines of Feb'26 | E6: Compounding P1 | F6: 13077.43 | G6: 0 | H6: 31621393
A7: 01-Feb-26 | B7: JV-26-02-0022 | C7: ฺBeginning Stock NBR Latex and Chemical of Plant 1 on Feb'26 | D7: Beginning Stock Compound latex in Dipping lines of Feb'26 | E7: Compounding P1 | F7: 56227.98 | G7: 0 | H7: 31677621
A8: 01-Feb-26 | B8: JV-26-02-0022 | C8: ฺBeginning Stock NBR Latex and Chemical of Plant 1 on Feb'26 | D8: Beginning Stock Compound latex in Dipping lines of Feb'26 | E8: Production P1 | F8: 2879.21 | G8: 0 | H8: 31680500
A9: 01-Feb-26 | B9: JV-26-02-0022 | C9: ฺBeginning Stock NBR Latex and Chemical of Plant 1 on Feb'26 | D9: Beginning Stock Chemical in Production Feb'26 | E9: Production P1 | F9: 14312.4 | G9: 0 | H9: 31694813
A10: 02-Feb-26 | B10: MIJ-26-02-0007 | C10: MI-26-02-0007 | D10: NITRIC ACID 68% (280 KGS/DRUM ),TEXKLEEN P22 (225KG/DRUM)(ALKALINE CLEANER ) | E10: Production P1 | F10: 34020 | G10: 0 | H10: 31728833
A11: 06-Feb-26 | B11: MIJ-26-02-0150 | C11: MI-26-02-0164 | D11: NITRIC ACID 68% (280 KGS/DRUM ),TEXKLEEN P22 (225KG/DRUM)(ALKALINE CLEANER ) | E11: Production P1 | F11: 24570 | G11: 0 | H11: 31753403
A12: 10-Feb-26 | B12: MIJ-26-02-0218 | C12: MI-26-02-0237 | D12: TEXKLEEN P22 (225KG/DRUM)(ALKALINE CLEANER ) | E12: Production P1 | F12: 9450 | G12: 0 | H12: 31762853
A13: 12-Feb-26 | B13: MIJ-26-02-0284 | C13: MI-26-02-0325 | D13: TEXKLEEN P22 (225KG/DRUM)(ALKALINE CLEANER ) | E13: Production P1 | F13: 9450 | G13: 0 | H13: 31772303
A14: 13-Feb-26 | B14: MIJ-26-02-0294 | C14: MI-26-02-0336 | D14: TEXKLEEN P22 (225KG/DRUM)(ALKALINE CLEANER ),TEXKLEEN P22 (225KG/DRUM)(ALKALINE CLEANER ) | E14: Production P1 | F14: 18900 | G14: 0 | H14: 31791203
A15: 17-Feb-26 | B15: MIJ-26-02-0361 | C15: MI-26-02-0408 | D15: NITRIC ACID 68% (280 KGS/DRUM ),TEXKLEEN P22 (225KG/DRUM)(ALKALINE CLEANER ) | E15: Production P1 | F15: 24570 | G15: 0 | H15: 31815773
... A32: 28-Feb-26 | B32: JV-26-02-0131 | C32: Transfer Compound latex and Dispersion between plants of Feb'26 | D32: Transfer Dispersion between plants of Feb'26 | E32: Compounding P1 | F32: 13570.93 | G32: 0 | H32: 34049065
E33: Total | F33: 3380102.9 | G33: 741946.35
E34: Grand Total | F34: 3380102.9 | G34: 741946.35
A35: Printed by Siriporn Boonrath On 11-Mar-2026 09:45:09 AM | B35: Page -1 of 1
E38: Total | F38: 3380102.9 | G38: 741946.35

Sheet CHE-last month
A1: Net consumed Latex and Chemical on Apr'26 | K1: Net consumed Latex and Chemical on Apr'26
B3: Description | D3: Mar'26 | M3: Closing stock
A4: Code | C4: Kgs | D4: Cost : Kg | E4: Value (Bht) | K4: Code | L4: Description | M4: Kgs | N4: Cost : Kg | O4: Value (Bht)
A5: =+K5 -> CH101 | B5: =+L5 -> CHLORINE 99.5% (1,000 KGS CYLINDER) MOITURE 100 MG/KG MAX. | C5: =SUMIF(K:K,A5,M:M) -> 0 | D5: =IF(C5=0,0,E5/C5) -> 0 | E5: =SUMIF($K:$K,A5,O:O) -> 0 | K5: CH101 | L5: CHLORINE 99.5% (1,000 KGS CYLINDER) MOITURE 100 MG/KG MAX. | M5: 0 | N5: 0 | O5: 0
A6: =+K6 -> CH102 | B6: =+L6 -> SODIUM HYDROXIDE 50% (1500 KGS/IBC) | C6: =SUMIF(K:K,A6,M:M) -> 0 | D6: =IF(C6=0,0,E6/C6) -> 0 | E6: =SUMIF($K:$K,A6,O:O) -> 0 | K6: CH102 | L6: SODIUM HYDROXIDE 50% (1500 KGS/IBC) | M6: 0 | N6: 0 | O6: 0
A7: =+K7 -> CH104 | B7: =+L7 -> SPECLEAN 11 (246 KGS /DRUM) | C7: =SUMIF(K:K,A7,M:M) -> 0 | D7: =IF(C7=0,0,E7/C7) -> 0 | E7: =SUMIF($K:$K,A7,O:O) -> 0 | K7: CH104 | L7: SPECLEAN 11 (246 KGS /DRUM) | M7: 0 | N7: 0 | O7: 0
A8: =+K8 -> CH105 | B8: =+L8 -> HISOL D203 (QA75/137) 200 KGS/DRUM (MOQ 400KG/TRIP) | C8: =SUMIF(K:K,A8,M:M) -> 0 | D8: =IF(C8=0,0,E8/C8) -> 0 | E8: =SUMIF($K:$K,A8,O:O) -> 0 | K8: CH105 | L8: HISOL D203 (QA75/137) 200 KGS/DRUM (MOQ 400KG/TRIP) | M8: 0 | N8: 0 | O8: 0
A9: =+K9 -> CH106 | B9: =+L9 -> OCTOSOL 643 (200KG/DRUM) | C9: =SUMIF(K:K,A9,M:M) -> 24.103642 | D9: =IF(C9=0,0,E9/C9) -> 25.550081 | E9: =SUMIF($K:$K,A9,O:O) -> 615.85 | K9: CH106 | L9: OCTOSOL 643 (200KG/DRUM) | M9: 24.103642 | N9: 25.550081 | O9: 615.85
A10: =+K10 -> CH109 | B10: =+L10 -> VIVASHIELD 9177 WAX (950KG/IBC) | C10: =SUMIF(K:K,A10,M:M) -> 0 | D10: =IF(C10=0,0,E10/C10) -> 0 | E10: =SUMIF($K:$K,A10,O:O) -> 0 | K10: CH109 | L10: VIVASHIELD 9177 WAX (950KG/IBC) | M10: 0 | N10: 0 | O10: 0
A11: =+K11 -> CH110 | B11: =+L11 -> CS COAT T403 (1000 KG/TANK) | C11: =SUMIF(K:K,A11,M:M) -> 0 | D11: =IF(C11=0,0,E11/C11) -> 0 | E11: =SUMIF($K:$K,A11,O:O) -> 0 | K11: CH110 | L11: CS COAT T403 (1000 KG/TANK) | M11: 0 | N11: 0 | O11: 0
A12: =+K12 -> CH111 | B12: =+L12 -> ALKALINE CLEAN S4 (1100 KG/TANK) | C12: =SUMIF(K:K,A12,M:M) -> 0 | D12: =IF(C12=0,0,E12/C12) -> 0 | E12: =SUMIF($K:$K,A12,O:O) -> 0 | K12: CH111 | L12: ALKALINE CLEAN S4 (1100 KG/TANK) | M12: 0 | N12: 0 | O12: 0
A13: =+K13 -> CH112 | B13: =+L13 -> TRUCOAT NR 12 (200KG/DRUM) MOQ=16,000KG/TRIP | C13: =SUMIF(K:K,A13,M:M) -> 0 | D13: =IF(C13=0,0,E13/C13) -> 0 | E13: =SUMIF($K:$K,A13,O:O) -> 0 | K13: CH112 | L13: TRUCOAT NR 12 (200KG/DRUM) MOQ=16,000KG/TRIP | M13: 0 | N13: 0 | O13: 0
A14: =+K14 -> CH113 | B14: =+L14 -> CALCIUM NITRATE LIQUOR 54- 56% (300KG/DRUM)-MEYCHERN | C14: =SUMIF(K:K,A14,M:M) -> 0 | D14: =IF(C14=0,0,E14/C14) -> 0 | E14: =SUMIF($K:$K,A14,O:O) -> 0 | K14: CH113 | L14: CALCIUM NITRATE LIQUOR 54- 56% (300KG/DRUM)-MEYCHERN | M14: 0 | N14: 0 | O14: 0
A15: =+K15 -> CH114 | B15: =+L15 -> TRANSCURE ZDB50 (225KG/DRUM) | C15: =SUMIF(K:K,A15,M:M) -> 0 | D15: =IF(C15=0,0,E15/C15) -> 0 | E15: =SUMIF($K:$K,A15,O:O) -> 0 | K15: CH114 | L15: TRANSCURE ZDB50 (225KG/DRUM) | M15: 0 | N15: 0 | O15: 0
A16: =+K16 -> CH115 | B16: =+L16 -> TRANSACT ZNO60 (250KG/DRUM) | C16: =SUMIF(K:K,A16,M:M) -> 0 | D16: =IF(C16=0,0,E16/C16) -> 0 | E16: =SUMIF($K:$K,A16,O:O) -> 0 | K16: CH115 | L16: TRANSACT ZNO60 (250KG/DRUM) | M16: 0 | N16: 0 | O16: 0
... A169: =+K169 -> SFG-Water | B169: =+L169 -> Water | C169: =SUMIF(K:K,A169,M:M) -> 44115.782 | D169: =IF(C169=0,0,E169/C169) -> 0 | E169: =SUMIF($K:$K,A169,O:O) -> 0 | K169: SFG-Water | L169: Water | M169: 44115.782 | N169: 0 | O169: 0
C170: =SUM(C6:C168)-C168 -> 35845.211 | E170: =SUM(E6:H167) -> 541750.3 | M170: =SUM(M6:M168)-M168 -> 35845.211 | O170: =SUM(O6:O168) -> 541750.3
A172: LN01 | B172: NITRILE LATEX | C172: =SUMIF(K:K,A172,M:M) -> 42708.388 | D172: =IF(C172=0,0,E172/C172) -> 43.988122 | E172: =SUMIF($K:$K,A172,O:O) -> 1878661.8 | K172: LN01 | L172: NITRILE LATEX | M172: 42708.388 | N172: 43.988122 | O172: 1878661.8
B173: **check Total LN01 with Detail as below** | D173: =IF(C173=0,0,E173/C173) -> 0 | L173: **check Total LN01 with Detail as below**
A174: NBR01 | B174: SYNTHETIC LATEX BST NBL 8503S | C174: =M174 -> 42708.388 | D174: =N174 -> 43.988122 | E174: =O174 -> 1878661.8 | K174: NBR01 | L174: SYNTHETIC LATEX BST NBL 8503S | M174: 42708.388 | N174: 43.988122 | O174: 1878661.8
A175: NBR11 | B175: NBR LATEX KNL830 | C175: =M175 -> 0 | D175: =N175 -> 0 | E175: =O175 -> 0 | K175: NBR13 | L175: SYNTHOMER 6329 | M175: 0 | N175: 0 | O175: 0
A176: NBR13 | B176: SYNTHOMER 6329 | C176: =M176 -> 0 | D176: =N176 -> 0 | E176: =O176 -> 0 | K176: NBR30 | L176: (TEST) NBR-XY806
K177: NBR12 | L177: SYNTHETIC LATEX '' LG NITRILE LUTEX 125 ''
C185: =+C172+C170 -> 78553.598 | E185: =+E170+E172 -> 2420412.1 | M185: =+M170+M172 -> 78553.598 | O185: =+O170+O172 -> 2420412.1

Sheet NBR Latex-Store
A1: Mercator Medical (Thailand) LTD.
A2: Stock Card Report By Location- Fin Year Based
A3: From 01-May-26 To 31-May-26 | F3: Costing method: WA | J3: TAX ID : | L3: 0905546002869
A5: Code | B5: Item | C5: UOM | F5: Received Qty | G5: Received Amount | H5: Transfer from Inv Store P1 Qty | I5: Transfer from Inv Store P1 Amount | J5: Transfer from Inv Store P2 Qty | K5: Transfer from Inv Store P2 Amount | L5: Transfer from Inv Store P3 Qty | M5: Transfer from Inv Store P3 Amount | O5: Transfer from Comp P1 Qty | P5: Transfer from Comp P1 Amount | Q5: Transfer from Comp P2 Qty | R5: Transfer from Comp P2 Amount | S5: Transfer from Comp P3 Qty | T5: Transfer from Comp P3 Amount | U5: Transfer from Prod Store P1 Qty | V5: Transfer from Prod Store P1 Amount | W5: Transfer from Prod Store P2 Qty | X5: Transfer from Prod Store P2 Amount | Z5: Transfer from Prod Store P3 Qty | AA5: Transfer from Prod Store P3 Amount | AC5: Issued Qty | AD5: Issued Amount | AE5: Transfer to Inv Store P1 Qty | AF5: Transfer to Inv Store P1 Amount | AG5: Transfer to Inv Store P2 Qty | AH5: Transfer to Inv Store P2 Amount | AI5: Transfer to Inv Store P3 Qty | AJ5: Transfer to Inv Store P3 Amount | AK5: Transfer to Comp P1 Qty | AM5: Transfer to Comp P1 Amount | AN5: Transfer to Comp P2 Qty | AO5: Transfer to Comp P2 Amount | AQ5: Transfer to Comp P3 Qty | AR5: Transfer to Comp P3 Amount | AS5: Transfer to Prod Store P1 Qty | AT5: Transfer to Prod Store P1 Amount | AU5: Transfer to Prod Store P2 Qty | AV5: Transfer to Prod Store P2 Amount | AW5: Transfer to Prod Store P3 Qty | AX5: Transfer to Prod Store P3 Amount | AY5: Adjustment Qty | AZ5: Balance Qty | BA5: Balance Unit Cost | BB5: Balance Amount | BC5: Category
A6: Inv Store - Plant 1
B13: Total | F13: =SUM(F7:F12) -> 0 | G13: =SUM(G7:G12) -> 0 | H13: =SUM(H7:H12) -> 0 | I13: =SUM(I7:I12) -> 0 | J13: =SUM(J7:J12) -> 0 | K13: =SUM(K7:K12) -> 0 | L13: =SUM(L7:L12) -> 0 | M13: =SUM(M7:M12) -> 0 | ... AZ13: =SUM(AZ7:AZ12) -> 0 | BB13: =SUM(BB7:BB12) -> 0
C15: check | AZ15: 0 | BB15: 0
B17: ผลต่างจากใบตาชั่ง

Sheet NBR Latex-Comp
A1: Mercator Medical (Thailand) LTD. | AE1: 0
A2: Stock Card Report By Location- Fin Year Based
A3: From 01-May-26 To 31-May-26 | F3: Costing method: WA | J3: TAX ID : | L3: 0905546002869
A5: Code | B5: Item | C5: UOM | D5: B/F | F5: Received Qty | G5: Received Amount | H5: Transfer from Inv Store P1 Qty | I5: Transfer from Inv Store P1 Amount | J5: Transfer from Inv Store P2 Qty | K5: Transfer from Inv Store P2 Amount | L5: Transfer from Inv Store P3 Qty | M5: Transfer from Inv Store P3 Amount | O5: Transfer from Comp P1 Qty | P5: Transfer from Comp P1 Amount | Q5: Transfer from Comp P2 Qty | R5: Transfer from Comp P2 Amount | S5: Transfer from Comp P3 Qty | T5: Transfer from Comp P3 Amount | U5: Transfer from Prod Store P1 Qty | V5: Transfer from Prod Store P1 Amount | W5: Transfer from Prod Store P2 Qty | X5: Transfer from Prod Store P2 Amount | Z5: Transfer from Prod Store P3 Qty | AA5: Transfer from Prod Store P3 Amount | AC5: Issued Qty | AD5: Issued Amount | AE5: Transfer to Inv Store P1 Qty | AF5: Transfer to Inv Store P1 Amount | AG5: Transfer to Inv Store P2 Qty | AH5: Transfer to Inv Store P2 Amount | AI5: Transfer to Inv Store P3 Qty | AJ5: Transfer to Inv Store P3 Amount | AK5: Transfer to Comp P1 Qty | AM5: Transfer to Comp P1 Amount | AN5: Transfer to Comp P2 Qty | AO5: Transfer to Comp P2 Amount | AQ5: Transfer to Comp P3 Qty | AR5: Transfer to Comp P3 Amount | AS5: Transfer to Prod Store P1 Qty | AT5: Transfer to Prod Store P1 Amount | AU5: Transfer to Prod Store P2 Qty | AV5: Transfer to Prod Store P2 Amount | AW5: Transfer to Prod Store P3 Qty | AX5: Transfer to Prod Store P3 Amount | AY5: Adjustment Qty | AZ5: Balance Qty | BA5: Balance Unit Cost | BB5: Balance Amount | BC5: Category
A6: Compound store - Plant 1 | D6: Qty | E6: Amount
A7: NBR01 | B7: SYNTHETIC LATEX BST NBL 8503S | C7: Kg | D7: 43750 | E7: 2112425 | F7: 0 | G7: 0 | H7: 0 | I7: 0 | J7: 128030 | K7: 6777780.2 | L7: 0 | M7: 0 | O7: 0 | P7: 0 | Q7: 0 | R7: 0 | S7: 0 | T7: 0 | U7: 0 | V7: 0 | W7: 0 | X7: 0 | Z7: 0 | AA7: 0 | AC7: 84083 | AD7: 4247613.7 | AE7: 0 | AF7: 0 | AG7: 0 | AH7: 0 | AI7: 0 | AJ7: 0 | AK7: 0 | AM7: 0 | AN7: 6760 | AO7: 357867.64 | AQ7: 0 | AR7: 0 | AS7: 0 | AT7: 0 | AU7: 0 | AV7: 0 | AW7: 0 | AX7: 0 | AY7: 0 | AZ7: 80937 | BA7: 52.938999 | BB7: 4284723.8 | BC7: NBR-Latex
A8: NBR12 | B8: SYNTHETIC LATEX '' LG NITRILE LUTEX 125 '' | C8: Kg | D8: 144908 | E8: 3332719.8 | F8: 0 | G8: 0 | H8: 0 | I8: 0 | J8: 0 | K8: 0 | L8: 0 | M8: 0 | O8: 0 | P8: 0 | Q8: 0 | R8: 0 | S8: 0 | T8: 0 | U8: 0 | V8: 0 | W8: 0 | X8: 0 | Z8: 0 | AA8: 0 | AC8: 0 | AD8: 0 | AE8: 0 | AF8: 0 | AG8: 0 | AH8: 0 | AI8: 0 | AJ8: 0 | AK8: 0 | AM8: 0 | AN8: 0 | AO8: 0 | AQ8: 29879 | AR8: 691743.98 | AS8: 0 | AT8: 0 | AU8: 0 | AV8: 0 | AW8: 0 | AX8: 0 | AY8: 0 | AZ8: 115029 | BA8: 22.959217 | BB8: 2640975.8 | BC8: NBR-Latex
A9: NBR30 | B9: (TEST) NBR-XY806 | C9: Kg | D9: 87900 | E9: 2815557.1 | F9: 0 | G9: 0 | H9: 0 | I9: 0 | J9: 0 | K9: 0 | L9: 109760 | M9: 4724320.9 | O9: 0 | P9: 0 | Q9: 25945 | R9: 1034216.1 | S9: 14671 | T9: 468421.56 | U9: 0 | V9: 0 | W9: 0 | X9: 0 | Z9: 0 | AA9: 0 | AC9: 220715 | AD9: 8455174.4 | AE9: 0 | AF9: 0 | AG9: 0 | AH9: 0 | AI9: 0 | AJ9: 0 | AK9: 0 | AM9: 0 | AN9: 14000 | AO9: 450427.6 | AQ9: 0 | AR9: 0 | AS9: 0 | AT9: 0 | AU9: 0 | AV9: 0 | AW9: 0 | AX9: 0 | AY9: 0 | AZ9: 3561 | BA9: 38.44813 | BB9: 136913.79 | BC9: NBR-Latex
A10: NBR31 | B10: (TEST) NBR LATEX, RFA-7632 | C10: Kg | D10: 0 | E10: 0 | F10: 0 | G10: 0 | H10: 0 | I10: 0 | J10: 0 | K10: 0 | L10: 45950 | M10: 2080514.9 | O10: 0 | P10: 0 | Q10: 10000 | R10: 397354 | S10: 0 | T10: 0 | U10: 0 | V10: 0 | W10: 0 | X10: 0 | Z10: 0 | AA10: 0 | AC10: 8377 | AD10: 379292.13 | AE10: 0 | AF10: 0 | AG10: 0 | AH10: 0 | AI10: 0 | AJ10: 0 | AK10: 0 | AM10: 0 | AN10: 10000 | AO10: 397354 | AQ10: 0 | AR10: 0 | AS10: 0 | AT10: 0 | AU10: 0 | AV10: 0 | AW10: 0 | AX10: 0 | AY10: 0 | AZ10: 37573 | BA10: 45.2778 | BB10: 1701222.8 | BC10: NBR-Latex
B13: Total | D13: =SUM(D7:D12) -> 276558 | E13: =SUM(E7:E12) -> 8260701.9 | F13: =SUM(F7:F12) -> 0 | G13: =SUM(G7:G12) -> 0 | H13: =SUM(H7:H12) -> 0 | I13: =SUM(I7:I12) -> 0 | J13: =SUM(J7:J12) -> 128030 | K13: =SUM(K7:K12) -> 6777780.2 | ... AZ13: =SUM(AZ7:AZ12) -> 237100 | BB13: =SUM(BB7:BB12) -> 8763836.2
C15: check | D15: 276558 | E15: 8260701.9 | AZ15: =+D13+F13+J13+L13+Q13+S13-AC13-AN13-AQ13 -> 237100 | BB15: =+E13+K13+M13+T13-AD13-AO13-AR13+G13+R13 -> 8763836.2
AZ16: =+AZ13-AZ15 -> 0 | BB16: =+BB13-BB15 -> 0
C17: in | D17: =F13+J13+L13+Q13+S13 -> 334356
C18: out | D18: =AC13+AN13+AQ13 -> 373814
C19: BL | D19: =D13+D17-D18 -> 237100

Sheet Che-Store
A1: Mercator Medical (Thailand) LTD.
A2: Stock Card Report By Location- Fin Year Based
A3: From 01-May-26 To 31-May-26 | F3: Costing method: WA | J3: TAX ID : | L3: 0905546002869
A5: Code | B5: Item | C5: UOM | D5: B/F | F5: Received Qty | G5: Received Amount | H5: Transfer from Inv Store P1 Qty | I5: Transfer from Inv Store P1 Amount | J5: Transfer from Inv Store P2 Qty | K5: Transfer from Inv Store P2 Amount | L5: Transfer from Inv Store P3 Qty | M5: Transfer from Inv Store P3 Amount | O5: Transfer from Comp P1 Qty | P5: Transfer from Comp P1 Amount | Q5: Transfer from Comp P2 Qty | R5: Transfer from Comp P2 Amount | S5: Transfer from Comp P3 Qty | T5: Transfer from Comp P3 Amount | U5: Transfer from Prod Store P1 Qty | V5: Transfer from Prod Store P1 Amount | W5: Transfer from Prod Store P2 Qty | X5: Transfer from Prod Store P2 Amount | Z5: Transfer from Prod Store P3 Qty | AA5: Transfer from Prod Store P3 Amount | AC5: Issued Qty | AD5: @ | AE5: Issued Amount | AF5: Transfer to Inv Store P1 Qty | AG5: Transfer to Inv Store P1 Amount | AH5: Transfer to Inv Store P2 Qty | AI5: Transfer to Inv Store P2 Amount | AJ5: Transfer to Inv Store P3 Qty | AK5: Transfer to Inv Store P3 Amount | AL5: Transfer to Comp P1 Qty | AN5: Transfer to Comp P1 Amount | AO5: Transfer to Comp P2 Qty | AP5: Transfer to Comp P2 Amount | AR5: Transfer to Comp P3 Qty | AS5: Transfer to Comp P3 Amount | AT5: Transfer to Prod Store P1 Qty | AU5: Transfer to Prod Store P1 Amount | AV5: Transfer to Prod Store P2 Qty | AW5: Transfer to Prod Store P2 Amount | AX5: Transfer to Prod Store P3 Qty | AY5: Transfer to Prod Store P3 Amount | AZ5: Adjustment Qty | BA5: Balance Qty | BB5: Balance Unit Cost | BC5: Balance Amount | BD5: Category
A6: Inv Store - Plant 1 | D6: Qty | E6: Amount
A7: CH145 | B7: BIO-F20 (25KG/PACK) - TNG (BIOCIDE) | C7: Kg | D7: 100 | E7: 13483.19 | F7: 100 | G7: 13709.36 | H7: 0 | I7: 0 | J7: 0 | K7: 0 | L7: 0 | M7: 0 | O7: 0 | P7: 0 | Q7: 0 | R7: 0 | S7: 0 | T7: 0 | U7: 0 | V7: 0 | W7: 0 | X7: 0 | Z7: 0 | AA7: 0 | AC7: 0 | AE7: 0 | AF7: 0 | AG7: 0 | AH7: 0 | AI7: 0 | AJ7: 0 | AK7: 0 | AL7: 75 | AN7: 10112.49 | AO7: 0 | AP7: 0 | AR7: 0 | AS7: 0 | AT7: 0 | AU7: 0 | AV7: 0 | AW7: 0 | AX7: 0 | AY7: 0 | AZ7: 0 | BA7: 125 | BB7: 136.64048 | BC7: 17080.06 | BD7: CHEMICAL
A8: CH196 | B8: TEXKLEEN P22 (225KG/DRUM)(ALKALINE CLEANER ) | C8: Kg | D8: 0 | E8: 0 | F8: 0 | G8: 0 | H8: 0 | I8: 0 | J8: 4500 | K8: 47250 | L8: 0 | M8: 0 | O8: 0 | P8: 0 | Q8: 0 | R8: 0 | S8: 0 | T8: 0 | U8: 0 | V8: 0 | W8: 0 | X8: 0 | Z8: 0 | AA8: 0 | AC8: 4500 | AD8: =+AE8/AC8 -> 10.5 | AE8: 47250 | AF8: 0 | AG8: 0 | AH8: 0 | AI8: 0 | AJ8: 0 | AK8: 0 | AL8: 0 | AN8: 0 | AO8: 0 | AP8: 0 | AR8: 0 | AS8: 0 | AT8: 0 | AU8: 0 | AV8: 0 | AW8: 0 | AX8: 0 | AY8: 0 | AZ8: 0 | BA8: 0 | BB8: 0 | BC8: 0 | BD8: CHEMICAL
A9: CH23 | B9: AMMONIUM HYDROXIDE (180KGS /DRUM)(900KG/IBC) | C9: Kg | D9: 1494 | E9: 24210 | F9: 0 | G9: 0 | H9: 0 | I9: 0 | J9: 0 | K9: 0 | L9: 0 | M9: 0 | O9: 0 | P9: 0 | Q9: 0 | R9: 0 | S9: 0 | T9: 0 | U9: 0 | V9: 0 | W9: 0 | X9: 0 | Z9: 0 | AA9: 0 | AC9: 0 | AE9: 0 | AF9: 0 | AG9: 0 | AH9: 0 | AI9: 0 | AJ9: 0 | AK9: 0 | AL9: 432 | AN9: 6952.5 | AO9: 0 | AP9: 0 | AR9: 0 | AS9: 0 | AT9: 0 | AU9: 0 | AV9: 0 | AW9: 0 | AX9: 0 | AY9: 0 | AZ9: 0 | BA9: 1062 | BB9: 16.25 | BC9: 17257.5 | BD9: CHEMICAL
A10: CH233 | B10: MAXSILK B280M(1000KG/IBC) - NBR POLYMER | C10: Kg | D10: 17000 | E10: 1074284.1 | F10: 19000 | G10: 1290101.9 | H10: 0 | I10: 0 | J10: 0 | K10: 0 | L10: 0 | M10: 0 | O10: 0 | P10: 0 | Q10: 0 | R10: 0 | S10: 0 | T10: 0 | U10: 0 | V10: 0 | W10: 0 | X10: 0 | Z10: 0 | AA10: 0 | AC10: 0 | AE10: 0 | AF10: 0 | AG10: 0 | AH10: 0 | AI10: 0 | AJ10: 0 | AK10: 0 | AL10: 12000 | AN10: 757195.4 | AO10: 0 | AP10: 0 | AR10: 0 | AS10: 0 | AT10: 0 | AU10: 0 | AV10: 0 | AW10: 0 | AX10: 0 | AY10: 0 | AZ10: 0 | BA10: 24000 | BB10: 66.966275 | BC10: 1607190.6 | BD10: CHEMICAL
A11: CH245 | B11: (TEST) SPECLEAN 10 (230KG/DRUM) - ALKALINE CLEANER | C11: Kg | D11: 0 | E11: 0 | F11: 0 | G11: 0 | H11: 0 | I11: 0 | J11: 8280 | K11: 79290.56 | L11: 0 | M11: 0 | O11: 0 | P11: 0 | Q11: 0 | R11: 0 | S11: 0 | T11: 0 | U11: 0 | V11: 0 | W11: 0 | X11: 0 | Z11: 0 | AA11: 0 | AC11: 8280 | AD11: =+AE11/AC11 -> 9.5761546 | AE11: 79290.56 | AF11: 0 | AG11: 0 | AH11: 0 | AI11: 0 | AJ11: 0 | AK11: 0 | AL11: 0 | AN11: 0 | AO11: 0 | AP11: 0 | AR11: 0 | AS11: 0 | AT11: 0 | AU11: 0 | AV11: 0 | AW11: 0 | AX11: 0 | AY11: 0 | AZ11: 0 | BA11: 0 | BB11: 0 | BC11: 0 | BD11: CHEMICAL
A12: CH252 | B12: (TEST) KLEEN S21 (225KG/DRUM) (ALAKLINE CLEANNER) | C12: Kg | D12: 0 | E12: 0 | F12: 0 | G12: 0 | H12: 0 | I12: 0 | J12: 900 | K12: 8550 | L12: 0 | M12: 0 | O12: 0 | P12: 0 | Q12: 0 | R12: 0 | S12: 0 | T12: 0 | U12: 0 | V12: 0 | W12: 0 | X12: 0 | Z12: 0 | AA12: 0 | AC12: 900 | AD12: =+AE12/AC12 -> 9.5 | AE12: 8550 | AF12: 0 | AG12: 0 | AH12: 0 | AI12: 0 | AJ12: 0 | AK12: 0 | AL12: 0 | AN12: 0 | AO12: 0 | AP12: 0 | AR12: 0 | AS12: 0 | AT12: 0 | AU12: 0 | AV12: 0 | AW12: 0 | AX12: 0 | AY12: 0 | AZ12: 0 | BA12: 0 | BB12: 0 | BC12: 0 | BD12: CHEMICAL
A13: CH26 | B13: NITRIC ACID 68% (280 KGS/DRUM ) | C13: Kg | D13: 0 | E13: 0 | F13: 0 | G13: 0 | H13: 0 | I13: 0 | J13: 3360 | K13: 52080 | L13: 0 | M13: 0 | O13: 0 | P13: 0 | Q13: 0 | R13: 0 | S13: 0 | T13: 0 | U13: 0 | V13: 0 | W13: 0 | X13: 0 | Z13: 0 | AA13: 0 | AC13: 3360 | AD13: =+AE13/AC13 -> 15.5 | AE13: 52080 | AF13: 0 | AG13: 0 | AH13: 0 | AI13: 0 | AJ13: 0 | AK13: 0 | AL13: 0 | AN13: 0 | AO13: 0 | AP13: 0 | AR13: 0 | AS13: 0 | AT13: 0 | AU13: 0 | AV13: 0 | AW13: 0 | AX13: 0 | AY13: 0 | AZ13: 0 | BA13: 0 | BB13: 0 | BC13: 0 | BD13: CHEMICAL
B14: Total | D14: =SUM(D7:D13) -> 18594 | E14: =SUM(E7:E13) -> 1111977.3 | F14: =SUM(F7:F13) -> 19100 | G14: =SUM(G7:G13) -> 1303811.3 | J14: =SUM(J7:J13) -> 17040 | K14: =SUM(K7:K13) -> 187170.56 | L14: =SUM(L7:L13) -> 0 | M14: =SUM(M7:M13) -> 0 | N14: =SUM(N7:N13) -> 0 | O14: =SUM(O7:O13) -> 0 | P14: =SUM(P7:P13) -> 0 | Q14: =SUM(Q7:Q13) -> 0 | ... AC14: =SUM(AC7:AC13) -> 17040 | AE14: =SUM(AE7:AE13) -> 187170.56 | AF14: =SUM(AF7:AF13) -> 0 | AG14: =SUM(AG7:AG13) -> 0 | AH14: =SUM(AH7:AH13) -> 0 | AI14: =SUM(AI7:AI13) -> 0 | AJ14: =SUM(AJ7:AJ13) -> 0 | AK14: =SUM(AK7:AK13) -> 0 | AL14: =SUM(AL7:AL13) -> 12507 | ... BA14: =SUM(BA7:BA13) -> 25187 | BC14: =SUM(BC7:BC13) -> 1641528.2
C16: check | D16: 18594 | E16: 1111977.3 | G16: ='1008-402'!F38 -> 1303811.2 | BA16: =+D14+F14+J14-AC14-AH14-AJ14-AL14+L14 -> 25187 | BC16: =+E14+G14+K14-AE14-AI14-AK14-AN14+M14 -> 1641528.2
G17: =+G14-G16 -> 0.09

Sheet Che-Comp
A1: Mercator Medical (Thailand) LTD.
A2: Stock Card Report By Location- Fin Year Based
A3: From 01-May-26 To 31-May-26 | F3: Costing method: WA | J3: TAX ID : | L3: 0905546002869
A5: Code | B5: Item | C5: UOM | D5: B/F | F5: Received Qty | G5: Received Amount | H5: Transfer from Inv Store P1 Qty | I5: Transfer from Inv Store P1 Amount | J5: Transfer from Inv Store P2 Qty | K5: Transfer from Inv Store P2 Amount | L5: Transfer from Inv Store P3 Qty | M5: Transfer from Inv Store P3 Amount | O5: Transfer from Comp P1 Qty | P5: Transfer from Comp P1 Amount | Q5: Transfer from Comp P2 Qty | R5: Transfer from Comp P2 Amount | S5: Transfer from Comp P3 Qty | T5: Transfer from Comp P3 Amount | U5: Transfer from Prod Store P1 Qty | V5: Transfer from Prod Store P1 Amount | W5: Transfer from Prod Store P2 Qty | X5: Transfer from Prod Store P2 Amount | Z5: Transfer from Prod Store P3 Qty | AA5: Transfer from Prod Store P3 Amount | AC5: Issued Qty | AE5: Issued Amount | AF5: Transfer to Inv Store P1 Qty | AG5: Transfer to Inv Store P1 Amount | AH5: Transfer to Inv Store P2 Qty | AI5: Transfer to Inv Store P2 Amount | AJ5: Transfer to Inv Store P3 Qty | AK5: Transfer to Inv Store P3 Amount | AL5: Transfer to Comp P1 Qty | AN5: Transfer to Comp P1 Amount | AO5: Transfer to Comp P2 Qty | AP5: Transfer to Comp P2 Amount | AR5: Transfer to Comp P3 Qty | AS5: Transfer to Comp P3 Amount | AT5: Transfer to Prod Store P1 Qty | AU5: Transfer to Prod Store P1 Amount | AV5: Transfer to Prod Store P2 Qty | AW5: Transfer to Prod Store P2 Amount | AX5: Transfer to Prod Store P3 Qty | AY5: Transfer to Prod Store P3 Amount | AZ5: Adjustment Qty | BA5: Balance Qty | BB5: Balance Unit Cost | BC5: Balance Amount | BD5: Category
A6: Compound store - Plant 1 | D6: QTY | E6: Amount
A7: CH106 | B7: OCTOSOL 643 (1000KG/IBC)(SDBS) | C7: Kg | D7: 0 | E7: 0 | F7: 0 | G7: 0 | H7: 0 | I7: 0 | J7: 1000 | K7: 32574.8 | L7: 0 | M7: 0 | O7: 0 | P7: 0 | Q7: 0 | R7: 0 | S7: 0 | T7: 0 | U7: 0 | V7: 0 | W7: 0 | X7: 0 | Z7: 0 | AA7: 0 | AC7: 20.15 | AD7: =+AE7/AC7 -> 32.57469 | AE7: 656.38 | AF7: 0 | AG7: 0 | AH7: 0 | AI7: 0 | AJ7: 0 | AK7: 0 | AL7: 0 | AN7: 0 | AO7: 0 | AP7: 0 | AR7: 0 | AS7: 0 | AT7: 0 | AU7: 0 | AV7: 0 | AW7: 0 | AX7: 0 | AY7: 0 | AZ7: 0 | BA7: 979.85 | BB7: 32.574802 | BC7: 31918.42 | BD7: CHEMICAL
A8: CH128 | B8: FARSPERSE BLUE MPL1523 (20 KGS/PAIL) (PIGMENT) | C8: Kg | D8: 126.35 | E8: 27335.85 | F8: 0 | G8: 0 | H8: 0 | I8: 0 | J8: 0 | K8: 0 | L8: 0 | M8: 0 | O8: 0 | P8: 0 | Q8: 0 | R8: 0 | S8: 0 | T8: 0 | U8: 0 | V8: 0 | W8: 0 | X8: 0 | Z8: 0 | AA8: 0 | AC8: 77.74 | AD8: =+AE8/AC8 -> 216.34127 | AE8: 16818.37 | AF8: 0 | AG8: 0 | AH8: 0 | AI8: 0 | AJ8: 0 | AK8: 0 | AL8: 0 | AN8: 0 | AO8: 48.61 | AP8: 10517.49 | AR8: 0 | AS8: 0 | AT8: 0 | AU8: 0 | AV8: 0 | AW8: 0 | AX8: 0 | AY8: 0 | AZ8: 0 | BA8: 0 | BB8: 0 | BC8: 0 | BD8: CHEMICAL
A9: CH140 | B9: HYDROTINT BLACK BA (20KG/PK) PIGMENT | C9: Kg | D9: 240 | E9: 13880.94 | F9: 0 | G9: 0 | H9: 0 | I9: 0 | J9: 2200 | K9: 128490.39 | L9: 0 | M9: 0 | O9: 0 | P9: 0 | Q9: 100 | R9: 5748.23 | S9: 0 | T9: 0 | U9: 0 | V9: 0 | W9: 0 | X9: 0 | Z9: 0 | AA9: 0 | AC9: 2090 | AD9: =+AE9/AC9 -> 57.918555 | AE9: 121049.78 | AF9: 0 | AG9: 0 | AH9: 0 | AI9: 0 | AJ9: 0 | AK9: 0 | AL9: 0 | AN9: 0 | AO9: 0 | AP9: 0 | AR9: 0 | AS9: 0 | AT9: 0 | AU9: 0 | AV9: 0 | AW9: 0 | AX9: 0 | AY9: 0 | AZ9: 0 | BA9: 450 | BB9: 60.154799 | BC9: 27069.78 | BD9: CHEMICAL
A10: CH145 | B10: BIO-F20 (25KG/PACK) - TNG (BIOCIDE) | C10: Kg | D10: 80 | E10: 10784.77 | F10: 5.8 | G10: 781.78 | H10: 75 | I10: 10112.49 | J10: 0 | K10: 0 | L10: 0 | M10: 0 | O10: 0 | P10: 0 | Q10: 0 | R10: 0 | S10: 0 | T10: 0 | U10: 0 | V10: 0 | W10: 0 | X10: 0 | Z10: 0 | AA10: 0 | AC10: 108.8 | AD10: =+AE10/AC10 -> 134.83382 | AE10: 14669.92 | AF10: 0 | AG10: 0 | AH10: 0 | AI10: 0 | AJ10: 0 | AK10: 0 | AL10: 0 | AN10: 0 | AO10: 0 | AP10: 0 | AR10: 0 | AS10: 0 | AT10: 0 | AU10: 0 | AV10: 0 | AW10: 0 | AX10: 0 | AY10: 0 | AZ10: 0 | BA10: 52 | BB10: 134.79077 | BC10: 7009.12 | BD10: CHEMICAL
A11: CH168 | B11: ALPHALINK 30 (ACELERATOR FREE CROSSLINKER) (1100KG/IBC) | C11: Kg | D11: 0 | E11: 0 | F11: 0 | G11: 0 | H11: 0 | I11: 0 | J11: 3300 | K11: 192734.85 | L11: 0 | M11: 0 | O11: 0 | P11: 0 | Q11: 0 | R11: 0 | S11: 0 | T11: 0 | U11: 0 | V11: 0 | W11: 0 | X11: 0 | Z11: 0 | AA11: 0 | AC11: 1170.96 | AD11: =+AE11/AC11 -> 58.404506 | AE11: 68389.34 | AF11: 0 | AG11: 0 | AH11: 0 | AI11: 0 | AJ11: 0 | AK11: 0 | AL11: 0 | AN11: 0 | AO11: 1100 | AP11: 64244.95 | AR11: 0 | AS11: 0 | AT11: 0 | AU11: 0 | AV11: 0 | AW11: 0 | AX11: 0 | AY11: 0 | AZ11: 0 | BA11: 1029.04 | BB11: 58.404494 | BC11: 60100.56 | BD11: CHEMICAL
A12: CH211 | B12: CALCIUM NITRATE TETRAHYDRATE CRYSTAL ( CALCIUM SALT )(25KG/BG) | C12: Kg | D12: 9000 | E12: 74622.63 | F12: 0 | G12: 0 | H12: 0 | I12: 0 | J12: 112500 | K12: 948304.5 | L12: 0 | M12: 0 | O12: 0 | P12: 0 | Q12: 0 | R12: 0 | S12: 0 | T12: 0 | U12: 0 | V12: 0 | W12: 0 | X12: 0 | Z12: 0 | AA12: 0 | AC12: 120040 | AD12: =+AE12/AC12 -> 8.4181774 | AE12: 1010518 | AF12: 0 | AG12: 0 | AH12: 0 | AI12: 0 | AJ12: 0 | AK12: 0 | AL12: 0 | AN12: 0 | AO12: 0 | AP12: 0 | AR12: 0 | AS12: 0 | AT12: 0 | AU12: 0 | AV12: 0 | AW12: 0 | AX12: 0 | AY12: 0 | AZ12: 0 | BA12: 1460 | BB12: 8.4994032 | BC12: 12409.11 | BD12: CHEMICAL
A13: CH212 | B13: POTASSIUM HYDROXIDE FLAKE 90% ( KOH ) ( 25 KGS / BAG )MOQ20000KG/TRIP | C13: Kg | D13: 800 | E13: 28000.04 | F13: 0 | G13: 0 | H13: 0 | I13: 0 | J13: 2100 | K13: 59916.78 | L13: 0 | M13: 0 | O13: 0 | P13: 0 | Q13: 0 | R13: 0 | S13: 0 | T13: 0 | U13: 0 | V13: 0 | W13: 0 | X13: 0 | Z13: 0 | AA13: 0 | AC13: 2400 | AD13: =+AE13/AC13 -> 32.035421 | AE13: 76885.01 | AF13: 0 | AG13: 0 | AH13: 0 | AI13: 0 | AJ13: 0 | AK13: 0 | AL13: 0 | AN13: 0 | AO13: 0 | AP13: 0 | AR13: 0 | AS13: 0 | AT13: 0 | AU13: 0 | AV13: 0 | AW13: 0 | AX13: 0 | AY13: 0 | AZ13: 0 | BA13: 500 | BB13: 22.06351 | BC13: 11031.81 | BD13: CHEMICAL
A14: CH215 | B14: ACUMIN H65 (1600KG/IBC) - EXTENDER | C14: Kg | D14: 7661 | E14: 158257.73 | F14: 0 | G14: 0 | H14: 0 | I14: 0 | J14: 17600 | K14: 365680.64 | L14: 0 | M14: 0 | O14: 0 | P14: 0 | Q14: 0 | R14: 0 | S14: 0 | T14: 0 | U14: 0 | V14: 0 | W14: 0 | X14: 0 | Z14: 0 | AA14: 0 | AC14: 21250 | AD14: =+AE14/AC14 -> 20.738312 | AE14: 440689.13 | AF14: 0 | AG14: 0 | AH14: 0 | AI14: 0 | AJ14: 0 | AK14: 0 | AL14: 0 | AN14: 0 | AO14: 0 | AP14: 0 | AR14: 0 | AS14: 0 | AT14: 0 | AU14: 0 | AV14: 0 | AW14: 0 | AX14: 0 | AY14: 0 | AZ14: 0 | BA14: 4011 | BB14: 20.755189 | BC14: 83249.16 | BD14: CHEMICAL
A15: CH222 | B15: AQUAWAX 022S (950KG/IBC) -WAX | C15: Kg | D15: 1471 | E15: 59113.39 | F15: 0 | G15: 0 | H15: 0 | I15: 0 | J15: 2850 | K15: 125729.46 | L15: 0 | M15: 0 | O15: 0 | P15: 0 | Q15: 0 | R15: 0 | S15: 0 | T15: 0 | U15: 0 | V15: 0 | W15: 0 | X15: 0 | Z15: 0 | AA15: 0 | AC15: 3259 | AD15: =+AE15/AC15 -> 42.341881 | AE15: 137992.19 | AF15: 0 | AG15: 0 | AH15: 0 | AI15: 0 | AJ15: 0 | AK15: 0 | AL15: 0 | AN15: 0 | AO15: 0 | AP15: 0 | AR15: 0 | AS15: 0 | AT15: 0 | AU15: 0 | AV15: 0 | AW15: 0 | AX15: 0 | AY15: 0 | AZ15: 0 | BA15: 1062 | BB15: 44.115499 | BC15: 46850.66 | BD15: CHEMICAL
A16: CH227 | B16: NEOPELEX G-15P (1000KG/IBC) (SDBS) | C16: Kg | D16: 1054.28 | E16: 14759.8 | F16: 0 | G16: 0 | H16: 0 | I16: 0 | J16: 0 | K16: 0 | L16: 1000 | M16: 14000 | O16: 0 | P16: 0 | Q16: 601.2 | R16: 8517.1 | S16: 0 | T16: 0 | U16: 0 | V16: 0 | W16: 0 | X16: 0 | Z16: 0 | AA16: 0 | AC16: 1855.48 | AD16: =+AE16/AC16 -> 14.05404 | AE16: 26076.99 | AF16: 0 | AG16: 0 | AH16: 0 | AI16: 0 | AJ16: 0 | AK16: 0 | AL16: 0 | AN16: 0 | AO16: 800 | AP16: 11200 | AR16: 0 | AS16: 0 | AT16: 0 | AU16: 0 | AV16: 0 | AW16: 0 | AX16: 0 | AY16: 0 | AZ16: 0 | BA16: 0 | BB16: 0 | BC16: 0 | BD16: CHEMICAL
A17: CH23 | B17: AMMONIUM HYDROXIDE (180KGS /DRUM)(900KG/IBC) | C17: Kg | D17: 108 | E17: 1619.36 | F17: 0 | G17: 0 | H17: 432 | I17: 6952.5 | J17: 0 | K17: 0 | L17: 0 | M17: 0 | O17: 0 | P17: 0 | Q17: 0 | R17: 0 | S17: 0 | T17: 0 | U17: 0 | V17: 0 | W17: 0 | X17: 0 | Z17: 0 | AA17: 0 | AC17: 492.8 | AD17: =+AE17/AC17 -> 15.839083 | AE17: 7805.5 | AF17: 0 | AG17: 0 | AH17: 0 | AI17: 0 | AJ17: 0 | AK17: 0 | AL17: 0 | AN17: 0 | AO17: 0 | AP17: 0 | AR17: 0 | AS17: 0 | AT17: 0 | AU17: 0 | AV17: 0 | AW17: 0 | AX17: 0 | AY17: 0 | AZ17: 0 | BA17: 47.2 | BB17: 16.236269 | BC17: 766.36 | BD17: CHEMICAL
A18: CH233 | B18: MAXSILK B280M(1000KG/IBC) - NBR POLYMER | C18: Kg | D18: 2000 | E18: 123017.93 | F18: 0 | G18: 0 | H18: 12000 | I18: 757195 | J18: 0 | K18: 0 | L18: 0 | M18: 0 | O18: 0 | P18: 0 | Q18: 0 | R18: 0 | S18: 0 | T18: 0 | U18: 0 | V18: 0 | W18: 0 | X18: 0 | Z18: 0 | AA18: 0 | AC18: 12494.7 | AD18: =+AE18/AC18 -> 62.807468 | AE18: 784760.47 | AF18: 0 | AG18: 0 | AH18: 0 | AI18: 0 | AJ18: 0 | AK18: 0 | AL18: 0 | AN18: 0 | AO18: 0 | AP18: 0 | AR18: 0 | AS18: 0 | AT18: 0 | AU18: 0 | AV18: 0 | AW18: 0 | AX18: 0 | AY18: 0 | AZ18: 0 | BA18: 1505.3 | BB18: 63.410921 | BC18: 95452.46 | BD18: CHEMICAL
... A20: CH240 | B20: ALPHALINK 50 (200KG/DRUM),(1100KG/IBC) - ACELERATOR FREE CROSSLINKER | C20: Kg | D20: 767 | E20: 59550.23 | F20: 0 | G20: 0 | H20: 0 | I20: 0 | J20: 1100 | K20: 88234.3 | L20: 0 | M20: 0 | O20: 0 | P20: 0 | Q20: 0 | R20: 0 | S20: 0 | T20: 0 | U20: 0 | V20: 0 | W20: 0 | X20: 0 | Z20: 0 | AA20: 0 | AC20: 407.34 | AD20: =+AE20/AC20 -> 77.639859 | AE20: 31625.82 | AF20: 0 | AG20: 0 | AH20: 0 | AI20: 0 | AJ20: 0 | AK20: 0 | AL20: 0 | AN20: 0 | AO20: 1459.66 | AP20: 116158.75 | AR20: 0 | AS20: 0 | AT20: 0 | AU20: 0 | AV20: 0 | AW20: 0 | AX20: 0 | AY20: 0 | AZ20: 0 | BA20: 0 | BB20: 0 | BC20: 0 | BD20: CHEMICAL
A21: CH249 | B21: (TEST) SULPHUR 60% 1200 KGS/IBC | C21: Kg | D21: 0 | E21: 0 | F21: 0 | G21: 0 | H21: 0 | I21: 0 | J21: 0 | K21: 0 | L21: 0 | M21: 0 | O21: 0 | P21: 0 | Q21: 0 | R21: 0 | S21: 0 | T21: 0 | U21: 0 | V21: 0 | W21: 0 | X21: 0 | Z21: 0 | AA21: 0 | AC21: 0 | AE21: 0 | AF21: 0 | AG21: 0 | AH21: 0 | AI21: 0 | AJ21: 0 | AK21: 0 | AL21: 0 | AN21: 0 | AO21: 0 | AP21: 0 | AR21: 0 | AS21: 0 | AT21: 0 | AU21: 0 | AV21: 0 | AW21: 0 | AX21: 0 | AY21: 0 | AZ21: 0 | BA21: 0 | BB21: 20 | BC21: 0.08 | BD21: CHEMICAL
A22: CH88 | B22: SURFYNOL DF 37 (DEFORMER) 20KGS./DRUM | C22: Kg | D22: 13 | E22: 7280.02 | F22: 0 | G22: 0 | H22: 0 | I22: 0 | J22: 0 | K22: 0 | L22: 0 | M22: 0 | O22: 0 | P22: 0 | Q22: 0 | R22: 0 | S22: 0 | T22: 0 | U22: 0 | V22: 0 | W22: 0 | X22: 0 | Z22: 0 | AA22: 0 | AC22: 0 | AE22: 0 | AF22: 0 | AG22: 0 | AH22: 0 | AI22: 0 | AJ22: 0 | AK22: 0 | AL22: 0 | AN22: 0 | AO22: 0 | AP22: 0 | AR22: 0 | AS22: 0 | AT22: 0 | AU22: 0 | AV22: 0 | AW22: 0 | AX22: 0 | AY22: 0 | AZ22: 0 | BA22: 13 | BB22: 560.00154 | BC22: 7280.02 | BD22: CHEMICAL
A23: CH91 | B23: ZDBC 50% 225 KGS/DRUM | C23: Kg | D23: 286.5 | E23: 13877.33 | F23: 0 | G23: 0 | H23: 0 | I23: 0 | J23: 900 | K23: 47379.69 | L23: 0 | M23: 0 | O23: 0 | P23: 0 | Q23: 400 | R23: 19722.72 | S23: 0 | T23: 0 | U23: 0 | V23: 0 | W23: 0 | X23: 0 | Z23: 0 | AA23: 0 | AC23: 1090.7 | AD23: =+AE23/AC23 -> 50.317319 | AE23: 54881.1 | AF23: 0 | AG23: 0 | AH23: 0 | AI23: 0 | AJ23: 0 | AK23: 0 | AL23: 0 | AN23: 0 | AO23: 0 | AP23: 0 | AR23: 0 | AS23: 0 | AT23: 0 | AU23: 0 | AV23: 0 | AW23: 0 | AX23: 0 | AY23: 0 | AZ23: 0 | BA23: 495.8 | BB23: 52.639802 | BC23: 26098.64 | BD23: CHEMICAL
A24: CH92 | B24: SULPHUR 60% 250 KGS/DRUM | C24: Kg | D24: 903.29 | E24: 25097.81 | F24: 0 | G24: 0 | H24: 0 | I24: 0 | J24: 2000 | K24: 60426.4 | L24: 0 | M24: 0 | O24: 0 | P24: 0 | Q24: 0 | R24: 0 | S24: 0 | T24: 0 | U24: 0 | V24: 0 | W24: 0 | X24: 0 | Z24: 0 | AA24: 0 | AC24: 1781.29 | AD24: =+AE24/AC24 -> 28.016028 | AE24: 49904.67 | AF24: 0 | AG24: 0 | AH24: 0 | AI24: 0 | AJ24: 0 | AK24: 0 | AL24: 0 | AN24: 0 | AO24: 0 | AP24: 0 | AR24: 0 | AS24: 0 | AT24: 0 | AU24: 0 | AV24: 0 | AW24: 0 | AX24: 0 | AY24: 0 | AZ24: 0 | BA24: 1122 | BB24: 31.746471 | BC24: 35619.54 | BD24: CHEMICAL
A25: CH93 | B25: ZINC OXIDE 60% (ZNO) 250 KGS/DRUM | C25: Kg | D25: 1062 | E25: 73286.82 | F25: 0 | G25: 0 | H25: 0 | I25: 0 | J25: 2000 | K25: 142859.9 | L25: 0 | M25: 0 | O25: 0 | P25: 0 | Q25: 0 | R25: 0 | S25: 0 | T25: 0 | U25: 0 | V25: 0 | W25: 0 | X25: 0 | Z25: 0 | AA25: 0 | AC25: 2259 | AD25: =+AE25/AC25 -> 69.839849 | AE25: 157768.22 | AF25: 0 | AG25: 0 | AH25: 0 | AI25: 0 | AJ25: 0 | AK25: 0 | AL25: 0 | AN25: 0 | AO25: 0 | AP25: 0 | AR25: 0 | AS25: 0 | AT25: 0 | AU25: 0 | AV25: 0 | AW25: 0 | AX25: 0 | AY25: 0 | AZ25: 0 | BA25: 803 | BB25: 72.700833 | BC25: 58378.5 | BD25: CHEMICAL
A26: CH94 | B26: TIO2 70% (TITANIUM DIOXIDE) 250 KGS/DRUM | C26: Kg | D26: 1618.39 | E26: 86203.52 | F26: 0 | G26: 0 | H26: 0 | I26: 0 | J26: 0 | K26: 0 | L26: 0 | M26: 0 | O26: 0 | P26: 0 | Q26: 0 | R26: 0 | S26: 0 | T26: 0 | U26: 0 | V26: 0 | W26: 0 | X26: 0 | Z26: 0 | AA26: 0 | AC26: 720.84 | AD26: =+AE26/AC26 -> 52.941651 | AE26: 38162.46 | AF26: 0 | AG26: 0 | AH26: 0 | AI26: 0 | AJ26: 0 | AK26: 0 | AL26: 0 | AN26: 0 | AO26: 897.55 | AP26: 48041.05 | AR26: 0 | AS26: 0 | AT26: 0 | AU26: 0 | AV26: 0 | AW26: 0 | AX26: 0 | AY26: 0 | AZ26: 0 | BA26: 0 | BB26: 0 | BC26: 0 | BD26: CHEMICAL
B30: Total | D30: =SUM(D7:D29) -> 28730.81 | E30: =SUM(E7:E29) -> 855624.92 | F30: =SUM(F7:F29) -> 5.8 | G30: =SUM(G7:G29) -> 781.78 | H30: =SUM(H7:H29) -> 12507 | I30: =SUM(I7:I29) -> 774259.99 | J30: =SUM(J7:J29) -> 149550 | K30: =SUM(K7:K29) -> 2296974.4 | ... AC30: =SUM(AC7:AC29) -> 174648.8 | AE30: =SUM(AE7:AE29) -> 3200898.4 | AF30: =SUM(AF7:AF29) -> 0 | AG30: =SUM(AG7:AG29) -> 0 | AH30: =SUM(AH7:AH29) -> 0 | AI30: =SUM(AI7:AI29) -> 0 | AJ30: =SUM(AJ7:AJ29) -> 0 | AK30: =SUM(AK7:AK29) -> 0 | AL30: =SUM(AL7:AL29) -> 0 | ... BA30: =SUM(BA7:BA29) -> 13940.19 | BC30: =SUM(BC7:BC29) -> 524568.67
C32: check | D32: 28730.81 | E32: 855624.92 | BA32: =+D30+F30+H30+J30+L30+Q30+S30-AC30-AO30 -> 13940.19 | BC32: =+E30+G30+I30+K30+M30+R30-AE30-AP30-AS30+T30+0.13 -> 524568.67
BA34: =+BA30-BA32 -> 1.8189894e-11 | BC34: =+BC30-BC32 -> 0

Sheet Che.-Prod
A1: Mercator Medical (Thailand) LTD.
A2: Stock Card Report By Location
A3: From 01-May-26 To 31-May-26 | G3: Costing method: WA | L3: TAX ID : | M3: 0905546002869
A5: Code | B5: Item | C5: UOM | D5: Balance | G5: Received | I5: Transfer from other plant | K5: Issued | M5: Transfer to other plant | O5: Adjustment | P5: Balance
D6: Qty | E6: Unit Cost | F6: Amount | G6: Qty | H6: Amount | I6: Qty | J6: Amount | K6: Qty | L6: Amount | M6: Qty | N6: Amount | O6: Qty | P6: Qty | Q6: Unit Cost | R6: Amount
A7: Production - Plant 1
A9: CH104 | B9: SPECLEAN 11 (246 KGS /DRUM) | C9: Kg | F9: 0 | R9: =P9*Q9 -> 0
A10: CH111 | B10: ALKALINE CLEAN S4 (1100 KG/TANK) | C10: Kg | F10: 0 | R10: =P10*Q10 -> 0
A11: CH196 | B11: TEXKLEEN P22 (225KG/DRUM)(ALKALINE CLEANER ) | C11: Kg | D11: 1800 | E11: 10.5 | F11: 18900 | P11: 450 | Q11: 10.5 | R11: =P11*Q11 -> 4725
A12: CH26 | B12: NITRIC ACID 68% (280 KGS/DRUM ) | C12: Kg | D12: 1960 | E12: 13 | F12: 25480 | P12: 1120 | Q12: 13 | R12: =P12*Q12 -> 14560
A13: CH23 | B13: AMMONIUM HYDROXIDE 180KGS /DRUM | C13: Kg | D13: 720 | E13: 16.2 | F13: 11664 | P13: 720 | Q13: 16.2 | R13: =P13*Q13 -> 11664
A14: CH209 | B14: (TEST) SPECLEAN8 (240KG/DRUM) - ALKALINE CLEANER | C14: Kg | E14: 15.5 | F14: 0 | Q14: =SUMIF('Che-Store'!A10:A15,'Che.-Prod'!A12,'Che-Store'!AD10:AD15) -> 15.5 | R14: =P14*Q14 -> 0
A15: CH252 | B15: (TEST) KLEEN S21 (225KG/DRUM) (ALAKLINE CLEANNER) | C15: Kg | D15: 1125 | E15: 10.35 | F15: 11643.75 | Q15: 10.35 | R15: =P15*Q15 -> 0
A16: CH245 | B16: (TEST) SPECLEAN 10 (230KG/DRUM) - ALKALINE CLEANER | C16: Kg | P16: 1150 | Q16: 9.58 | R16: =P16*Q16 -> 11017
D18: 5605 | F18: 67687.75 | I18: 0 | J18: 0 | K18: 0 | L18: 0 | P18: =SUM(P9:P17) -> 3440 | R18: =SUM(R9:R17) -> 41966
C20: checked | D20: 5605 | F20: 67687.75 | P20: =P18 -> 3440 | R20: =R18 -> 41966

Sheet BalCom
C1: Balance Compound latex
C3: Name | D3: Master name | E3: Item Name | F3: Code | G3: TSC | H3: Dry Kg | I3: Balance (Kg) | J3: Column1 | K3: Total Dry Kg | L3: Bal. Kg Dry | M3: Bal. Kg Wet | N3: New Code | O3: Price | P3: Cost (Baht) | Q3: **Check**
A4: =IF(LEFT(BalCom[[#This Row],[Code]],3)="NBR","NBR","CHE") -> NBR | C4: _BalCom | D4: PLANT#1 FINGER TEXTURE BLACK 6.0G WITH BST8503S+NEOPELEX+15PHR MRC+AQUAWAX NITRILE COMPOUND | E4: NBR01 - SYNTHETIC LATEX BST NBL 8503S | F4: NBR01 | G4: 0.4496 | H4: 1818 | I4: 2183.692 | K4: =SUMIFS(H:H,C:C,BalCom[[#This Row],[Name]],D:D,BalCom[[#This Row],[Master name]]) -> 2201.598 | L4: =IFERROR(BalCom[[#This Row],[Balance (Kg)]]*BalCom[[#This Row],[Dry Kg]]/BalCom[[#This Row],[Total Dry Kg]],0) -> 1803.2139 | M4: =IF(D4="","",BalCom[[#This Row],[Bal. Kg Dry]]/BalCom[[#This Row],[TSC]]) -> 4010.707 | N4: =IF(_xlfn.XLOOKUP(BalCom[[#This Row],[Code]],Info!B:B,Info!D:D,0)=0,BalCom[[#This Row],[Code]],(_xlfn.XLOOKUP(BalCom[[#This Row],[Code]],Info!B:B,Info!D:D,0))) -> NBR01 | O4: =IF(BalCom[[#This Row],[New Code]]="SFG-Water",0,_xlfn.XLOOKUP(BalCom[[#This Row],[New Code]],Used_before_Trf!A:A,Used_before_Trf!U:U,"")) -> 50.516914 | P4: =IF(D4="","",ROUND((BalCom[[#This Row],[Price]]*BalCom[[#This Row],[Bal. Kg Wet]]),2)) -> 202608.54 | Q4: =IF(BalCom[[#This Row],[Master name]]="","",IF(N4="SFG-Water","",IF(AND(N4<>0,P4<>0),"Ok","Error"))) -> Ok
A5: =IF(LEFT(BalCom[[#This Row],[Code]],3)="NBR","NBR","CHE") -> CHE | C5: _BalCom | D5: PLANT#1 FINGER TEXTURE BLACK 6.0G WITH BST8503S+NEOPELEX+15PHR MRC+AQUAWAX NITRILE COMPOUND | E5: CH148 - KOH 48% SOLUTION (1500KG/IBC) (TC GROUP) (POTASSIUM HYDROXIDE) | F5: CH212 | G5: 0.03 | H5: 1.8699312 | I5: 2183.692 | K5: =SUMIFS(H:H,C:C,BalCom[[#This Row],[Name]],D:D,BalCom[[#This Row],[Master name]]) -> 2201.598 | L5: =IFERROR(BalCom[[#This Row],[Balance (Kg)]]*BalCom[[#This Row],[Dry Kg]]/BalCom[[#This Row],[Total Dry Kg]],0) -> 1.8547227 | M5: =IF(D5="","",BalCom[[#This Row],[Bal. Kg Dry]]/BalCom[[#This Row],[TSC]]) -> 61.824089 | N5: =IF(_xlfn.XLOOKUP(BalCom[[#This Row],[Code]],Info!B:B,Info!D:D,0)=0,BalCom[[#This Row],[Code]],(_xlfn.XLOOKUP(BalCom[[#This Row],[Code]],Info!B:B,Info!D:D,0))) -> CH212 | O5: =IF(BalCom[[#This Row],[New Code]]="SFG-Water",0,_xlfn.XLOOKUP(BalCom[[#This Row],[New Code]],Used_before_Trf!A:A,Used_before_Trf!U:U,"")) -> 32.035421 | P5: =IF(D5="","",ROUND((BalCom[[#This Row],[Price]]*BalCom[[#This Row],[Bal. Kg Wet]]),2)) -> 1980.56 | Q5: =IF(BalCom[[#This Row],[Master name]]="","",IF(N5="SFG-Water","",IF(AND(N5<>0,P5<>0),"Ok","Error"))) -> Ok
A6: =IF(LEFT(BalCom[[#This Row],[Code]],3)="NBR","NBR","CHE") -> CHE | C6: _BalCom | D6: PLANT#1 FINGER TEXTURE BLACK 6.0G WITH BST8503S+NEOPELEX+15PHR MRC+AQUAWAX NITRILE COMPOUND | E6: SFG-Water - WATER FOR COMPOUND ONLY | F6: SFG-Water | G6: 0.03 | H6: 25.400069 | I6: 2183.692 | K6: =SUMIFS(H:H,C:C,BalCom[[#This Row],[Name]],D:D,BalCom[[#This Row],[Master name]]) -> 2201.598 | L6: =IFERROR(BalCom[[#This Row],[Balance (Kg)]]*BalCom[[#This Row],[Dry Kg]]/BalCom[[#This Row],[Total Dry Kg]],0) -> 25.193485 | M6: =IF(D6="","",BalCom[[#This Row],[Bal. Kg Dry]]/BalCom[[#This Row],[TSC]]) -> 839.78285 | N6: =IF(_xlfn.XLOOKUP(BalCom[[#This Row],[Code]],Info!B:B,Info!D:D,0)=0,BalCom[[#This Row],[Code]],(_xlfn.XLOOKUP(BalCom[[#This Row],[Code]],Info!B:B,Info!D:D,0))) -> SFG-Water | O6: =IF(BalCom[[#This Row],[New Code]]="SFG-Water",0,_xlfn.XLOOKUP(BalCom[[#This Row],[New Code]],Used_before_Trf!A:A,Used_before_Trf!U:U,"")) -> 0 | P6: =IF(D6="","",ROUND((BalCom[[#This Row],[Price]]*BalCom[[#This Row],[Bal. Kg Wet]]),2)) -> 0 | Q6: =IF(BalCom[[#This Row],[Master name]]="","",IF(N6="SFG-Water","",IF(AND(N6<>0,P6<>0),"Ok","Error")))
A7: =IF(LEFT(BalCom[[#This Row],[Code]],3)="NBR","NBR","CHE") -> CHE | C7: _BalCom | D7: PLANT#1 FINGER TEXTURE BLACK 6.0G WITH BST8503S+NEOPELEX+15PHR MRC+AQUAWAX NITRILE COMPOUND | E7: CH227 - NEOPELEX G-15P (1000KG/IBC) (SDBS) | F7: CH227 | G7: 0.15 | H7: 3.636 | I7: 2183.692 | K7: =SUMIFS(H:H,C:C,BalCom[[#This Row],[Name]],D:D,BalCom[[#This Row],[Master name]]) -> 2201.598 | L7: =IFERROR(BalCom[[#This Row],[Balance (Kg)]]*BalCom[[#This Row],[Dry Kg]]/BalCom[[#This Row],[Total Dry Kg]],0) -> 3.6064277 | M7: =IF(D7="","",BalCom[[#This Row],[Bal. Kg Dry]]/BalCom[[#This Row],[TSC]]) -> 24.042852 | N7: =IF(_xlfn.XLOOKUP(BalCom[[#This Row],[Code]],Info!B:B,Info!D:D,0)=0,BalCom[[#This Row],[Code]],(_xlfn.XLOOKUP(BalCom[[#This Row],[Code]],Info!B:B,Info!D:D,0))) -> CH227 | O7: =IF(BalCom[[#This Row],[New Code]]="SFG-Water",0,_xlfn.XLOOKUP(BalCom[[#This Row],[New Code]],Used_before_Trf!A:A,Used_before_Trf!U:U,"")) -> 14.05404 | P7: =IF(D7="","",ROUND((BalCom[[#This Row],[Price]]*BalCom[[#This Row],[Bal. Kg Wet]]),2)) -> 337.9 | Q7: =IF(BalCom[[#This Row],[Master name]]="","",IF(N7="SFG-Water","",IF(AND(N7<>0,P7<>0),"Ok","Error"))) -> Ok
A8: =IF(LEFT(BalCom[[#This Row],[Code]],3)="NBR","NBR","CHE") -> CHE | C8: _BalCom | D8: PLANT#1 FINGER TEXTURE BLACK 6.0G WITH BST8503S+NEOPELEX+15PHR MRC+AQUAWAX NITRILE COMPOUND | E8: CH93 - ZINC OXIDE 60% (ZNO) 250 KGS/DRUM | F8: CH93 | G8: 0.6 | H8: 14.544 | I8: 2183.692 | K8: =SUMIFS(H:H,C:C,BalCom[[#This Row],[Name]],D:D,BalCom[[#This Row],[Master name]]) -> 2201.598 | L8: =IFERROR(BalCom[[#This Row],[Balance (Kg)]]*BalCom[[#This Row],[Dry Kg]]/BalCom[[#This Row],[Total Dry Kg]],0) -> 14.425711 | M8: =IF(D8="","",BalCom[[#This Row],[Bal. Kg Dry]]/BalCom[[#This Row],[TSC]]) -> 24.042852 | N8: =IF(_xlfn.XLOOKUP(BalCom[[#This Row],[Code]],Info!B:B,Info!D:D,0)=0,BalCom[[#This Row],[Code]],(_xlfn.XLOOKUP(BalCom[[#This Row],[Code]],Info!B:B,Info!D:D,0))) -> CH93 | O8: =IF(BalCom[[#This Row],[New Code]]="SFG-Water",0,_xlfn.XLOOKUP(BalCom[[#This Row],[New Code]],Used_before_Trf!A:A,Used_before_Trf!U:U,"")) -> 69.839849 | P8: =IF(D8="","",ROUND((BalCom[[#This Row],[Price]]*BalCom[[#This Row],[Bal. Kg Wet]]),2)) -> 1679.15 | Q8: =IF(BalCom[[#This Row],[Master name]]="","",IF(N8="SFG-Water","",IF(AND(N8<>0,P8<>0),"Ok","Error"))) -> Ok
A9: =IF(LEFT(BalCom[[#This Row],[Code]],3)="NBR","NBR","CHE") -> CHE | C9: _BalCom | D9: PLANT#1 FINGER TEXTURE BLACK 6.0G WITH BST8503S+NEOPELEX+15PHR MRC+AQUAWAX NITRILE COMPOUND | E9: CH92 - SULPHUR 60% 250 KGS/DRUM | F9: CH92 | G9: 0.6 | H9: 18.18 | I9: 2183.692 | K9: =SUMIFS(H:H,C:C,BalCom[[#This Row],[Name]],D:D,BalCom[[#This Row],[Master name]]) -> 2201.598 | L9: =IFERROR(BalCom[[#This Row],[Balance (Kg)]]*BalCom[[#This Row],[Dry Kg]]/BalCom[[#This Row],[Total Dry Kg]],0) -> 18.032139 | M9: =IF(D9="","",BalCom[[#This Row],[Bal. Kg Dry]]/BalCom[[#This Row],[TSC]]) -> 30.053565 | N9: =IF(_xlfn.XLOOKUP(BalCom[[#This Row],[Code]],Info!B:B,Info!D:D,0)=0,BalCom[[#This Row],[Code]],(_xlfn.XLOOKUP(BalCom[[#This Row],[Code]],Info!B:B,Info!D:D,0))) -> CH92 | O9: =IF(BalCom[[#This Row],[New Code]]="SFG-Water",0,_xlfn.XLOOKUP(BalCom[[#This Row],[New Code]],Used_before_Trf!A:A,Used_before_Trf!U:U,"")) -> 28.016028 | P9: =IF(D9="","",ROUND((BalCom[[#This Row],[Price]]*BalCom[[#This Row],[Bal. Kg Wet]]),2)) -> 841.98 | Q9: =IF(BalCom[[#This Row],[Master name]]="","",IF(N9="SFG-Water","",IF(AND(N9<>0,P9<>0),"Ok","Error"))) -> Ok
A10: =IF(LEFT(BalCom[[#This Row],[Code]],3)="NBR","NBR","CHE") -> CHE | C10: _BalCom | D10: PLANT#1 FINGER TEXTURE BLACK 6.0G WITH BST8503S+NEOPELEX+15PHR MRC+AQUAWAX NITRILE COMPOUND | E10: CH91 - ZDBC 50% 225 KGS/DRUM | F10: CH91 | G10: 0.5 | H10: 10.908 | I10: 2183.692 | K10: =SUMIFS(H:H,C:C,BalCom[[#This Row],[Name]],D:D,BalCom[[#This Row],[Master name]]) -> 2201.598 | L10: =IFERROR(BalCom[[#This Row],[Balance (Kg)]]*BalCom[[#This Row],[Dry Kg]]/BalCom[[#This Row],[Total Dry Kg]],0) -> 10.819283 | M10: =IF(D10="","",BalCom[[#This Row],[Bal. Kg Dry]]/BalCom[[#This Row],[TSC]]) -> 21.638566 | N10: =IF(_xlfn.XLOOKUP(BalCom[[#This Row],[Code]],Info!B:B,Info!D:D,0)=0,BalCom[[#This Row],[Code]],(_xlfn.XLOOKUP(BalCom[[#This Row],[Code]],Info!B:B,Info!D:D,0))) -> CH91 | O10: =IF(BalCom[[#This Row],[New Code]]="SFG-Water",0,_xlfn.XLOOKUP(BalCom[[#This Row],[New Code]],Used_before_Trf!A:A,Used_before_Trf!U:U,"")) -> 50.317319 | P10: =IF(D10="","",ROUND((BalCom[[#This Row],[Price]]*BalCom[[#This Row],[Bal. Kg Wet]]),2)) -> 1088.79 | Q10: =IF(BalCom[[#This Row],[Master name]]="","",IF(N10="SFG-Water","",IF(AND(N10<>0,P10<>0),"Ok","Error"))) -> Ok
A11: =IF(LEFT(BalCom[[#This Row],[Code]],3)="NBR","NBR","CHE") -> CHE | C11: _BalCom | D11: PLANT#1 FINGER TEXTURE BLACK 6.0G WITH BST8503S+NEOPELEX+15PHR MRC+AQUAWAX NITRILE COMPOUND | E11: CH229 - MRC600NB50(1400KG/IBC) MOQ: 22,400KG EXTENDER | F11: CH229 | G11: 0.45 | H11: 272.7 | I11: 2183.692 | K11: =SUMIFS(H:H,C:C,BalCom[[#This Row],[Name]],D:D,BalCom[[#This Row],[Master name]]) -> 2201.598 | L11: =IFERROR(BalCom[[#This Row],[Balance (Kg)]]*BalCom[[#This Row],[Dry Kg]]/BalCom[[#This Row],[Total Dry Kg]],0) -> 270.48208 | M11: =IF(D11="","",BalCom[[#This Row],[Bal. Kg Dry]]/BalCom[[#This Row],[TSC]]) -> 601.07129 | N11: =IF(_xlfn.XLOOKUP(BalCom[[#This Row],[Code]],Info!B:B,Info!D:D,0)=0,BalCom[[#This Row],[Code]],(_xlfn.XLOOKUP(BalCom[[#This Row],[Code]],Info!B:B,Info!D:D,0))) -> CH229 | O11: =IF(BalCom[[#This Row],[New Code]]="SFG-Water",0,_xlfn.XLOOKUP(BalCom[[#This Row],[New Code]],Used_before_Trf!A:A,Used_before_Trf!U:U,"")) -> 13.07 | P11: =IF(D11="","",ROUND((BalCom[[#This Row],[Price]]*BalCom[[#This Row],[Bal. Kg Wet]]),2)) -> 7856 | Q11: =IF(BalCom[[#This Row],[Master name]]="","",IF(N11="SFG-Water","",IF(AND(N11<>0,P11<>0),"Ok","Error"))) -> Ok
A12: =IF(LEFT(BalCom[[#This Row],[Code]],3)="NBR","NBR","CHE") -> CHE | C12: _BalCom | D12: PLANT#1 FINGER TEXTURE BLACK 6.0G WITH BST8503S+NEOPELEX+15PHR MRC+AQUAWAX NITRILE COMPOUND | E12: CH222 - AQUAWAX 022S (950KG/IBC) -WAX | F12: CH222 | G12: 0.55 | H12: 18.18 | I12: 2183.692 | K12: =SUMIFS(H:H,C:C,BalCom[[#This Row],[Name]],D:D,BalCom[[#This Row],[Master name]]) -> 2201.598 | L12: =IFERROR(BalCom[[#This Row],[Balance (Kg)]]*BalCom[[#This Row],[Dry Kg]]/BalCom[[#This Row],[Total Dry Kg]],0) -> 18.032139 | M12: =IF(D12="","",BalCom[[#This Row],[Bal. Kg Dry]]/BalCom[[#This Row],[TSC]]) -> 32.785707 | N12: =IF(_xlfn.XLOOKUP(BalCom[[#This Row],[Code]],Info!B:B,Info!D:D,0)=0,BalCom[[#This Row],[Code]],(_xlfn.XLOOKUP(BalCom[[#This Row],[Code]],Info!B:B,Info!D:D,0))) -> CH222 | O12: =IF(BalCom[[#This Row],[New Code]]="SFG-Water",0,_xlfn.XLOOKUP(BalCom[[#This Row],[New Code]],Used_before_Trf!A:A,Used_before_Trf!U:U,"")) -> 42.341881 | P12: =IF(D12="","",ROUND((BalCom[[#This Row],[Price]]*BalCom[[#This Row],[Bal. Kg Wet]]),2)) -> 1388.21 | Q12: =IF(BalCom[[#This Row],[Master name]]="","",IF(N12="SFG-Water","",IF(AND(N12<>0,P12<>0),"Ok","Error"))) -> Ok
A13: =IF(LEFT(BalCom[[#This Row],[Code]],3)="NBR","NBR","CHE") -> CHE | C13: _BalCom | D13: PLANT#1 FINGER TEXTURE BLACK 6.0G WITH BST8503S+NEOPELEX+15PHR MRC+AQUAWAX NITRILE COMPOUND | E13: CH199 - FARSPERSE BLACK PB-ZBX SF (20 KGS/PAIL) (PIGMENT SILICONE FREE) | F13: CH140 | G13: 0.5 | H13: 18.18 | I13: 2183.692 | K13: =SUMIFS(H:H,C:C,BalCom[[#This Row],[Name]],D:D,BalCom[[#This Row],[Master name]]) -> 2201.598 | L13: =IFERROR(BalCom[[#This Row],[Balance (Kg)]]*BalCom[[#This Row],[Dry Kg]]/BalCom[[#This Row],[Total Dry Kg]],0) -> 18.032139 | M13: =IF(D13="","",BalCom[[#This Row],[Bal. Kg Dry]]/BalCom[[#This Row],[TSC]]) -> 36.064277 | N13: =IF(_xlfn.XLOOKUP(BalCom[[#This Row],[Code]],Info!B:B,Info!D:D,0)=0,BalCom[[#This Row],[Code]],(_xlfn.XLOOKUP(BalCom[[#This Row],[Code]],Info!B:B,Info!D:D,0))) -> CH140 | O13: =IF(BalCom[[#This Row],[New Code]]="SFG-Water",0,_xlfn.XLOOKUP(BalCom[[#This Row],[New Code]],Used_before_Trf!A:A,Used_before_Trf!U:U,"")) -> 57.918555 | P13: =IF(D13="","",ROUND((BalCom[[#This Row],[Price]]*BalCom[[#This Row],[Bal. Kg Wet]]),2)) -> 2088.79 | Q13: =IF(BalCom[[#This Row],[Master name]]="","",IF(N13="SFG-Water","",IF(AND(N13<>0,P13<>0),"Ok","Error"))) -> Ok
A14: =IF(LEFT(BalCom[[#This Row],[Code]],3)="NBR","NBR","CHE") -> NBR | C14: _BalCom | D14: PLANT#1 FINGER TEXTURE BLACK 6.0G WITH BST8503S+NEOPELEX+15PHR MRC NITRILE COMPOUND-DIP2 | E14: NBR01 - SYNTHETIC LATEX BST NBL 8503S | F14: NBR01 | G14: 0.4496 | H14: 1827 | I14: 2027.936 | K14: =SUMIFS(H:H,C:C,BalCom[[#This Row],[Name]],D:D,BalCom[[#This Row],[Master name]]) -> 2199.708 | L14: =IFERROR(BalCom[[#This Row],[Balance (Kg)]]*BalCom[[#This Row],[Dry Kg]]/BalCom[[#This Row],[Total Dry Kg]],0) -> 1684.3322 | M14: =IF(D14="","",BalCom[[#This Row],[Bal. Kg Dry]]/BalCom[[#This Row],[TSC]]) -> 3746.2905 | N14: =IF(_xlfn.XLOOKUP(BalCom[[#This Row],[Code]],Info!B:B,Info!D:D,0)=0,BalCom[[#This Row],[Code]],(_xlfn.XLOOKUP(BalCom[[#This Row],[Code]],Info!B:B,Info!D:D,0))) -> NBR01 | O14: =IF(BalCom[[#This Row],[New Code]]="SFG-Water",0,_xlfn.XLOOKUP(BalCom[[#This Row],[New Code]],Used_before_Trf!A:A,Used_before_Trf!U:U,"")) -> 50.516914 | P14: =IF(D14="","",ROUND((BalCom[[#This Row],[Price]]*BalCom[[#This Row],[Bal. Kg Wet]]),2)) -> 189251.04 | Q14: =IF(BalCom[[#This Row],[Master name]]="","",IF(N14="SFG-Water","",IF(AND(N14<>0,P14<>0),"Ok","Error"))) -> Ok
A15: =IF(LEFT(BalCom[[#This Row],[Code]],3)="NBR","NBR","CHE") -> CHE | C15: _BalCom | D15: PLANT#1 FINGER TEXTURE BLACK 6.0G WITH BST8503S+NEOPELEX+15PHR MRC NITRILE COMPOUND-DIP2 | E15: CH148 - KOH 48% SOLUTION (1500KG/IBC) (TC GROUP) (POTASSIUM HYDROXIDE) | F15: CH212 | G15: 0.03 | H15: 2.1297467 | I15: 2027.936 | K15: =SUMIFS(H:H,C:C,BalCom[[#This Row],[Name]],D:D,BalCom[[#This Row],[Master name]]) -> 2199.708 | L15: =IFERROR(BalCom[[#This Row],[Balance (Kg)]]*BalCom[[#This Row],[Dry Kg]]/BalCom[[#This Row],[Total Dry Kg]],0) -> 1.9634379 | M15: =IF(D15="","",BalCom[[#This Row],[Bal. Kg Dry]]/BalCom[[#This Row],[TSC]]) -> 65.447929 | N15: =IF(_xlfn.XLOOKUP(BalCom[[#This Row],[Code]],Info!B:B,Info!D:D,0)=0,BalCom[[#This Row],[Code]],(_xlfn.XLOOKUP(BalCom[[#This Row],[Code]],Info!B:B,Info!D:D,0))) -> CH212 | O15: =IF(BalCom[[#This Row],[New Code]]="SFG-Water",0,_xlfn.XLOOKUP(BalCom[[#This Row],[New Code]],Used_before_Trf!A:A,Used_before_Trf!U:U,"")) -> 32.035421 | P15: =IF(D15="","",ROUND((BalCom[[#This Row],[Price]]*BalCom[[#This Row],[Bal. Kg Wet]]),2)) -> 2096.65 | Q15: =IF(BalCom[[#This Row],[Master name]]="","",IF(N15="SFG-Water","",IF(AND(N15<>0,P15<>0),"Ok","Error"))) -> Ok
... A149: =IF(LEFT(BalCom[[#This Row],[Code]],3)="NBR","NBR","CHE") -> CHE | C149: _BalCom | D149: PLANT#3 FINGER TEXTURE VIOLET BLUE 3.5G WITH BST8503S+OCTOSOL+ALPHALINK30 COMPOUND-DIP2 | E149: CH96 - 47% FARSPERSE VIOLET PV-RLS 20 KGS/PAIL (PIGMENT) | F149: CH96 | G149: 0.47 | H149: 0.5203 | I149: 575.6268 | K149: =SUMIFS(H:H,C:C,BalCom[[#This Row],[Name]],D:D,BalCom[[#This Row],[Master name]]) -> 1195.7261 | L149: =IFERROR(BalCom[[#This Row],[Balance (Kg)]]*BalCom[[#This Row],[Dry Kg]]/BalCom[[#This Row],[Total Dry Kg]],0) -> 0.25047427 | M149: =IF(D149="","",BalCom[[#This Row],[Bal. Kg Dry]]/BalCom[[#This Row],[TSC]]) -> 0.53292398 | N149: =IF(_xlfn.XLOOKUP(BalCom[[#This Row],[Code]],Info!B:B,Info!D:D,0)=0,BalCom[[#This Row],[Code]],(_xlfn.XLOOKUP(BalCom[[#This Row],[Code]],Info!B:B,Info!D:D,0))) -> CH96 | O149: =IF(BalCom[[#This Row],[New Code]]="SFG-Water",0,_xlfn.XLOOKUP(BalCom[[#This Row],[New Code]],Used_before_Trf!A:A,Used_before_Trf!U:U,"")) -> 871.79 | P149: =IF(D149="","",ROUND((BalCom[[#This Row],[Price]]*BalCom[[#This Row],[Bal. Kg Wet]]),2)) -> 464.6 | Q149: =IF(BalCom[[#This Row],[Master name]]="","",IF(N149="SFG-Water","",IF(AND(N149<>0,P149<>0),"Ok","Error"))) -> Ok
C150: Total | K150: =SUBTOTAL(109,BalCom[Total Dry Kg]) -> 273132.91 | M150: =SUBTOTAL(109,BalCom[Bal. Kg Wet]) -> 57950.384 | P150: =SUBTOTAL(109,BalCom[Cost (Baht)]) -> 2100027.3

Sheet BalDis
A1: Balance Dispersion
A3: Name | B3: Master Name | C3: Item Name | D3: Code | E3: Kg | F3: Balance (Kg) | G3: Column1 | H3: Total Kg Dry | I3: Bal. Kg | J3: New Code | K3: Price | L3: Cost (Baht) | M3: **check**
A4: _BalDis | B4: COAGULANT PLANT#1 FINGER TEXTURE BLACK 6.0G GLOVES WITH MAXCO-SUPPLY BATCH | C4: SFG-Water - WATER FOR COMPOUND ONLY | D4: SFG-Water | E4: 1254 | F4: 1820 | H4: =SUMIFS(E:E,A:A,A4,B:B,B4) -> 1500 | I4: =IFERROR(BalDis[[#This Row],[Balance (Kg)]]*BalDis[[#This Row],[Kg]]/BalDis[[#This Row],[Total Kg Dry]],0) -> 1521.52 | J4: =IF(_xlfn.XLOOKUP(D4,Info!B:B,Info!D:D,0)=0,BalDis[[#This Row],[Code]],_xlfn.XLOOKUP(D4,Info!B:B,Info!D:D,0)) -> SFG-Water | K4: =_xlfn.XLOOKUP(BalDis[[#This Row],[New Code]],Used_before_Trf!A:A,Used_before_Trf!U:U,0) -> 0 | L4: =ROUND(BalDis[[#This Row],[Price]]*BalDis[[#This Row],[Bal. Kg]],2) -> 0 | M4: =IF(B4="","",IF(J4="SFG-Water","",IF(AND(J4<>0,L4<>0),"Ok","Error")))
A5: _BalDis | B5: COAGULANT PLANT#1 FINGER TEXTURE BLACK 6.0G GLOVES WITH MAXCO-SUPPLY BATCH | C5: CH45 - CALCIUM NITRATE, SOLUTION 54-55% (310/DRUM),(30,000KG/TANK) | D5: CH211 | E5: 225 | F5: 1820 | H5: =SUMIFS(E:E,A:A,A5,B:B,B5) -> 1500 | I5: =IFERROR(BalDis[[#This Row],[Balance (Kg)]]*BalDis[[#This Row],[Kg]]/BalDis[[#This Row],[Total Kg Dry]],0) -> 273 | J5: =IF(_xlfn.XLOOKUP(D5,Info!B:B,Info!D:D,0)=0,BalDis[[#This Row],[Code]],_xlfn.XLOOKUP(D5,Info!B:B,Info!D:D,0)) -> CH211 | K5: =_xlfn.XLOOKUP(BalDis[[#This Row],[New Code]],Used_before_Trf!A:A,Used_before_Trf!U:U,0) -> 8.4181774 | L5: =ROUND(BalDis[[#This Row],[Price]]*BalDis[[#This Row],[Bal. Kg]],2) -> 2298.16 | M5: =IF(B5="","",IF(J5="SFG-Water","",IF(AND(J5<>0,L5<>0),"Ok","Error"))) -> Ok
A6: _BalDis | B6: COAGULANT PLANT#1 FINGER TEXTURE BLACK 6.0G GLOVES WITH MAXCO-SUPPLY BATCH | C6: CH235 - MAXCO B3108M (1000KG/IBC) - ANTI TACK | D6: CH235 | E6: 21 | F6: 1820 | H6: =SUMIFS(E:E,A:A,A6,B:B,B6) -> 1500 | I6: =IFERROR(BalDis[[#This Row],[Balance (Kg)]]*BalDis[[#This Row],[Kg]]/BalDis[[#This Row],[Total Kg Dry]],0) -> 25.48 | J6: =IF(_xlfn.XLOOKUP(D6,Info!B:B,Info!D:D,0)=0,BalDis[[#This Row],[Code]],_xlfn.XLOOKUP(D6,Info!B:B,Info!D:D,0)) -> CH235 | K6: =_xlfn.XLOOKUP(BalDis[[#This Row],[New Code]],Used_before_Trf!A:A,Used_before_Trf!U:U,0) -> 51.835463 | L6: =ROUND(BalDis[[#This Row],[Price]]*BalDis[[#This Row],[Bal. Kg]],2) -> 1320.77 | M6: =IF(B6="","",IF(J6="SFG-Water","",IF(AND(J6<>0,L6<>0),"Ok","Error"))) -> Ok
A7: _BalDis | B7: COAGULANT PLANT#1 PALM&FINGER TEXTURE BLACK 5.5G GLOVES WITH MAXCO-SUPPLY BATCH | C7: SFG-Water - WATER FOR COMPOUND ONLY | D7: SFG-Water | E7: 3735 | F7: 2296 | H7: =SUMIFS(E:E,A:A,A7,B:B,B7) -> 5000 | I7: =IFERROR(BalDis[[#This Row],[Balance (Kg)]]*BalDis[[#This Row],[Kg]]/BalDis[[#This Row],[Total Kg Dry]],0) -> 1715.112 | J7: =IF(_xlfn.XLOOKUP(D7,Info!B:B,Info!D:D,0)=0,BalDis[[#This Row],[Code]],_xlfn.XLOOKUP(D7,Info!B:B,Info!D:D,0)) -> SFG-Water | K7: =_xlfn.XLOOKUP(BalDis[[#This Row],[New Code]],Used_before_Trf!A:A,Used_before_Trf!U:U,0) -> 0 | L7: =ROUND(BalDis[[#This Row],[Price]]*BalDis[[#This Row],[Bal. Kg]],2) -> 0 | M7: =IF(B7="","",IF(J7="SFG-Water","",IF(AND(J7<>0,L7<>0),"Ok","Error")))
A8: _BalDis | B8: COAGULANT PLANT#1 PALM&FINGER TEXTURE BLACK 5.5G GLOVES WITH MAXCO-SUPPLY BATCH | C8: CH45 - CALCIUM NITRATE, SOLUTION 54-55% (310/DRUM),(30,000KG/TANK) | D8: CH211 | E8: 1159 | F8: 2296 | H8: =SUMIFS(E:E,A:A,A8,B:B,B8) -> 5000 | I8: =IFERROR(BalDis[[#This Row],[Balance (Kg)]]*BalDis[[#This Row],[Kg]]/BalDis[[#This Row],[Total Kg Dry]],0) -> 532.2128 | J8: =IF(_xlfn.XLOOKUP(D8,Info!B:B,Info!D:D,0)=0,BalDis[[#This Row],[Code]],_xlfn.XLOOKUP(D8,Info!B:B,Info!D:D,0)) -> CH211 | K8: =_xlfn.XLOOKUP(BalDis[[#This Row],[New Code]],Used_before_Trf!A:A,Used_before_Trf!U:U,0) -> 8.4181774 | L8: =ROUND(BalDis[[#This Row],[Price]]*BalDis[[#This Row],[Bal. Kg]],2) -> 4480.26 | M8: =IF(B8="","",IF(J8="SFG-Water","",IF(AND(J8<>0,L8<>0),"Ok","Error"))) -> Ok
A9: _BalDis | B9: COAGULANT PLANT#1 PALM&FINGER TEXTURE BLACK 5.5G GLOVES WITH MAXCO-SUPPLY BATCH | C9: CH235 - MAXCO B3108M (1000KG/IBC) - ANTI TACK | D9: CH235 | E9: 106 | F9: 2296 | H9: =SUMIFS(E:E,A:A,A9,B:B,B9) -> 5000 | I9: =IFERROR(BalDis[[#This Row],[Balance (Kg)]]*BalDis[[#This Row],[Kg]]/BalDis[[#This Row],[Total Kg Dry]],0) -> 48.6752 | J9: =IF(_xlfn.XLOOKUP(D9,Info!B:B,Info!D:D,0)=0,BalDis[[#This Row],[Code]],_xlfn.XLOOKUP(D9,Info!B:B,Info!D:D,0)) -> CH235 | K9: =_xlfn.XLOOKUP(BalDis[[#This Row],[New Code]],Used_before_Trf!A:A,Used_before_Trf!U:U,0) -> 51.835463 | L9: =ROUND(BalDis[[#This Row],[Price]]*BalDis[[#This Row],[Bal. Kg]],2) -> 2523.1 | M9: =IF(B9="","",IF(J9="SFG-Water","",IF(AND(J9<>0,L9<>0),"Ok","Error"))) -> Ok
A10: _BalDis | B10: PLANT#1 KOH SOLUTION 90% TO 3% WITH SOLID KOH | C10: SFG-Water - WATER FOR COMPOUND ONLY | D10: SFG-Water | E10: 5800 | F10: 7873 | H10: =SUMIFS(E:E,A:A,A10,B:B,B10) -> 6000 | I10: =IFERROR(BalDis[[#This Row],[Balance (Kg)]]*BalDis[[#This Row],[Kg]]/BalDis[[#This Row],[Total Kg Dry]],0) -> 7610.5667 | J10: =IF(_xlfn.XLOOKUP(D10,Info!B:B,Info!D:D,0)=0,BalDis[[#This Row],[Code]],_xlfn.XLOOKUP(D10,Info!B:B,Info!D:D,0)) -> SFG-Water | K10: =_xlfn.XLOOKUP(BalDis[[#This Row],[New Code]],Used_before_Trf!A:A,Used_before_Trf!U:U,0) -> 0 | L10: =ROUND(BalDis[[#This Row],[Price]]*BalDis[[#This Row],[Bal. Kg]],2) -> 0 | M10: =IF(B10="","",IF(J10="SFG-Water","",IF(AND(J10<>0,L10<>0),"Ok","Error")))
A11: _BalDis | B11: PLANT#1 KOH SOLUTION 90% TO 3% WITH SOLID KOH | C11: CH212 - POTASSIUM HYDROXIDE FLAKE 90% ( KOH ) ( 25 KGS / BAG )MOQ20000KG/TRIP | D11: CH212 | E11: 200 | F11: 7873 | H11: =SUMIFS(E:E,A:A,A11,B:B,B11) -> 6000 | I11: =IFERROR(BalDis[[#This Row],[Balance (Kg)]]*BalDis[[#This Row],[Kg]]/BalDis[[#This Row],[Total Kg Dry]],0) -> 262.43333 | J11: =IF(_xlfn.XLOOKUP(D11,Info!B:B,Info!D:D,0)=0,BalDis[[#This Row],[Code]],_xlfn.XLOOKUP(D11,Info!B:B,Info!D:D,0)) -> CH212 | K11: =_xlfn.XLOOKUP(BalDis[[#This Row],[New Code]],Used_before_Trf!A:A,Used_before_Trf!U:U,0) -> 32.035421 | L11: =ROUND(BalDis[[#This Row],[Price]]*BalDis[[#This Row],[Bal. Kg]],2) -> 8407.16 | M11: =IF(B11="","",IF(J11="SFG-Water","",IF(AND(J11<>0,L11<>0),"Ok","Error"))) -> Ok
A12: _BalDis | B12: PLANT#1-55% CALCIUM NITRATE PREPARATION FROM 70%CRYSTAL | C12: CH211 - CALCIUM NITRATE TETRAHYDRATE CRYSTAL ( CALCIUM SALT )(25KG/BG) | D12: CH211 | E12: 4000 | F12: 42190 | H12: =SUMIFS(E:E,A:A,A12,B:B,B12) -> 5091 | I12: =IFERROR(BalDis[[#This Row],[Balance (Kg)]]*BalDis[[#This Row],[Kg]]/BalDis[[#This Row],[Total Kg Dry]],0) -> 33148.694 | J12: =IF(_xlfn.XLOOKUP(D12,Info!B:B,Info!D:D,0)=0,BalDis[[#This Row],[Code]],_xlfn.XLOOKUP(D12,Info!B:B,Info!D:D,0)) -> CH211 | K12: =_xlfn.XLOOKUP(BalDis[[#This Row],[New Code]],Used_before_Trf!A:A,Used_before_Trf!U:U,0) -> 8.4181774 | L12: =ROUND(BalDis[[#This Row],[Price]]*BalDis[[#This Row],[Bal. Kg]],2) -> 279051.59 | M12: =IF(B12="","",IF(J12="SFG-Water","",IF(AND(J12<>0,L12<>0),"Ok","Error"))) -> Ok
A13: _BalDis | B13: PLANT#1-55% CALCIUM NITRATE PREPARATION FROM 70%CRYSTAL | C13: SFG-Water - WATER FOR COMPOUND ONLY | D13: SFG-Water | E13: 1091 | F13: 42190 | H13: =SUMIFS(E:E,A:A,A13,B:B,B13) -> 5091 | I13: =IFERROR(BalDis[[#This Row],[Balance (Kg)]]*BalDis[[#This Row],[Kg]]/BalDis[[#This Row],[Total Kg Dry]],0) -> 9041.3062 | J13: =IF(_xlfn.XLOOKUP(D13,Info!B:B,Info!D:D,0)=0,BalDis[[#This Row],[Code]],_xlfn.XLOOKUP(D13,Info!B:B,Info!D:D,0)) -> SFG-Water | K13: =_xlfn.XLOOKUP(BalDis[[#This Row],[New Code]],Used_before_Trf!A:A,Used_before_Trf!U:U,0) -> 0 | L13: =ROUND(BalDis[[#This Row],[Price]]*BalDis[[#This Row],[Bal. Kg]],2) -> 0 | M13: =IF(B13="","",IF(J13="SFG-Water","",IF(AND(J13<>0,L13<>0),"Ok","Error")))
A14: _BalDis | B14: POLYMER PLANT#1 WITH MAXSIL B280M-R1 | C14: SFG-Water - WATER FOR COMPOUND ONLY | D14: SFG-Water | E14: 4495.04 | F14: 5992 | H14: =SUMIFS(E:E,A:A,A14,B:B,B14) -> 5000 | I14: =IFERROR(BalDis[[#This Row],[Balance (Kg)]]*BalDis[[#This Row],[Kg]]/BalDis[[#This Row],[Total Kg Dry]],0) -> 5386.8559 | J14: =IF(_xlfn.XLOOKUP(D14,Info!B:B,Info!D:D,0)=0,BalDis[[#This Row],[Code]],_xlfn.XLOOKUP(D14,Info!B:B,Info!D:D,0)) -> SFG-Water | K14: =_xlfn.XLOOKUP(BalDis[[#This Row],[New Code]],Used_before_Trf!A:A,Used_before_Trf!U:U,0) -> 0 | L14: =ROUND(BalDis[[#This Row],[Price]]*BalDis[[#This Row],[Bal. Kg]],2) -> 0 | M14: =IF(B14="","",IF(J14="SFG-Water","",IF(AND(J14<>0,L14<>0),"Ok","Error")))
A15: _BalDis | B15: POLYMER PLANT#1 WITH MAXSIL B280M-R1 | C15: CH233 - MAXSILK B280M(1000KG/IBC) - NBR POLYMER | D15: CH233 | E15: 487.5 | F15: 5992 | H15: =SUMIFS(E:E,A:A,A15,B:B,B15) -> 5000 | I15: =IFERROR(BalDis[[#This Row],[Balance (Kg)]]*BalDis[[#This Row],[Kg]]/BalDis[[#This Row],[Total Kg Dry]],0) -> 584.22 | J15: =IF(_xlfn.XLOOKUP(D15,Info!B:B,Info!D:D,0)=0,BalDis[[#This Row],[Code]],_xlfn.XLOOKUP(D15,Info!B:B,Info!D:D,0)) -> CH233 | K15: =_xlfn.XLOOKUP(BalDis[[#This Row],[New Code]],Used_before_Trf!A:A,Used_before_Trf!U:U,0) -> 62.807468 | L15: =ROUND(BalDis[[#This Row],[Price]]*BalDis[[#This Row],[Bal. Kg]],2) -> 36693.38 | M15: =IF(B15="","",IF(J15="SFG-Water","",IF(AND(J15<>0,L15<>0),"Ok","Error"))) -> Ok
... A17: _BalDis | B17: POLYMER PLANT#1 WITH MAXSIL B280M-R1 | C17: CH23 - AMMONIUM HYDROXIDE (180KGS /DRUM)(900KG/IBC) | D17: CH23 | E17: 13.46 | F17: 5992 | H17: =SUMIFS(E:E,A:A,A17,B:B,B17) -> 5000 | I17: =IFERROR(BalDis[[#This Row],[Balance (Kg)]]*BalDis[[#This Row],[Kg]]/BalDis[[#This Row],[Total Kg Dry]],0) -> 16.130464 | J17: =IF(_xlfn.XLOOKUP(D17,Info!B:B,Info!D:D,0)=0,BalDis[[#This Row],[Code]],_xlfn.XLOOKUP(D17,Info!B:B,Info!D:D,0)) -> CH23 | K17: =_xlfn.XLOOKUP(BalDis[[#This Row],[New Code]],Used_before_Trf!A:A,Used_before_Trf!U:U,0) -> 15.839083 | L17: =ROUND(BalDis[[#This Row],[Price]]*BalDis[[#This Row],[Bal. Kg]],2) -> 255.49 | M17: =IF(B17="","",IF(J17="SFG-Water","",IF(AND(J17<>0,L17<>0),"Ok","Error"))) -> Ok
A30: Total | I30: =SUBTOTAL(109,BalDis[Bal. Kg]) -> 60171 | L30: =SUBTOTAL(109,BalDis[Cost (Baht)]) -> 335676.26

Sheet BalDip
C1: Compound latex and Solution in Dipping lines
E3: Dipping line | F3: DF 1 | G3: DF 2 | H3: DF 3 | I3: DF 4 | N3: Balance (Kgs)
E4: Type of gloves | H4: BLACK 5.5 | I4: BLACK 6.0
E5: Formula of Compound latex | F5: BST+AF | G5: BST+AF | H5: Xing Yu-806+Neopelex+15Phr Acumin+Aquawax | I5: RFA-7632+Neopelex+15Phr Acumin+Aquawax
E6: Latex Compound (Wet) | H6: 8800 | I6: 8800 | N6: =SUM(F6:M6) -> 17600
E7: Latex Compound (Wet) (Buffer Tank) | H7: 0 | I7: 0 | N7: =SUM(F7:M7) -> 0
E8: TSC % | H8: =H9/(H6+H7) -> 0.21945 | I8: =I9/(I6+I7) -> 0.235 | N8: =N9/(N6+N7) -> 0.227225
E9: Latex Compound (Dry) | H9: 1931.16 | I9: 2068 | N9: =H9+I9 -> 3999.16
E10: Master name of compound latex | F10: Master name | G10: Master name | H10: PLANT#1 PALM&FINGER TEXTURE BLACK 5.5G WITH XY-806+NEOPELEX+15PHR ACUMIN H65+AQUAWAX NITRILE COMPOUND-DIP1 | I10: PLANT#1 FINGER TEXTURE BLACK 6.0G WITH RFA-7632+NEOPELEX+15PHR ACUMIN H65+AQUAWAX NITRILE COMPOUND-DIP1
C14: {=_xlfn.UNIQUE(BalCom!N:N)} -> 0 | E14: _BalCom | F14: Master formula
C15: New Code | D15: % TSC | E15: Description | F15: Dry Kg | G15: Dry Kg | H15: Dry Kg | I15: Dry Kg
C16: NBR01 | D16: =IF(C16="","",_xlfn.XLOOKUP(C16,BalCom!N:N,BalCom!G:G,0)) -> 0.4496 | E16: =IF(C16="","",_xlfn.XLOOKUP(C16,Used_before_Trf!A:A,Used_before_Trf!B:B,0)) -> SYNTHETIC LATEX BST NBL 8503S | F16: =SUMIFS(BalCom!$H:$H,BalCom!$D:$D,BalDip!F$10,BalCom!$N:$N,BalDip!$C16,BalCom!$C:$C,BalDip!$E$14) -> 0 | G16: =SUMIFS(BalCom!$H:$H,BalCom!$D:$D,BalDip!G$10,BalCom!$N:$N,BalDip!$C16,BalCom!$C:$C,BalDip!$E$14) -> 0 | H16: =SUMIFS(BalCom!$H:$H,BalCom!$D:$D,BalDip!H$10,BalCom!$N:$N,BalDip!$C16,BalCom!$C:$C,BalDip!$E$14) -> 0 | I16: =SUMIFS(BalCom!$H:$H,BalCom!$D:$D,BalDip!I$10,BalCom!$N:$N,BalDip!$C16,BalCom!$C:$C,BalDip!$E$14) -> 0
C17: CH212 | D17: =IF(C17="","",_xlfn.XLOOKUP(C17,BalCom!N:N,BalCom!G:G,0)) -> 0.03 | E17: =IF(C17="","",_xlfn.XLOOKUP(C17,Used_before_Trf!A:A,Used_before_Trf!B:B,0)) -> (TEST) POTASSIUM HYDROXIDE FLAKE 90% ( KOH ) ( 25 KGS / BAG ) | F17: =SUMIFS(BalCom!$H:$H,BalCom!$D:$D,BalDip!F$10,BalCom!$N:$N,BalDip!$C17,BalCom!$C:$C,BalDip!$E$14) -> 0 | G17: =SUMIFS(BalCom!$H:$H,BalCom!$D:$D,BalDip!G$10,BalCom!$N:$N,BalDip!$C17,BalCom!$C:$C,BalDip!$E$14) -> 0 | H17: =SUMIFS(BalCom!$H:$H,BalCom!$D:$D,BalDip!H$10,BalCom!$N:$N,BalDip!$C17,BalCom!$C:$C,BalDip!$E$14) -> 2.1131936 | I17: =SUMIFS(BalCom!$H:$H,BalCom!$D:$D,BalDip!I$10,BalCom!$N:$N,BalDip!$C17,BalCom!$C:$C,BalDip!$E$14) -> 1.8699312
C18: SFG-Water | D18: =IF(C18="","",_xlfn.XLOOKUP(C18,BalCom!N:N,BalCom!G:G,0)) -> 0.03 | E18: =IF(C18="","",_xlfn.XLOOKUP(C18,Used_before_Trf!A:A,Used_before_Trf!B:B,0)) -> Water | F18: =SUMIFS(BalCom!$H:$H,BalCom!$D:$D,BalDip!F$10,BalCom!$N:$N,BalDip!$C18,BalCom!$C:$C,BalDip!$E$14) -> 0 | G18: =SUMIFS(BalCom!$H:$H,BalCom!$D:$D,BalDip!G$10,BalCom!$N:$N,BalDip!$C18,BalCom!$C:$C,BalDip!$E$14) -> 0 | H18: =SUMIFS(BalCom!$H:$H,BalCom!$D:$D,BalDip!H$10,BalCom!$N:$N,BalDip!$C18,BalCom!$C:$C,BalDip!$E$14) -> 28.704406 | I18: =SUMIFS(BalCom!$H:$H,BalCom!$D:$D,BalDip!I$10,BalCom!$N:$N,BalDip!$C18,BalCom!$C:$C,BalDip!$E$14) -> 25.400069
C19: CH227 | D19: =IF(C19="","",_xlfn.XLOOKUP(C19,BalCom!N:N,BalCom!G:G,0)) -> 0.15 | E19: =IF(C19="","",_xlfn.XLOOKUP(C19,Used_before_Trf!A:A,Used_before_Trf!B:B,0)) -> (TEST) NEOPELEX G-15P (1000KG/IBC) (SDBS) | F19: =SUMIFS(BalCom!$H:$H,BalCom!$D:$D,BalDip!F$10,BalCom!$N:$N,BalDip!$C19,BalCom!$C:$C,BalDip!$E$14) -> 0 | G19: =SUMIFS(BalCom!$H:$H,BalCom!$D:$D,BalDip!G$10,BalCom!$N:$N,BalDip!$C19,BalCom!$C:$C,BalDip!$E$14) -> 0 | H19: =SUMIFS(BalCom!$H:$H,BalCom!$D:$D,BalDip!H$10,BalCom!$N:$N,BalDip!$C19,BalCom!$C:$C,BalDip!$E$14) -> 3.6256 | I19: =SUMIFS(BalCom!$H:$H,BalCom!$D:$D,BalDip!I$10,BalCom!$N:$N,BalDip!$C19,BalCom!$C:$C,BalDip!$E$14) -> 3.636
C20: CH93 | D20: =IF(C20="","",_xlfn.XLOOKUP(C20,BalCom!N:N,BalCom!G:G,0)) -> 0.6 | E20: =IF(C20="","",_xlfn.XLOOKUP(C20,Used_before_Trf!A:A,Used_before_Trf!B:B,0)) -> ZINC OXIDE 60% (ZNO) 250 KGS/DRUM | F20: =SUMIFS(BalCom!$H:$H,BalCom!$D:$D,BalDip!F$10,BalCom!$N:$N,BalDip!$C20,BalCom!$C:$C,BalDip!$E$14) -> 0 | G20: =SUMIFS(BalCom!$H:$H,BalCom!$D:$D,BalDip!G$10,BalCom!$N:$N,BalDip!$C20,BalCom!$C:$C,BalDip!$E$14) -> 0 | H20: =SUMIFS(BalCom!$H:$H,BalCom!$D:$D,BalDip!H$10,BalCom!$N:$N,BalDip!$C20,BalCom!$C:$C,BalDip!$E$14) -> 14.5024 | I20: =SUMIFS(BalCom!$H:$H,BalCom!$D:$D,BalDip!I$10,BalCom!$N:$N,BalDip!$C20,BalCom!$C:$C,BalDip!$E$14) -> 10.908
C21: CH92 | D21: =IF(C21="","",_xlfn.XLOOKUP(C21,BalCom!N:N,BalCom!G:G,0)) -> 0.6 | E21: =IF(C21="","",_xlfn.XLOOKUP(C21,Used_before_Trf!A:A,Used_before_Trf!B:B,0)) -> SULPHUR 60% 250 KGS/DRUM | F21: =SUMIFS(BalCom!$H:$H,BalCom!$D:$D,BalDip!F$10,BalCom!$N:$N,BalDip!$C21,BalCom!$C:$C,BalDip!$E$14) -> 0 | G21: =SUMIFS(BalCom!$H:$H,BalCom!$D:$D,BalDip!G$10,BalCom!$N:$N,BalDip!$C21,BalCom!$C:$C,BalDip!$E$14) -> 0 | H21: =SUMIFS(BalCom!$H:$H,BalCom!$D:$D,BalDip!H$10,BalCom!$N:$N,BalDip!$C21,BalCom!$C:$C,BalDip!$E$14) -> 18.128 | I21: =SUMIFS(BalCom!$H:$H,BalCom!$D:$D,BalDip!I$10,BalCom!$N:$N,BalDip!$C21,BalCom!$C:$C,BalDip!$E$14) -> 18.18
C22: CH91 | D22: =IF(C22="","",_xlfn.XLOOKUP(C22,BalCom!N:N,BalCom!G:G,0)) -> 0.5 | E22: =IF(C22="","",_xlfn.XLOOKUP(C22,Used_before_Trf!A:A,Used_before_Trf!B:B,0)) -> ZDBC 50% 225 KGS/DRUM | F22: =SUMIFS(BalCom!$H:$H,BalCom!$D:$D,BalDip!F$10,BalCom!$N:$N,BalDip!$C22,BalCom!$C:$C,BalDip!$E$14) -> 0 | G22: =SUMIFS(BalCom!$H:$H,BalCom!$D:$D,BalDip!G$10,BalCom!$N:$N,BalDip!$C22,BalCom!$C:$C,BalDip!$E$14) -> 0 | H22: =SUMIFS(BalCom!$H:$H,BalCom!$D:$D,BalDip!H$10,BalCom!$N:$N,BalDip!$C22,BalCom!$C:$C,BalDip!$E$14) -> 10.8768 | I22: =SUMIFS(BalCom!$H:$H,BalCom!$D:$D,BalDip!I$10,BalCom!$N:$N,BalDip!$C22,BalCom!$C:$C,BalDip!$E$14) -> 10.908
C23: CH229 | D23: =IF(C23="","",_xlfn.XLOOKUP(C23,BalCom!N:N,BalCom!G:G,0)) -> 0.45 | E23: =IF(C23="","",_xlfn.XLOOKUP(C23,Used_before_Trf!A:A,Used_before_Trf!B:B,0)) -> (TEST) MRC600NB50(1400KG/IBC) MOQ: 23,800KG EXTENDER | F23: =SUMIFS(BalCom!$H:$H,BalCom!$D:$D,BalDip!F$10,BalCom!$N:$N,BalDip!$C23,BalCom!$C:$C,BalDip!$E$14) -> 0 | G23: =SUMIFS(BalCom!$H:$H,BalCom!$D:$D,BalDip!G$10,BalCom!$N:$N,BalDip!$C23,BalCom!$C:$C,BalDip!$E$14) -> 0 | H23: =SUMIFS(BalCom!$H:$H,BalCom!$D:$D,BalDip!H$10,BalCom!$N:$N,BalDip!$C23,BalCom!$C:$C,BalDip!$E$14) -> 0 | I23: =SUMIFS(BalCom!$H:$H,BalCom!$D:$D,BalDip!I$10,BalCom!$N:$N,BalDip!$C23,BalCom!$C:$C,BalDip!$E$14) -> 0
C24: CH222 | D24: =IF(C24="","",_xlfn.XLOOKUP(C24,BalCom!N:N,BalCom!G:G,0)) -> 0.55 | E24: =IF(C24="","",_xlfn.XLOOKUP(C24,Used_before_Trf!A:A,Used_before_Trf!B:B,0)) -> AQUAWAX 022S (950KG/IBC) -WAX | F24: =SUMIFS(BalCom!$H:$H,BalCom!$D:$D,BalDip!F$10,BalCom!$N:$N,BalDip!$C24,BalCom!$C:$C,BalDip!$E$14) -> 0 | G24: =SUMIFS(BalCom!$H:$H,BalCom!$D:$D,BalDip!G$10,BalCom!$N:$N,BalDip!$C24,BalCom!$C:$C,BalDip!$E$14) -> 0 | H24: =SUMIFS(BalCom!$H:$H,BalCom!$D:$D,BalDip!H$10,BalCom!$N:$N,BalDip!$C24,BalCom!$C:$C,BalDip!$E$14) -> 18.128 | I24: =SUMIFS(BalCom!$H:$H,BalCom!$D:$D,BalDip!I$10,BalCom!$N:$N,BalDip!$C24,BalCom!$C:$C,BalDip!$E$14) -> 18.18
C25: CH140 | D25: =IF(C25="","",_xlfn.XLOOKUP(C25,BalCom!N:N,BalCom!G:G,0)) -> 0.5 | E25: =IF(C25="","",_xlfn.XLOOKUP(C25,Used_before_Trf!A:A,Used_before_Trf!B:B,0)) -> HYDROTINT BLACK BA (20KG/PK) PIGMENT | F25: =SUMIFS(BalCom!$H:$H,BalCom!$D:$D,BalDip!F$10,BalCom!$N:$N,BalDip!$C25,BalCom!$C:$C,BalDip!$E$14) -> 0 | G25: =SUMIFS(BalCom!$H:$H,BalCom!$D:$D,BalDip!G$10,BalCom!$N:$N,BalDip!$C25,BalCom!$C:$C,BalDip!$E$14) -> 0 | H25: =SUMIFS(BalCom!$H:$H,BalCom!$D:$D,BalDip!H$10,BalCom!$N:$N,BalDip!$C25,BalCom!$C:$C,BalDip!$E$14) -> 18.128 | I25: =SUMIFS(BalCom!$H:$H,BalCom!$D:$D,BalDip!I$10,BalCom!$N:$N,BalDip!$C25,BalCom!$C:$C,BalDip!$E$14) -> 18.18
C26: NBR31 | D26: =IF(C26="","",_xlfn.XLOOKUP(C26,BalCom!N:N,BalCom!G:G,0)) -> 0.4556 | E26: =IF(C26="","",_xlfn.XLOOKUP(C26,Used_before_Trf!A:A,Used_before_Trf!B:B,0)) -> (TEST) NBR LATEX, RFA-7632 | F26: =SUMIFS(BalCom!$H:$H,BalCom!$D:$D,BalDip!F$10,BalCom!$N:$N,BalDip!$C26,BalCom!$C:$C,BalDip!$E$14) -> 0 | G26: =SUMIFS(BalCom!$H:$H,BalCom!$D:$D,BalDip!G$10,BalCom!$N:$N,BalDip!$C26,BalCom!$C:$C,BalDip!$E$14) -> 0 | H26: =SUMIFS(BalCom!$H:$H,BalCom!$D:$D,BalDip!H$10,BalCom!$N:$N,BalDip!$C26,BalCom!$C:$C,BalDip!$E$14) -> 0 | I26: =SUMIFS(BalCom!$H:$H,BalCom!$D:$D,BalDip!I$10,BalCom!$N:$N,BalDip!$C26,BalCom!$C:$C,BalDip!$E$14) -> 1818
C27: CH215 | D27: =IF(C27="","",_xlfn.XLOOKUP(C27,BalCom!N:N,BalCom!G:G,0)) -> 0.65 | E27: =IF(C27="","",_xlfn.XLOOKUP(C27,Used_before_Trf!A:A,Used_before_Trf!B:B,0)) -> (TEST)ACUMIN H65 (1600KG/IBC) - FILLER | F27: =SUMIFS(BalCom!$H:$H,BalCom!$D:$D,BalDip!F$10,BalCom!$N:$N,BalDip!$C27,BalCom!$C:$C,BalDip!$E$14) -> 0 | G27: =SUMIFS(BalCom!$H:$H,BalCom!$D:$D,BalDip!G$10,BalCom!$N:$N,BalDip!$C27,BalCom!$C:$C,BalDip!$E$14) -> 0 | H27: =SUMIFS(BalCom!$H:$H,BalCom!$D:$D,BalDip!H$10,BalCom!$N:$N,BalDip!$C27,BalCom!$C:$C,BalDip!$E$14) -> 271.92 | I27: =SUMIFS(BalCom!$H:$H,BalCom!$D:$D,BalDip!I$10,BalCom!$N:$N,BalDip!$C27,BalCom!$C:$C,BalDip!$E$14) -> 272.7
... C34: CH96 | D34: =IF(C34="","",_xlfn.XLOOKUP(C34,BalCom!N:N,BalCom!G:G,0)) -> 0.47 | E34: =IF(C34="","",_xlfn.XLOOKUP(C34,Used_before_Trf!A:A,Used_before_Trf!B:B,0)) -> 47% FARSPERSE VIOLET PV-RLS 20 KGS/PAIL | F34: =SUMIFS(BalCom!$H:$H,BalCom!$D:$D,BalDip!F$10,BalCom!$N:$N,BalDip!$C34,BalCom!$C:$C,BalDip!$E$14) -> 0 | G34: =SUMIFS(BalCom!$H:$H,BalCom!$D:$D,BalDip!G$10,BalCom!$N:$N,BalDip!$C34,BalCom!$C:$C,BalDip!$E$14) -> 0 | H34: =SUMIFS(BalCom!$H:$H,BalCom!$D:$D,BalDip!H$10,BalCom!$N:$N,BalDip!$C34,BalCom!$C:$C,BalDip!$E$14) -> 0 | I34: =SUMIFS(BalCom!$H:$H,BalCom!$D:$D,BalDip!I$10,BalCom!$N:$N,BalDip!$C34,BalCom!$C:$C,BalDip!$E$14) -> 0
D35: =IF(C35="","",_xlfn.XLOOKUP(C35,BalCom!N:N,BalCom!G:G,0)) | E35: =IF(C35="","",_xlfn.XLOOKUP(C35,Used_before_Trf!A:A,Used_before_Trf!B:B,0)) | F35: =SUMIFS(BalCom!$H:$H,BalCom!$D:$D,BalDip!F$10,BalCom!$N:$N,BalDip!$C35,BalCom!$C:$C,BalDip!$E$14) -> 0 | G35: =SUMIFS(BalCom!$H:$H,BalCom!$D:$D,BalDip!G$10,BalCom!$N:$N,BalDip!$C35,BalCom!$C:$C,BalDip!$E$14) -> 0 | H35: =SUMIFS(BalCom!$H:$H,BalCom!$D:$D,BalDip!H$10,BalCom!$N:$N,BalDip!$C35,BalCom!$C:$C,BalDip!$E$14) -> 0 | I35: =SUMIFS(BalCom!$H:$H,BalCom!$D:$D,BalDip!I$10,BalCom!$N:$N,BalDip!$C35,BalCom!$C:$C,BalDip!$E$14) -> 0
D36: =IF(C36="","",_xlfn.XLOOKUP(C36,BalCom!N:N,BalCom!G:G,0)) | E36: =IF(C36="","",_xlfn.XLOOKUP(C36,Used_before_Trf!A:A,Used_before_Trf!B:B,0)) | F36: =SUMIFS(BalCom!$H:$H,BalCom!$D:$D,BalDip!F$10,BalCom!$N:$N,BalDip!$C36,BalCom!$C:$C,BalDip!$E$14) -> 0 | G36: =SUMIFS(BalCom!$H:$H,BalCom!$D:$D,BalDip!G$10,BalCom!$N:$N,BalDip!$C36,BalCom!$C:$C,BalDip!$E$14) -> 0 | H36: =SUMIFS(BalCom!$H:$H,BalCom!$D:$D,BalDip!H$10,BalCom!$N:$N,BalDip!$C36,BalCom!$C:$C,BalDip!$E$14) -> 0 | I36: =SUMIFS(BalCom!$H:$H,BalCom!$D:$D,BalDip!I$10,BalCom!$N:$N,BalDip!$C36,BalCom!$C:$C,BalDip!$E$14) -> 0
D37: =IF(C37="","",_xlfn.XLOOKUP(C37,BalCom!N:N,BalCom!G:G,0)) | E37: =IF(C37="","",_xlfn.XLOOKUP(C37,Used_before_Trf!A:A,Used_before_Trf!B:B,0)) | F37: =SUMIFS(BalCom!$H:$H,BalCom!$D:$D,BalDip!F$10,BalCom!$N:$N,BalDip!$C37,BalCom!$C:$C,BalDip!$E$14) -> 0 | G37: =SUMIFS(BalCom!$H:$H,BalCom!$D:$D,BalDip!G$10,BalCom!$N:$N,BalDip!$C37,BalCom!$C:$C,BalDip!$E$14) -> 0 | H37: =SUMIFS(BalCom!$H:$H,BalCom!$D:$D,BalDip!H$10,BalCom!$N:$N,BalDip!$C37,BalCom!$C:$C,BalDip!$E$14) -> 0 | I37: =SUMIFS(BalCom!$H:$H,BalCom!$D:$D,BalDip!I$10,BalCom!$N:$N,BalDip!$C37,BalCom!$C:$C,BalDip!$E$14) -> 0
D38: =IF(C38="","",_xlfn.XLOOKUP(C38,BalCom!N:N,BalCom!G:G,0)) | E38: =IF(C38="","",_xlfn.XLOOKUP(C38,Used_before_Trf!A:A,Used_before_Trf!B:B,0)) | F38: =SUMIFS(BalCom!$H:$H,BalCom!$D:$D,BalDip!F$10,BalCom!$N:$N,BalDip!$C38,BalCom!$C:$C,BalDip!$E$14) -> 0 | G38: =SUMIFS(BalCom!$H:$H,BalCom!$D:$D,BalDip!G$10,BalCom!$N:$N,BalDip!$C38,BalCom!$C:$C,BalDip!$E$14) -> 0 | H38: =SUMIFS(BalCom!$H:$H,BalCom!$D:$D,BalDip!H$10,BalCom!$N:$N,BalDip!$C38,BalCom!$C:$C,BalDip!$E$14) -> 0 | I38: =SUMIFS(BalCom!$H:$H,BalCom!$D:$D,BalDip!I$10,BalCom!$N:$N,BalDip!$C38,BalCom!$C:$C,BalDip!$E$14) -> 0
D39: =IF(C39="","",_xlfn.XLOOKUP(C39,BalCom!N:N,BalCom!G:G,0)) | E39: =IF(C39="","",_xlfn.XLOOKUP(C39,Used_before_Trf!A:A,Used_before_Trf!B:B,0)) | F39: =SUMIFS(BalCom!$H:$H,BalCom!$D:$D,BalDip!F$10,BalCom!$N:$N,BalDip!$C39,BalCom!$C:$C,BalDip!$E$14) -> 0 | G39: =SUMIFS(BalCom!$H:$H,BalCom!$D:$D,BalDip!G$10,BalCom!$N:$N,BalDip!$C39,BalCom!$C:$C,BalDip!$E$14) -> 0 | H39: =SUMIFS(BalCom!$H:$H,BalCom!$D:$D,BalDip!H$10,BalCom!$N:$N,BalDip!$C39,BalCom!$C:$C,BalDip!$E$14) -> 0 | I39: =SUMIFS(BalCom!$H:$H,BalCom!$D:$D,BalDip!I$10,BalCom!$N:$N,BalDip!$C39,BalCom!$C:$C,BalDip!$E$14) -> 0
D40: =IF(C40="","",_xlfn.XLOOKUP(C40,BalCom!N:N,BalCom!G:G,0)) | E40: =IF(C40="","",_xlfn.XLOOKUP(C40,Used_before_Trf!A:A,Used_before_Trf!B:B,0)) | F40: =SUMIFS(BalCom!$H:$H,BalCom!$D:$D,BalDip!F$10,BalCom!$N:$N,BalDip!$C40,BalCom!$C:$C,BalDip!$E$14) -> 0 | G40: =SUMIFS(BalCom!$H:$H,BalCom!$D:$D,BalDip!G$10,BalCom!$N:$N,BalDip!$C40,BalCom!$C:$C,BalDip!$E$14) -> 0 | H40: =SUMIFS(BalCom!$H:$H,BalCom!$D:$D,BalDip!H$10,BalCom!$N:$N,BalDip!$C40,BalCom!$C:$C,BalDip!$E$14) -> 0 | I40: =SUMIFS(BalCom!$H:$H,BalCom!$D:$D,BalDip!I$10,BalCom!$N:$N,BalDip!$C40,BalCom!$C:$C,BalDip!$E$14) -> 0
D41: =IF(C41="","",_xlfn.XLOOKUP(C41,BalCom!N:N,BalCom!G:G,0)) | E41: =IF(C41="","",_xlfn.XLOOKUP(C41,Used_before_Trf!A:A,Used_before_Trf!B:B,0)) | F41: =SUMIFS(BalCom!$H:$H,BalCom!$D:$D,BalDip!F$10,BalCom!$N:$N,BalDip!$C41,BalCom!$C:$C,BalDip!$E$14) -> 0 | G41: =SUMIFS(BalCom!$H:$H,BalCom!$D:$D,BalDip!G$10,BalCom!$N:$N,BalDip!$C41,BalCom!$C:$C,BalDip!$E$14) -> 0 | H41: =SUMIFS(BalCom!$H:$H,BalCom!$D:$D,BalDip!H$10,BalCom!$N:$N,BalDip!$C41,BalCom!$C:$C,BalDip!$E$14) -> 0 | I41: =SUMIFS(BalCom!$H:$H,BalCom!$D:$D,BalDip!I$10,BalCom!$N:$N,BalDip!$C41,BalCom!$C:$C,BalDip!$E$14) -> 0
D42: =IF(C42="","",_xlfn.XLOOKUP(C42,BalCom!N:N,BalCom!G:G,0)) | E42: =IF(C42="","",_xlfn.XLOOKUP(C42,Used_before_Trf!A:A,Used_before_Trf!B:B,0)) | F42: =SUMIFS(BalCom!$H:$H,BalCom!$D:$D,BalDip!F$10,BalCom!$N:$N,BalDip!$C42,BalCom!$C:$C,BalDip!$E$14) -> 0 | G42: =SUMIFS(BalCom!$H:$H,BalCom!$D:$D,BalDip!G$10,BalCom!$N:$N,BalDip!$C42,BalCom!$C:$C,BalDip!$E$14) -> 0 | H42: =SUMIFS(BalCom!$H:$H,BalCom!$D:$D,BalDip!H$10,BalCom!$N:$N,BalDip!$C42,BalCom!$C:$C,BalDip!$E$14) -> 0 | I42: =SUMIFS(BalCom!$H:$H,BalCom!$D:$D,BalDip!I$10,BalCom!$N:$N,BalDip!$C42,BalCom!$C:$C,BalDip!$E$14) -> 0
D43: =IF(C43="","",_xlfn.XLOOKUP(C43,BalCom!N:N,BalCom!G:G,0)) | E43: =IF(C43="","",_xlfn.XLOOKUP(C43,Used_before_Trf!A:A,Used_before_Trf!B:B,0)) | F43: =SUMIFS(BalCom!$H:$H,BalCom!$D:$D,BalDip!F$10,BalCom!$N:$N,BalDip!$C43,BalCom!$C:$C,BalDip!$E$14) -> 0 | G43: =SUMIFS(BalCom!$H:$H,BalCom!$D:$D,BalDip!G$10,BalCom!$N:$N,BalDip!$C43,BalCom!$C:$C,BalDip!$E$14) -> 0 | H43: =SUMIFS(BalCom!$H:$H,BalCom!$D:$D,BalDip!H$10,BalCom!$N:$N,BalDip!$C43,BalCom!$C:$C,BalDip!$E$14) -> 0 | I43: =SUMIFS(BalCom!$H:$H,BalCom!$D:$D,BalDip!I$10,BalCom!$N:$N,BalDip!$C43,BalCom!$C:$C,BalDip!$E$14) -> 0
E44: =IF(C44="","",_xlfn.XLOOKUP(C44,Used_before_Trf!A:A,Used_before_Trf!B:B,0)) | F44: =SUM(F16:F43) -> 0 | G44: =SUM(G16:G43) -> 0 | H44: =SUM(H16:H43) -> 2198.9264 | I44: =SUM(I16:I43) -> 2197.962
E45: =IF(C45="","",_xlfn.XLOOKUP(C45,Used_before_Trf!A:A,Used_before_Trf!B:B,0))
E46: =IF(C46="","",_xlfn.XLOOKUP(C46,Used_before_Trf!A:A,Used_before_Trf!B:B,0))
A48: Type | B48: Unit | C48: =C15 -> New Code | E48: =E15 -> Description | F48: Kg Wet | G48: Kg Wet | H48: Kg Wet | I48: Kg Wet | N48: TOTAL KGs
A49: =IF(LEFT(C49,3)="NBR","NBR","CHE")&"_"&"COM" -> NBR_COM | B49: Kgs | C49: =C16 -> NBR01 | E49: =E16 -> SYNTHETIC LATEX BST NBL 8503S | F49: =IFERROR((F$9*F16/F$44/$D16),0) -> 0 | G49: =IFERROR((G$9*G16/G$44/$D16),0) -> 0 | H49: =IFERROR((H$9*H16/H$44/$D16),0) -> 0 | I49: =IFERROR((I$9*I16/I$44/$D16),0) -> 0 | N49: =SUM(F49:M49) -> 0
A50: =IF(LEFT(C50,3)="NBR","NBR","CHE")&"_"&"COM" -> CHE_COM | B50: Kgs | C50: =C17 -> CH212 | E50: =E17 -> (TEST) POTASSIUM HYDROXIDE FLAKE 90% ( KOH ) ( 25 KGS / BAG ) | F50: =IFERROR((F$9*F17/F$44/$D17),0) -> 0 | G50: =IFERROR((G$9*G17/G$44/$D17),0) -> 0 | H50: =IFERROR((H$9*H17/H$44/$D17),0) -> 61.862235 | I50: =IFERROR((I$9*I17/I$44/$D17),0) -> 58.645504 | N50: =SUM(F50:M50) -> 120.50774
A51: =IF(LEFT(C51,3)="NBR","NBR","CHE")&"_"&"COM" -> CHE_COM | B51: Kgs | C51: =C18 -> SFG-Water | E51: =E18 -> Water | F51: =IFERROR((F$9*F18/F$44/$D18),0) -> 0 | G51: =IFERROR((G$9*G18/G$44/$D18),0) -> 0 | H51: =IFERROR((H$9*H18/H$44/$D18),0) -> 840.301 | I51: =IFERROR((I$9*I18/I$44/$D18),0) -> 796.60677 | N51: =SUM(F51:M51) -> 1636.9078
A52: =IF(LEFT(C52,3)="NBR","NBR","CHE")&"_"&"COM" -> CHE_COM | B52: Kgs | C52: =C19 -> CH227 | E52: =E19 -> (TEST) NEOPELEX G-15P (1000KG/IBC) (SDBS) | F52: =IFERROR((F$9*F19/F$44/$D19),0) -> 0 | G52: =IFERROR((G$9*G19/G$44/$D19),0) -> 0 | H52: =IFERROR((H$9*H19/H$44/$D19),0) -> 21.22737 | I52: =IFERROR((I$9*I19/I$44/$D19),0) -> 22.806727 | N52: =SUM(F52:M52) -> 44.034097
A53: =IF(LEFT(C53,3)="NBR","NBR","CHE")&"_"&"COM" -> CHE_COM | B53: Kgs | C53: =C20 -> CH93 | E53: =E20 -> ZINC OXIDE 60% (ZNO) 250 KGS/DRUM | F53: =IFERROR((F$9*F20/F$44/$D20),0) -> 0 | G53: =IFERROR((G$9*G20/G$44/$D20),0) -> 0 | H53: =IFERROR((H$9*H20/H$44/$D20),0) -> 21.22737 | I53: =IFERROR((I$9*I20/I$44/$D20),0) -> 17.105045 | N53: =SUM(F53:M53) -> 38.332416
A54: =IF(LEFT(C54,3)="NBR","NBR","CHE")&"_"&"COM" -> CHE_COM | B54: Kgs | C54: =C21 -> CH92 | E54: =E21 -> SULPHUR 60% 250 KGS/DRUM | F54: =IFERROR((F$9*F21/F$44/$D21),0) -> 0 | G54: =IFERROR((G$9*G21/G$44/$D21),0) -> 0 | H54: =IFERROR((H$9*H21/H$44/$D21),0) -> 26.534213 | I54: =IFERROR((I$9*I21/I$44/$D21),0) -> 28.508409 | N54: =SUM(F54:M54) -> 55.042622
A55: =IF(LEFT(C55,3)="NBR","NBR","CHE")&"_"&"COM" -> CHE_COM | B55: Kgs | C55: =C22 -> CH91 | E55: =E22 -> ZDBC 50% 225 KGS/DRUM | F55: =IFERROR((F$9*F22/F$44/$D22),0) -> 0 | G55: =IFERROR((G$9*G22/G$44/$D22),0) -> 0 | H55: =IFERROR((H$9*H22/H$44/$D22),0) -> 19.104633 | I55: =IFERROR((I$9*I22/I$44/$D22),0) -> 20.526055 | N55: =SUM(F55:M55) -> 39.630688
A56: =IF(LEFT(C56,3)="NBR","NBR","CHE")&"_"&"COM" -> CHE_COM | B56: Kgs | C56: =C23 -> CH229 | E56: =E23 -> (TEST) MRC600NB50(1400KG/IBC) MOQ: 23,800KG EXTENDER | F56: =IFERROR((F$9*F23/F$44/$D23),0) -> 0 | G56: =IFERROR((G$9*G23/G$44/$D23),0) -> 0 | H56: =IFERROR((H$9*H23/H$44/$D23),0) -> 0 | I56: =IFERROR((I$9*I23/I$44/$D23),0) -> 0 | N56: =SUM(F56:M56) -> 0
A57: =IF(LEFT(C57,3)="NBR","NBR","CHE")&"_"&"COM" -> CHE_COM | B57: Kgs | C57: =C24 -> CH222 | E57: =E24 -> AQUAWAX 022S (950KG/IBC) -WAX | F57: =IFERROR((F$9*F24/F$44/$D24),0) -> 0 | G57: =IFERROR((G$9*G24/G$44/$D24),0) -> 0 | H57: =IFERROR((H$9*H24/H$44/$D24),0) -> 28.946414 | I57: =IFERROR((I$9*I24/I$44/$D24),0) -> 31.100083 | N57: =SUM(F57:M57) -> 60.046497
A58: =IF(LEFT(C58,3)="NBR","NBR","CHE")&"_"&"COM" -> CHE_COM | B58: Kgs | C58: =C25 -> CH140 | E58: =E25 -> HYDROTINT BLACK BA (20KG/PK) PIGMENT | F58: =IFERROR((F$9*F25/F$44/$D25),0) -> 0 | G58: =IFERROR((G$9*G25/G$44/$D25),0) -> 0 | H58: =IFERROR((H$9*H25/H$44/$D25),0) -> 31.841055 | I58: =IFERROR((I$9*I25/I$44/$D25),0) -> 34.210091 | N58: =SUM(F58:M58) -> 66.051146
A59: =IF(LEFT(C59,3)="NBR","NBR","CHE")&"_"&"COM" -> NBR_COM | B59: Kgs | C59: NBR01 | E59: =E26 -> (TEST) NBR LATEX, RFA-7632 | F59: =IFERROR((F$9*F26/F$44/$D26),0) -> 0 | G59: =IFERROR((G$9*G26/G$44/$D26),0) -> 0 | H59: =IFERROR((H$9*H26/H$44/$D26),0) -> 0 | I59: =IFERROR((I$9*I26/I$44/$D26),0) -> 3754.3998 | N59: =SUM(F59:M59) -> 3754.3998
A60: =IF(LEFT(C60,3)="NBR","NBR","CHE")&"_"&"COM" -> CHE_COM | B60: Kgs | C60: =C27 -> CH215 | E60: =E27 -> (TEST)ACUMIN H65 (1600KG/IBC) - FILLER | F60: =IFERROR((F$9*F27/F$44/$D27),0) -> 0 | G60: =IFERROR((G$9*G27/G$44/$D27),0) -> 0 | H60: =IFERROR((H$9*H27/H$44/$D27),0) -> 367.39679 | I60: =IFERROR((I$9*I27/I$44/$D27),0) -> 394.73182 | N60: =SUM(F60:M60) -> 762.12861
A61: =IF(LEFT(C61,3)="NBR","NBR","CHE")&"_"&"COM" -> NBR_COM | B61: Kgs | C61: =C28 -> NBR30 | E61: =E28 -> (TEST) NBR-XY806 | F61: =IFERROR((F$9*F28/F$44/$D28),0) -> 0 | G61: =IFERROR((G$9*G28/G$44/$D28),0) -> 0 | H61: =IFERROR((H$9*H28/H$44/$D28),0) -> 3612.5545 | I61: =IFERROR((I$9*I28/I$44/$D28),0) -> 0 | N61: =SUM(F61:M61) -> 3612.5545
A62: =IF(LEFT(C62,3)="NBR","NBR","CHE")&"_"&"COM" -> CHE_COM | B62: Kgs | C62: =C29 -> CH168 | E62: =E29 -> ALPHALINK (ACELERATOR FREE CROSSLINKER) (200KG/DRUM) | F62: =IFERROR((F$9*F29/F$44/$D29),0) -> 0 | G62: =IFERROR((G$9*G29/G$44/$D29),0) -> 0 | H62: =IFERROR((H$9*H29/H$44/$D29),0) -> 0 | I62: =IFERROR((I$9*I29/I$44/$D29),0) -> 0 | N62: =SUM(F62:M62) -> 0
A63: =IF(LEFT(C63,3)="NBR","NBR","CHE")&"_"&"COM" -> CHE_COM | B63: Kgs | C63: =C30 -> CH106 | E63: =E30 -> OCTOSOL 643 (200KG/DRUM) | F63: =IFERROR((F$9*F30/F$44/$D30),0) -> 0 | G63: =IFERROR((G$9*G30/G$44/$D30),0) -> 0 | H63: =IFERROR((H$9*H30/H$44/$D30),0) -> 0 | I63: =IFERROR((I$9*I30/I$44/$D30),0) -> 0 | N63: =SUM(F63:M63) -> 0
A64: =IF(LEFT(C64,3)="NBR","NBR","CHE")&"_"&"COM" -> CHE_COM | B64: Kgs | C64: =C31 -> CH94 | E64: =E31 -> TIO2 70% (TITANIUM DIOXIDE) 250 KGS/DRUM | F64: =IFERROR((F$9*F31/F$44/$D31),0) -> 0 | G64: =IFERROR((G$9*G31/G$44/$D31),0) -> 0 | H64: =IFERROR((H$9*H31/H$44/$D31),0) -> 0 | I64: =IFERROR((I$9*I31/I$44/$D31),0) -> 0 | N64: =SUM(F64:M64) -> 0
A65: =IF(LEFT(C65,3)="NBR","NBR","CHE")&"_"&"COM" -> CHE_COM | B65: Kgs | C65: =C32 -> CH128 | E65: =E32 -> FARSPERSE BLUE MPL1523 (20 KGS/PAIL) | F65: =IFERROR((F$9*F32/F$44/$D32),0) -> 0 | G65: =IFERROR((G$9*G32/G$44/$D32),0) -> 0 | H65: =IFERROR((H$9*H32/H$44/$D32),0) -> 0 | I65: =IFERROR((I$9*I32/I$44/$D32),0) -> 0 | N65: =SUM(F65:M65) -> 0
A66: =IF(LEFT(C66,3)="NBR","NBR","CHE")&"_"&"COM" -> CHE_COM | B66: Kgs | C66: =C33 -> CH240 | E66: =E33 -> (TEST) ALPHALINK 50 (200KG/DRUM),(1000KG/IBC) - ACELERATOR FREE CROSSLINKER | F66: =IFERROR((F$9*F33/F$44/$D33),0) -> 0 | G66: =IFERROR((G$9*G33/G$44/$D33),0) -> 0 | H66: =IFERROR((H$9*H33/H$44/$D33),0) -> 0 | I66: =IFERROR((I$9*I33/I$44/$D33),0) -> 0 | N66: =SUM(F66:M66) -> 0
A67: =IF(LEFT(C67,3)="NBR","NBR","CHE")&"_"&"COM" -> CHE_COM | B67: Kgs | C67: =C34 -> CH96 | E67: =E34 -> 47% FARSPERSE VIOLET PV-RLS 20 KGS/PAIL | F67: =IFERROR((F$9*F34/F$44/$D34),0) -> 0 | G67: =IFERROR((G$9*G34/G$44/$D34),0) -> 0 | H67: =IFERROR((H$9*H34/H$44/$D34),0) -> 0 | I67: =IFERROR((I$9*I34/I$44/$D34),0) -> 0 | N67: =SUM(F67:M67) -> 0
A68: =IF(LEFT(C68,3)="NBR","NBR","CHE")&"_"&"COM" -> CHE_COM | B68: Kgs | C68: =C35 -> 0 | E68: =E35 | F68: =IFERROR((F$9*F35/F$44/$D35),0) -> 0 | G68: =IFERROR((G$9*G35/G$44/$D35),0) -> 0 | H68: =IFERROR((H$9*H35/H$44/$D35),0) -> 0 | I68: =IFERROR((I$9*I35/I$44/$D35),0) -> 0 | N68: =SUM(F68:M68) -> 0
A69: =IF(LEFT(C69,3)="NBR","NBR","CHE")&"_"&"COM" -> CHE_COM | B69: Kgs | C69: =C36 -> 0 | E69: =E36 | F69: =IFERROR((F$9*F36/F$44/$D36),0) -> 0 | G69: =IFERROR((G$9*G36/G$44/$D36),0) -> 0 | H69: =IFERROR((H$9*H36/H$44/$D36),0) -> 0 | I69: =IFERROR((I$9*I36/I$44/$D36),0) -> 0 | N69: =SUM(F69:M69) -> 0
A70: =IF(LEFT(C70,3)="NBR","NBR","CHE")&"_"&"COM" -> CHE_COM | B70: Kgs | C70: =C37 -> 0 | E70: =E37 | F70: =IFERROR((F$9*F37/F$44/$D37),0) -> 0 | G70: =IFERROR((G$9*G37/G$44/$D37),0) -> 0 | H70: =IFERROR((H$9*H37/H$44/$D37),0) -> 0 | I70: =IFERROR((I$9*I37/I$44/$D37),0) -> 0 | N70: =SUM(F70:M70) -> 0
A71: =IF(LEFT(C71,3)="NBR","NBR","CHE")&"_"&"COM" -> CHE_COM | B71: Kgs | C71: =C38 -> 0 | E71: =E38 | F71: =IFERROR((F$9*F38/F$44/$D38),0) -> 0 | G71: =IFERROR((G$9*G38/G$44/$D38),0) -> 0 | H71: =IFERROR((H$9*H38/H$44/$D38),0) -> 0 | I71: =IFERROR((I$9*I38/I$44/$D38),0) -> 0 | N71: =SUM(F71:M71) -> 0
... A73: =IF(LEFT(C73,3)="NBR","NBR","CHE")&"_"&"COM" -> CHE_COM | B73: Kgs | C73: =C40 -> 0 | E73: =E40 | F73: =IFERROR((F$9*F40/F$44/$D40),0) -> 0 | G73: =IFERROR((G$9*G40/G$44/$D40),0) -> 0 | H73: =IFERROR((H$9*H40/H$44/$D40),0) -> 0 | I73: =IFERROR((I$9*I40/I$44/$D40),0) -> 0 | N73: =SUM(F73:M73) -> 0
A74: =IF(LEFT(C74,3)="NBR","NBR","CHE")&"_"&"COM" -> CHE_COM | B74: Kgs | D74: =IF(C74="","",_xlfn.XLOOKUP(C74,Used_before_Trf!A:A,Used_before_Trf!U:U,0)) | E74: =E41 | F74: =IFERROR((F$9*F41/F$44/$D41),0) -> 0 | G74: =IFERROR((G$9*G41/G$44/$D41),0) -> 0 | H74: =IFERROR((H$9*H41/H$44/$D41),0) -> 0 | I74: =IFERROR((I$9*I41/I$44/$D41),0) -> 0 | N74: =SUM(F74:M74) -> 0
E75: TOTAL KGS | F75: =SUM(F49:F74) -> 0 | G75: =SUM(G49:G74) -> 0 | H75: =SUM(H49:H74) -> 5030.9956 | I75: =SUM(I49:I74) -> 5158.6403 | N75: =SUM(N49:N74) -> 10189.636
A79: Type | B79: Unit | C79: =C48 -> New Code | D79: Price | E79: =E48 -> Description | F79: Cost (Baht) | G79: Cost (Baht) | H79: Cost (Baht) | I79: Cost (Baht) | N79: TOTAL BAHT | O79: **check Kg VS Baht**
A80: =IF(LEFT(C80,3)="NBR","NBR","CHE")&"_"&"COM" -> NBR_COM | B80: Baht | C80: =C49 -> NBR01 | D80: =IF(C80="","",_xlfn.XLOOKUP(C80,Used_before_Trf!A:A,Used_before_Trf!U:U,0)) -> 50.516914 | E80: =E49 -> SYNTHETIC LATEX BST NBL 8503S | F80: =ROUND(F49*$D80,2) -> 0 | G80: =ROUND(G49*$D80,2) -> 0 | H80: =ROUND(H49*$D80,2) -> 0 | I80: =ROUND(I49*$D80,2) -> 0 | N80: =SUM(F80:M80) -> 0 | O80: =IF(C80="SFG-Water","",IF(AND(N49>0,N80=0),"Error","OK")) -> OK
A81: =IF(LEFT(C81,3)="NBR","NBR","CHE")&"_"&"COM" -> CHE_COM | B81: Baht | C81: =C50 -> CH212 | D81: =IF(C81="","",_xlfn.XLOOKUP(C81,Used_before_Trf!A:A,Used_before_Trf!U:U,0)) -> 32.035421 | E81: =E50 -> (TEST) POTASSIUM HYDROXIDE FLAKE 90% ( KOH ) ( 25 KGS / BAG ) | F81: =ROUND(F50*$D81,2) -> 0 | G81: =ROUND(G50*$D81,2) -> 0 | H81: =ROUND(H50*$D81,2) -> 1981.78 | I81: =ROUND(I50*$D81,2) -> 1878.73 | N81: =SUM(F81:M81) -> 3860.51 | O81: =IF(C81="SFG-Water","",IF(AND(N50>0,N81=0),"Error","OK")) -> OK
A82: =IF(LEFT(C82,3)="NBR","NBR","CHE")&"_"&"COM" -> CHE_COM | B82: Baht | C82: =C51 -> SFG-Water | D82: =IF(C82="","",_xlfn.XLOOKUP(C82,Used_before_Trf!A:A,Used_before_Trf!U:U,0)) -> 0 | E82: =E51 -> Water | F82: =ROUND(F51*$D82,2) -> 0 | G82: =ROUND(G51*$D82,2) -> 0 | H82: =ROUND(H51*$D82,2) -> 0 | I82: =ROUND(I51*$D82,2) -> 0 | N82: =SUM(F82:M82) -> 0 | O82: =IF(C82="SFG-Water","",IF(AND(N51>0,N82=0),"Error","OK"))
A83: =IF(LEFT(C83,3)="NBR","NBR","CHE")&"_"&"COM" -> CHE_COM | B83: Baht | C83: =C52 -> CH227 | D83: =IF(C83="","",_xlfn.XLOOKUP(C83,Used_before_Trf!A:A,Used_before_Trf!U:U,0)) -> 14.05404 | E83: =E52 -> (TEST) NEOPELEX G-15P (1000KG/IBC) (SDBS) | F83: =ROUND(F52*$D83,2) -> 0 | G83: =ROUND(G52*$D83,2) -> 0 | H83: =ROUND(H52*$D83,2) -> 298.33 | I83: =ROUND(I52*$D83,2) -> 320.53 | N83: =SUM(F83:M83) -> 618.86 | O83: =IF(C83="SFG-Water","",IF(AND(N52>0,N83=0),"Error","OK")) -> OK
A84: =IF(LEFT(C84,3)="NBR","NBR","CHE")&"_"&"COM" -> CHE_COM | B84: Baht | C84: =C53 -> CH93 | D84: =IF(C84="","",_xlfn.XLOOKUP(C84,Used_before_Trf!A:A,Used_before_Trf!U:U,0)) -> 69.839849 | E84: =E53 -> ZINC OXIDE 60% (ZNO) 250 KGS/DRUM | F84: =ROUND(F53*$D84,2) -> 0 | G84: =ROUND(G53*$D84,2) -> 0 | H84: =ROUND(H53*$D84,2) -> 1482.52 | I84: =ROUND(I53*$D84,2) -> 1194.61 | N84: =SUM(F84:M84) -> 2677.13 | O84: =IF(C84="SFG-Water","",IF(AND(N53>0,N84=0),"Error","OK")) -> OK
A85: =IF(LEFT(C85,3)="NBR","NBR","CHE")&"_"&"COM" -> CHE_COM | B85: Baht | C85: =C54 -> CH92 | D85: =IF(C85="","",_xlfn.XLOOKUP(C85,Used_before_Trf!A:A,Used_before_Trf!U:U,0)) -> 28.016028 | E85: =E54 -> SULPHUR 60% 250 KGS/DRUM | F85: =ROUND(F54*$D85,2) -> 0 | G85: =ROUND(G54*$D85,2) -> 0 | H85: =ROUND(H54*$D85,2) -> 743.38 | I85: =ROUND(I54*$D85,2) -> 798.69 | N85: =SUM(F85:M85) -> 1542.07 | O85: =IF(C85="SFG-Water","",IF(AND(N54>0,N85=0),"Error","OK")) -> OK
A86: =IF(LEFT(C86,3)="NBR","NBR","CHE")&"_"&"COM" -> CHE_COM | B86: Baht | C86: =C55 -> CH91 | D86: =IF(C86="","",_xlfn.XLOOKUP(C86,Used_before_Trf!A:A,Used_before_Trf!U:U,0)) -> 50.317319 | E86: =E55 -> ZDBC 50% 225 KGS/DRUM | F86: =ROUND(F55*$D86,2) -> 0 | G86: =ROUND(G55*$D86,2) -> 0 | H86: =ROUND(H55*$D86,2) -> 961.29 | I86: =ROUND(I55*$D86,2) -> 1032.82 | N86: =SUM(F86:M86) -> 1994.11 | O86: =IF(C86="SFG-Water","",IF(AND(N55>0,N86=0),"Error","OK")) -> OK
A87: =IF(LEFT(C87,3)="NBR","NBR","CHE")&"_"&"COM" -> CHE_COM | B87: Baht | C87: =C56 -> CH229 | D87: =IF(C87="","",_xlfn.XLOOKUP(C87,Used_before_Trf!A:A,Used_before_Trf!U:U,0)) -> 13.07 | E87: =E56 -> (TEST) MRC600NB50(1400KG/IBC) MOQ: 23,800KG EXTENDER | F87: =ROUND(F56*$D87,2) -> 0 | G87: =ROUND(G56*$D87,2) -> 0 | H87: =ROUND(H56*$D87,2) -> 0 | I87: =ROUND(I56*$D87,2) -> 0 | N87: =SUM(F87:M87) -> 0 | O87: =IF(C87="SFG-Water","",IF(AND(N56>0,N87=0),"Error","OK")) -> OK
A88: =IF(LEFT(C88,3)="NBR","NBR","CHE")&"_"&"COM" -> CHE_COM | B88: Baht | C88: =C57 -> CH222 | D88: =IF(C88="","",_xlfn.XLOOKUP(C88,Used_before_Trf!A:A,Used_before_Trf!U:U,0)) -> 42.341881 | E88: =E57 -> AQUAWAX 022S (950KG/IBC) -WAX | F88: =ROUND(F57*$D88,2) -> 0 | G88: =ROUND(G57*$D88,2) -> 0 | H88: =ROUND(H57*$D88,2) -> 1225.65 | I88: =ROUND(I57*$D88,2) -> 1316.84 | N88: =SUM(F88:M88) -> 2542.49 | O88: =IF(C88="SFG-Water","",IF(AND(N57>0,N88=0),"Error","OK")) -> OK
A89: =IF(LEFT(C89,3)="NBR","NBR","CHE")&"_"&"COM" -> CHE_COM | B89: Baht | C89: =C58 -> CH140 | D89: =IF(C89="","",_xlfn.XLOOKUP(C89,Used_before_Trf!A:A,Used_before_Trf!U:U,0)) -> 57.918555 | E89: =E58 -> HYDROTINT BLACK BA (20KG/PK) PIGMENT | F89: =ROUND(F58*$D89,2) -> 0 | G89: =ROUND(G58*$D89,2) -> 0 | H89: =ROUND(H58*$D89,2) -> 1844.19 | I89: =ROUND(I58*$D89,2) -> 1981.4 | N89: =SUM(F89:M89) -> 3825.59 | O89: =IF(C89="SFG-Water","",IF(AND(N58>0,N89=0),"Error","OK")) -> OK
A90: =IF(LEFT(C90,3)="NBR","NBR","CHE")&"_"&"COM" -> NBR_COM | B90: Baht | C90: =C59 -> NBR01 | D90: =IF(C90="","",_xlfn.XLOOKUP(C90,Used_before_Trf!A:A,Used_before_Trf!U:U,0)) -> 50.516914 | E90: =E59 -> (TEST) NBR LATEX, RFA-7632 | F90: =ROUND(F59*$D90,2) -> 0 | G90: =ROUND(G59*$D90,2) -> 0 | H90: =ROUND(H59*$D90,2) -> 0 | I90: =ROUND(I59*$D90,2) -> 189660.69 | N90: =SUM(F90:M90) -> 189660.69 | O90: =IF(C90="SFG-Water","",IF(AND(N59>0,N90=0),"Error","OK")) -> OK
A91: =IF(LEFT(C91,3)="NBR","NBR","CHE")&"_"&"COM" -> CHE_COM | B91: Baht | C91: =C60 -> CH215 | D91: =IF(C91="","",_xlfn.XLOOKUP(C91,Used_before_Trf!A:A,Used_before_Trf!U:U,0)) -> 20.738312 | E91: =E60 -> (TEST)ACUMIN H65 (1600KG/IBC) - FILLER | F91: =ROUND(F60*$D91,2) -> 0 | G91: =ROUND(G60*$D91,2) -> 0 | H91: =ROUND(H60*$D91,2) -> 7619.19 | I91: =ROUND(I60*$D91,2) -> 8186.07 | N91: =SUM(F91:M91) -> 15805.26 | O91: =IF(C91="SFG-Water","",IF(AND(N60>0,N91=0),"Error","OK")) -> OK
... A104: =IF(LEFT(C104,3)="NBR","NBR","CHE")&"_"&"COM" -> CHE_COM | B104: Baht | C104: =C73 -> 0 | D104: =IF(C104="","",_xlfn.XLOOKUP(C104,Used_before_Trf!A:A,Used_before_Trf!U:U,0)) -> 0 | E104: =E73 | F104: =ROUND(F73*$D104,2) -> 0 | G104: =ROUND(G73*$D104,2) -> 0 | H104: =ROUND(H73*$D104,2) -> 0 | I104: =ROUND(I73*$D104,2) -> 0 | N104: =SUM(F104:M104) -> 0 | O104: =IF(C104="SFG-Water","",IF(AND(N73>0,N104=0),"Error","OK")) -> OK
A105: =IF(LEFT(C105,3)="NBR","NBR","CHE")&"_"&"COM" -> CHE_COM | B105: Baht | C105: =C74 -> 0 | D105: =IF(C105="","",_xlfn.XLOOKUP(C105,Used_before_Trf!A:A,Used_before_Trf!U:U,0)) -> 0 | E105: =E74 | N105: =SUM(F105:M105) -> 0 | O105: =IF(C105="SFG-Water","",IF(AND(N74>0,N105=0),"Error","OK")) -> OK
E106: TOTAL BAHT | F106: =SUM(F80:F105) -> 0 | G106: =SUM(G80:G105) -> 0 | H106: =SUM(H80:H105) -> 154546.46 | I106: =SUM(I80:I105) -> 206370.38 | N106: =SUM(N80:N105) -> 360916.84
C109: Dispersion of Dipping lines
E110: =E3 -> Dipping line | F110: =F3 -> DF 1 | G110: =G3 -> DF 2 | H110: =H3 -> DF 3 | I110: =I3 -> DF 4 | N110: =N3 -> Balance (Kgs)
E111: =E4 -> Type of gloves | F111: =F4 -> 0 | G111: =G4 -> 0 | H111: =H4 -> BLACK 5.5 | I111: =I4 -> BLACK 6.0
E112: Acid Tank | H112: 1300 | I112: 1300 | N112: =SUM(F112:M112) -> 2600
E113: Nobel 734, Akaline Clean S4, Speclean 11 | H113: 2600 | I113: 2600 | N113: =SUM(F113:M113) -> 5200
E114: Coagulant for LVD & BLUE-CS COAT T406 | N114: =SUM(F114:M114) -> 0
E115: Coagulant for LVD & BLUE-MAXCO | N115: =SUM(F115:M115) -> 0
E116: Coagulant for LVD & BLUE-CS COAT T403 | N116: =SUM(F116:M116) -> 0
E117: Coagulant for LVD & BLUE-Cyclaron 927 | N117: =SUM(F117:M117) -> 0
E118: Coagulant for LVD & BLUE-MRA-N59 | N118: =SUM(F118:M118) -> 0
E119: Coagulant for ORANGE-2XL | N119: =SUM(F119:M119) -> 0
E120: Coagulant for ORANGE-Cyclaron927 | N120: =SUM(F120:M120) -> 0
E121: Coagulant for BLACK- Cyclaron 927 | N121: =SUM(F121:M121) -> 0
E122: Coagulant for YELLOW | N122: =SUM(F122:M122) -> 0
E123: Coagulant for BLACK-MAXCO | H123: 3300 | I123: 3300 | N123: =SUM(F123:M123) -> 6600
E124: Coagulant for BLACK-MRA N23T | N124: =SUM(F124:M124) -> 0
E125: Coagulant for BLACK-MRA-N59 | N125: =SUM(F125:M125) -> 0
E126: Coagulant for BLACK-T403 | N126: =SUM(F126:M126) -> 0
E127: Coagulant for BLACK-T406 | N127: =SUM(F127:M127) -> 0
E128: Coagulant for BLACK-2XL | N128: =SUM(F128:M128) -> 0
N129: =SUM(F129:M129) -> 0
...

Sheet Used_before_Trf
A1: Net consumed Latex and Chemical on May'26 | AC1: _BalCom
C2: Issue from Store | F2: Adjustment | H2: Net Issue after adjustment | K2: Bal. of Chemical in Dipping & Compound (Production) | T2: Consumed of Chemical | W2: Bal. of Solution in Dipping & Compound | AL2: Net Consumed of Chemical before Transfer
K3: Opening stock | N3: Receive Stock | Q3: Closing stock | W3: Opening stock | Z3: Closing stock | AC3: Closing Compound latex | AF3: Closing stock of Dispersion | AI3: Closing stock of Dipping lines
A4: Code | B4: Description | C4: Kgs | D4: Cost : Kg | E4: Value (Bht) | F4: Kgs | G4: Value (Bht) | H4: Kgs | I4: Cost : Kg | J4: Value (Bht) | K4: Kgs | L4: Cost : Kg | M4: Value (Bht) | N4: Kgs | O4: Cost : Kg | P4: Value (Bht) | Q4: Kgs | R4: Cost : Kg | S4: Value (Bht) | T4: Kgs | U4: Cost : Kg | V4: Value (Bht) | W4: Kgs | X4: Cost : Kg | Y4: Value (Bht) | Z4: Kgs | AA4: Cost : Kg | AB4: Value (Bht) | AC4: Kgs | AD4: Cost : Kg | AE4: Value (Bht) | AF4: Kgs | AG4: Cost : Kg | AH4: Value (Bht) | AI4: Kgs | AJ4: Cost : Kg | AK4: Value (Bht) | AL4: Kgs | AM4: Cost : Kg | AN4: Value (Bht)
A5: CH101 | B5: CHLORINE 99.5% (1,000 KGS CYLINDER) MOITURE 100 MG/KG MAX. | C5: =SUMIF('Che-Store'!A:A,Used_before_Trf!A5,'Che-Store'!AC:AC)+SUMIF('Che-Comp'!A:A,Used_before_Trf!A5,'Che-Comp'!AC:AC) -> 0 | D5: =IFERROR(E5/C5,0) -> 0 | E5: =SUMIF('Che-Store'!A:A,Used_before_Trf!A5,'Che-Store'!AE:AE)+SUMIF('Che-Comp'!A:A,Used_before_Trf!A5,'Che-Comp'!AE:AE) -> 0 | F5: =SUMIFS('Che-Comp'!F:F,'Che-Comp'!$A:$A,Used_before_Trf!$A5) -> 0 | G5: =SUMIFS('Che-Comp'!G:G,'Che-Comp'!$A:$A,Used_before_Trf!$A5) -> 0 | H5: =C5-F5 -> 0 | I5: =IFERROR(J5/H5,0) -> 0 | J5: =E5-G5 -> 0 | K5: =SUMIF('Che.-Prod'!A:A,Used_before_Trf!A5,'Che.-Prod'!D:D) -> 0 | L5: =IFERROR(M5/K5,0) -> 0 | M5: =SUMIF('Che.-Prod'!A:A,Used_before_Trf!A5,'Che.-Prod'!F:F) -> 0 | N5: =SUMIF('Che.-Prod'!A:A,Used_before_Trf!A5,'Che.-Prod'!G:G) -> 0 | O5: =IF(N5=0,0,P5/N5) -> 0 | P5: =SUMIF('Che.-Prod'!A:A,Used_before_Trf!A5,'Che.-Prod'!H:H) -> 0 | Q5: =SUMIF('Che.-Prod'!A:A,Used_before_Trf!A5,'Che.-Prod'!P:P) -> 0 | R5: =IF(Q5=0,0,S5/Q5) -> 0 | S5: =SUMIF('Che.-Prod'!A:A,Used_before_Trf!A5,'Che.-Prod'!R:R) -> 0 | T5: =H5+K5+N5-Q5 -> 0 | U5: =IF(T5=0,0,V5/T5) -> 0 | V5: =J5+M5+P5-S5 -> 0 | W5: =SUMIF('CHE-last month'!$A:$A,Used_before_Trf!A5,'CHE-last month'!C:C) -> 0 | X5: =IF(W5=0,0,Y5/W5) -> 0 | Y5: =SUMIF('CHE-last month'!$A:$A,Used_before_Trf!A5,'CHE-last month'!E:E) -> 0 | Z5: =+AC5+AF5+AI5 -> 0 | AA5: =IF(Z5=0,0,AB5/Z5) -> 0 | AB5: =+AE5+AH5+AK5 -> 0 | AC5: =SUMIFS(BalCom!M:M,BalCom!N:N,Used_before_Trf!A5,BalCom!C:C,Used_before_Trf!$AC$1) -> 0 | AD5: =IF(AC5=0,0,AE5/AC5) -> 0 | AE5: =SUMIFS(BalCom!P:P,BalCom!N:N,Used_before_Trf!A5,BalCom!C:C,Used_before_Trf!$AC$1) -> 0 | AF5: =SUMIFS(BalDis!I:I,BalDis!J:J,Used_before_Trf!A5) -> 0 | AG5: =IF(AF5=0,0,AH5/AF5) -> 0 | AH5: =SUMIFS(BalDis!L:L,BalDis!J:J,Used_before_Trf!A5) -> 0 | AI5: =SUMIFS(BalDip!$N$49:$N$75,BalDip!$C$49:$C$75,Used_before_Trf!A5)+SUMIFS(BalDip!$N$134:$N$157,BalDip!$C$134:$C$157,Used_before_Trf!A5) -> 0 | AJ5: =IF(AI5=0,0,AK5/AI5) -> 0 | AK5: =SUMIFS(BalDip!$N$80:$N$106,BalDip!$C$80:$C$106,Used_before_Trf!A5)+SUMIFS(BalDip!$N$161:$N$184,BalDip!$C$161:$C$184,Used_before_Trf!A5) -> 0 | AL5: =+T5+W5-Z5 -> 0 | AM5: =IF(AL5=0,0,AN5/AL5) -> 0 | AN5: =+V5+Y5-AB5 -> 0
A6: CH102 | B6: SODIUM HYDROXIDE 50% (1500 KGS/IBC) | C6: =SUMIF('Che-Store'!A:A,Used_before_Trf!A6,'Che-Store'!AC:AC)+SUMIF('Che-Comp'!A:A,Used_before_Trf!A6,'Che-Comp'!AC:AC) -> 0 | D6: =IFERROR(E6/C6,0) -> 0 | E6: =SUMIF('Che-Store'!A:A,Used_before_Trf!A6,'Che-Store'!AE:AE)+SUMIF('Che-Comp'!A:A,Used_before_Trf!A6,'Che-Comp'!AE:AE) -> 0 | F6: =SUMIFS('Che-Comp'!F:F,'Che-Comp'!$A:$A,Used_before_Trf!$A6) -> 0 | G6: =SUMIFS('Che-Comp'!G:G,'Che-Comp'!$A:$A,Used_before_Trf!$A6) -> 0 | H6: =C6-F6 -> 0 | I6: =IFERROR(J6/H6,0) -> 0 | J6: =E6-G6 -> 0 | K6: =SUMIF('Che.-Prod'!A:A,Used_before_Trf!A6,'Che.-Prod'!D:D) -> 0 | L6: =IFERROR(M6/K6,0) -> 0 | M6: =SUMIF('Che.-Prod'!A:A,Used_before_Trf!A6,'Che.-Prod'!F:F) -> 0 | N6: =SUMIF('Che.-Prod'!A:A,Used_before_Trf!A6,'Che.-Prod'!G:G) -> 0 | O6: =IF(N6=0,0,P6/N6) -> 0 | P6: =SUMIF('Che.-Prod'!A:A,Used_before_Trf!A6,'Che.-Prod'!H:H) -> 0 | Q6: =SUMIF('Che.-Prod'!A:A,Used_before_Trf!A6,'Che.-Prod'!P:P) -> 0 | R6: =IF(Q6=0,0,S6/Q6) -> 0 | S6: =SUMIF('Che.-Prod'!A:A,Used_before_Trf!A6,'Che.-Prod'!R:R) -> 0 | T6: =H6+K6+N6-Q6 -> 0 | U6: =IF(T6=0,0,V6/T6) -> 0 | V6: =J6+M6+P6-S6 -> 0 | W6: =SUMIF('CHE-last month'!$A:$A,Used_before_Trf!A6,'CHE-last month'!C:C) -> 0 | X6: =IF(W6=0,0,Y6/W6) -> 0 | Y6: =SUMIF('CHE-last month'!$A:$A,Used_before_Trf!A6,'CHE-last month'!E:E) -> 0 | Z6: =+AC6+AF6+AI6 -> 0 | AA6: =IF(Z6=0,0,AB6/Z6) -> 0 | AB6: =+AE6+AH6+AK6 -> 0 | AC6: =SUMIFS(BalCom!M:M,BalCom!N:N,Used_before_Trf!A6,BalCom!C:C,Used_before_Trf!$AC$1) -> 0 | AD6: =IF(AC6=0,0,AE6/AC6) -> 0 | AE6: =SUMIFS(BalCom!P:P,BalCom!N:N,Used_before_Trf!A6,BalCom!C:C,Used_before_Trf!$AC$1) -> 0 | AF6: =SUMIFS(BalDis!I:I,BalDis!J:J,Used_before_Trf!A6) -> 0 | AG6: =IF(AF6=0,0,AH6/AF6) -> 0 | AH6: =SUMIFS(BalDis!L:L,BalDis!J:J,Used_before_Trf!A6) -> 0 | AI6: =SUMIFS(BalDip!$N$49:$N$75,BalDip!$C$49:$C$75,Used_before_Trf!A6)+SUMIFS(BalDip!$N$134:$N$157,BalDip!$C$134:$C$157,Used_before_Trf!A6) -> 0 | AJ6: =IF(AI6=0,0,AK6/AI6) -> 0 | AK6: =SUMIFS(BalDip!$N$80:$N$106,BalDip!$C$80:$C$106,Used_before_Trf!A6)+SUMIFS(BalDip!$N$161:$N$184,BalDip!$C$161:$C$184,Used_before_Trf!A6) -> 0 | AL6: =+T6+W6-Z6 -> 0 | AM6: =IF(AL6=0,0,AN6/AL6) -> 0 | AN6: =+V6+Y6-AB6 -> 0
A7: CH104 | B7: SPECLEAN 11 (246 KGS /DRUM) | C7: =SUMIF('Che-Store'!A:A,Used_before_Trf!A7,'Che-Store'!AC:AC)+SUMIF('Che-Comp'!A:A,Used_before_Trf!A7,'Che-Comp'!AC:AC) -> 0 | D7: =IFERROR(E7/C7,0) -> 0 | E7: =SUMIF('Che-Store'!A:A,Used_before_Trf!A7,'Che-Store'!AE:AE)+SUMIF('Che-Comp'!A:A,Used_before_Trf!A7,'Che-Comp'!AE:AE) -> 0 | F7: =SUMIFS('Che-Comp'!F:F,'Che-Comp'!$A:$A,Used_before_Trf!$A7) -> 0 | G7: =SUMIFS('Che-Comp'!G:G,'Che-Comp'!$A:$A,Used_before_Trf!$A7) -> 0 | H7: =C7-F7 -> 0 | I7: =IFERROR(J7/H7,0) -> 0 | J7: =E7-G7 -> 0 | K7: =SUMIF('Che.-Prod'!A:A,Used_before_Trf!A7,'Che.-Prod'!D:D) -> 0 | L7: =IFERROR(M7/K7,0) -> 0 | M7: =SUMIF('Che.-Prod'!A:A,Used_before_Trf!A7,'Che.-Prod'!F:F) -> 0 | N7: =SUMIF('Che.-Prod'!A:A,Used_before_Trf!A7,'Che.-Prod'!G:G) -> 0 | O7: =IF(N7=0,0,P7/N7) -> 0 | P7: =SUMIF('Che.-Prod'!A:A,Used_before_Trf!A7,'Che.-Prod'!H:H) -> 0 | Q7: =SUMIF('Che.-Prod'!A:A,Used_before_Trf!A7,'Che.-Prod'!P:P) -> 0 | R7: =IF(Q7=0,0,S7/Q7) -> 0 | S7: =SUMIF('Che.-Prod'!A:A,Used_before_Trf!A7,'Che.-Prod'!R:R) -> 0 | T7: =H7+K7+N7-Q7 -> 0 | U7: =IF(T7=0,0,V7/T7) -> 0 | V7: =J7+M7+P7-S7 -> 0 | W7: =SUMIF('CHE-last month'!$A:$A,Used_before_Trf!A7,'CHE-last month'!C:C) -> 0 | X7: =IF(W7=0,0,Y7/W7) -> 0 | Y7: =SUMIF('CHE-last month'!$A:$A,Used_before_Trf!A7,'CHE-last month'!E:E) -> 0 | Z7: =+AC7+AF7+AI7 -> 0 | AA7: =IF(Z7=0,0,AB7/Z7) -> 0 | AB7: =+AE7+AH7+AK7 -> 0 | AC7: =SUMIFS(BalCom!M:M,BalCom!N:N,Used_before_Trf!A7,BalCom!C:C,Used_before_Trf!$AC$1) -> 0 | AD7: =IF(AC7=0,0,AE7/AC7) -> 0 | AE7: =SUMIFS(BalCom!P:P,BalCom!N:N,Used_before_Trf!A7,BalCom!C:C,Used_before_Trf!$AC$1) -> 0 | AF7: =SUMIFS(BalDis!I:I,BalDis!J:J,Used_before_Trf!A7) -> 0 | AG7: =IF(AF7=0,0,AH7/AF7) -> 0 | AH7: =SUMIFS(BalDis!L:L,BalDis!J:J,Used_before_Trf!A7) -> 0 | AI7: =SUMIFS(BalDip!$N$49:$N$75,BalDip!$C$49:$C$75,Used_before_Trf!A7)+SUMIFS(BalDip!$N$134:$N$157,BalDip!$C$134:$C$157,Used_before_Trf!A7) -> 0 | AJ7: =IF(AI7=0,0,AK7/AI7) -> 0 | AK7: =SUMIFS(BalDip!$N$80:$N$106,BalDip!$C$80:$C$106,Used_before_Trf!A7)+SUMIFS(BalDip!$N$161:$N$184,BalDip!$C$161:$C$184,Used_before_Trf!A7) -> 0 | AL7: =+T7+W7-Z7 -> 0 | AM7: =IF(AL7=0,0,AN7/AL7) -> 0 | AN7: =+V7+Y7-AB7 -> 0 | AO7: =AM7-U7 -> 0
A8: CH105 | B8: HISOL D203 (QA75/137) 200 KGS/DRUM (MOQ 400KG/TRIP) | C8: =SUMIF('Che-Store'!A:A,Used_before_Trf!A8,'Che-Store'!AC:AC)+SUMIF('Che-Comp'!A:A,Used_before_Trf!A8,'Che-Comp'!AC:AC) -> 0 | D8: =IFERROR(E8/C8,0) -> 0 | E8: =SUMIF('Che-Store'!A:A,Used_before_Trf!A8,'Che-Store'!AE:AE)+SUMIF('Che-Comp'!A:A,Used_before_Trf!A8,'Che-Comp'!AE:AE) -> 0 | F8: =SUMIFS('Che-Comp'!F:F,'Che-Comp'!$A:$A,Used_before_Trf!$A8) -> 0 | G8: =SUMIFS('Che-Comp'!G:G,'Che-Comp'!$A:$A,Used_before_Trf!$A8) -> 0 | H8: =C8-F8 -> 0 | I8: =IFERROR(J8/H8,0) -> 0 | J8: =E8-G8 -> 0 | K8: =SUMIF('Che.-Prod'!A:A,Used_before_Trf!A8,'Che.-Prod'!D:D) -> 0 | L8: =IFERROR(M8/K8,0) -> 0 | M8: =SUMIF('Che.-Prod'!A:A,Used_before_Trf!A8,'Che.-Prod'!F:F) -> 0 | N8: =SUMIF('Che.-Prod'!A:A,Used_before_Trf!A8,'Che.-Prod'!G:G) -> 0 | O8: =IF(N8=0,0,P8/N8) -> 0 | P8: =SUMIF('Che.-Prod'!A:A,Used_before_Trf!A8,'Che.-Prod'!H:H) -> 0 | Q8: =SUMIF('Che.-Prod'!A:A,Used_before_Trf!A8,'Che.-Prod'!P:P) -> 0 | R8: =IF(Q8=0,0,S8/Q8) -> 0 | S8: =SUMIF('Che.-Prod'!A:A,Used_before_Trf!A8,'Che.-Prod'!R:R) -> 0 | T8: =H8+K8+N8-Q8 -> 0 | U8: =IF(T8=0,0,V8/T8) -> 0 | V8: =J8+M8+P8-S8 -> 0 | W8: =SUMIF('CHE-last month'!$A:$A,Used_before_Trf!A8,'CHE-last month'!C:C) -> 0 | X8: =IF(W8=0,0,Y8/W8) -> 0 | Y8: =SUMIF('CHE-last month'!$A:$A,Used_before_Trf!A8,'CHE-last month'!E:E) -> 0 | Z8: =+AC8+AF8+AI8 -> 0 | AA8: =IF(Z8=0,0,AB8/Z8) -> 0 | AB8: =+AE8+AH8+AK8 -> 0 | AC8: =SUMIFS(BalCom!M:M,BalCom!N:N,Used_before_Trf!A8,BalCom!C:C,Used_before_Trf!$AC$1) -> 0 | AD8: =IF(AC8=0,0,AE8/AC8) -> 0 | AE8: =SUMIFS(BalCom!P:P,BalCom!N:N,Used_before_Trf!A8,BalCom!C:C,Used_before_Trf!$AC$1) -> 0 | AF8: =SUMIFS(BalDis!I:I,BalDis!J:J,Used_before_Trf!A8) -> 0 | AG8: =IF(AF8=0,0,AH8/AF8) -> 0 | AH8: =SUMIFS(BalDis!L:L,BalDis!J:J,Used_before_Trf!A8) -> 0 | AI8: =SUMIFS(BalDip!$N$49:$N$75,BalDip!$C$49:$C$75,Used_before_Trf!A8)+SUMIFS(BalDip!$N$134:$N$157,BalDip!$C$134:$C$157,Used_before_Trf!A8) -> 0 | AJ8: =IF(AI8=0,0,AK8/AI8) -> 0 | AK8: =SUMIFS(BalDip!$N$80:$N$106,BalDip!$C$80:$C$106,Used_before_Trf!A8)+SUMIFS(BalDip!$N$161:$N$184,BalDip!$C$161:$C$184,Used_before_Trf!A8) -> 0 | AL8: =+T8+W8-Z8 -> 0 | AM8: =IF(AL8=0,0,AN8/AL8) -> 0 | AN8: =+V8+Y8-AB8 -> 0 | AO8: =AM8-U8 -> 0
A9: CH106 | B9: OCTOSOL 643 (200KG/DRUM) | C9: =SUMIF('Che-Store'!A:A,Used_before_Trf!A9,'Che-Store'!AC:AC)+SUMIF('Che-Comp'!A:A,Used_before_Trf!A9,'Che-Comp'!AC:AC) -> 20.15 | D9: =IFERROR(E9/C9,0) -> 32.57469 | E9: =SUMIF('Che-Store'!A:A,Used_before_Trf!A9,'Che-Store'!AE:AE)+SUMIF('Che-Comp'!A:A,Used_before_Trf!A9,'Che-Comp'!AE:AE) -> 656.38 | F9: =SUMIFS('Che-Comp'!F:F,'Che-Comp'!$A:$A,Used_before_Trf!$A9) -> 0 | G9: =SUMIFS('Che-Comp'!G:G,'Che-Comp'!$A:$A,Used_before_Trf!$A9) -> 0 | H9: =C9-F9 -> 20.15 | I9: =IFERROR(J9/H9,0) -> 32.57469 | J9: =E9-G9 -> 656.38 | K9: =SUMIF('Che.-Prod'!A:A,Used_before_Trf!A9,'Che.-Prod'!D:D) -> 0 | L9: =IFERROR(M9/K9,0) -> 0 | M9: =SUMIF('Che.-Prod'!A:A,Used_before_Trf!A9,'Che.-Prod'!F:F) -> 0 | N9: =SUMIF('Che.-Prod'!A:A,Used_before_Trf!A9,'Che.-Prod'!G:G) -> 0 | O9: =IF(N9=0,0,P9/N9) -> 0 | P9: =SUMIF('Che.-Prod'!A:A,Used_before_Trf!A9,'Che.-Prod'!H:H) -> 0 | Q9: =SUMIF('Che.-Prod'!A:A,Used_before_Trf!A9,'Che.-Prod'!P:P) -> 0 | R9: =IF(Q9=0,0,S9/Q9) -> 0 | S9: =SUMIF('Che.-Prod'!A:A,Used_before_Trf!A9,'Che.-Prod'!R:R) -> 0 | T9: =H9+K9+N9-Q9 -> 20.15 | U9: =IF(T9=0,0,V9/T9) -> 32.57469 | V9: =J9+M9+P9-S9 -> 656.38 | W9: =SUMIF('CHE-last month'!$A:$A,Used_before_Trf!A9,'CHE-last month'!C:C) -> 24.103642 | X9: =IF(W9=0,0,Y9/W9) -> 25.550081 | Y9: =SUMIF('CHE-last month'!$A:$A,Used_before_Trf!A9,'CHE-last month'!E:E) -> 615.85 | Z9: =+AC9+AF9+AI9 -> 38.489855 | AA9: =IF(Z9=0,0,AB9/Z9) -> 32.574558 | AB9: =+AE9+AH9+AK9 -> 1253.79 | AC9: =SUMIFS(BalCom!M:M,BalCom!N:N,Used_before_Trf!A9,BalCom!C:C,Used_before_Trf!$AC$1) -> 38.489855 | AD9: =IF(AC9=0,0,AE9/AC9) -> 32.574558 | AE9: =SUMIFS(BalCom!P:P,BalCom!N:N,Used_before_Trf!A9,BalCom!C:C,Used_before_Trf!$AC$1) -> 1253.79 | AF9: =SUMIFS(BalDis!I:I,BalDis!J:J,Used_before_Trf!A9) -> 0 | AG9: =IF(AF9=0,0,AH9/AF9) -> 0 | AH9: =SUMIFS(BalDis!L:L,BalDis!J:J,Used_before_Trf!A9) -> 0 | AI9: =SUMIFS(BalDip!$N$49:$N$75,BalDip!$C$49:$C$75,Used_before_Trf!A9)+SUMIFS(BalDip!$N$134:$N$157,BalDip!$C$134:$C$157,Used_before_Trf!A9) -> 0 | AJ9: =IF(AI9=0,0,AK9/AI9) -> 0 | AK9: =SUMIFS(BalDip!$N$80:$N$106,BalDip!$C$80:$C$106,Used_before_Trf!A9)+SUMIFS(BalDip!$N$161:$N$184,BalDip!$C$161:$C$184,Used_before_Trf!A9) -> 0 | AL9: =+T9+W9-Z9 -> 5.7637869 | AM9: =U9 -> 32.57469 | AN9: =+V9+Y9-AB9 -> 18.44 | AO9: =AM9-U9 -> 0
A10: CH109 | B10: VIVASHIELD 9177 WAX (950KG/IBC) | C10: =SUMIF('Che-Store'!A:A,Used_before_Trf!A10,'Che-Store'!AC:AC)+SUMIF('Che-Comp'!A:A,Used_before_Trf!A10,'Che-Comp'!AC:AC) -> 0 | D10: =IFERROR(E10/C10,0) -> 0 | E10: =SUMIF('Che-Store'!A:A,Used_before_Trf!A10,'Che-Store'!AE:AE)+SUMIF('Che-Comp'!A:A,Used_before_Trf!A10,'Che-Comp'!AE:AE) -> 0 | F10: =SUMIFS('Che-Comp'!F:F,'Che-Comp'!$A:$A,Used_before_Trf!$A10) -> 0 | G10: =SUMIFS('Che-Comp'!G:G,'Che-Comp'!$A:$A,Used_before_Trf!$A10) -> 0 | H10: =C10-F10 -> 0 | I10: =IFERROR(J10/H10,0) -> 0 | J10: =E10-G10 -> 0 | K10: =SUMIF('Che.-Prod'!A:A,Used_before_Trf!A10,'Che.-Prod'!D:D) -> 0 | L10: =IFERROR(M10/K10,0) -> 0 | M10: =SUMIF('Che.-Prod'!A:A,Used_before_Trf!A10,'Che.-Prod'!F:F) -> 0 | N10: =SUMIF('Che.-Prod'!A:A,Used_before_Trf!A10,'Che.-Prod'!G:G) -> 0 | O10: =IF(N10=0,0,P10/N10) -> 0 | P10: =SUMIF('Che.-Prod'!A:A,Used_before_Trf!A10,'Che.-Prod'!H:H) -> 0 | Q10: =SUMIF('Che.-Prod'!A:A,Used_before_Trf!A10,'Che.-Prod'!P:P) -> 0 | R10: =IF(Q10=0,0,S10/Q10) -> 0 | S10: =SUMIF('Che.-Prod'!A:A,Used_before_Trf!A10,'Che.-Prod'!R:R) -> 0 | T10: =H10+K10+N10-Q10 -> 0 | U10: =IF(T10=0,0,V10/T10) -> 0 | V10: =J10+M10+P10-S10 -> 0 | W10: =SUMIF('CHE-last month'!$A:$A,Used_before_Trf!A10,'CHE-last month'!C:C) -> 0 | X10: =IF(W10=0,0,Y10/W10) -> 0 | Y10: =SUMIF('CHE-last month'!$A:$A,Used_before_Trf!A10,'CHE-last month'!E:E) -> 0 | Z10: =+AC10+AF10+AI10 -> 0 | AA10: =IF(Z10=0,0,AB10/Z10) -> 0 | AB10: =+AE10+AH10+AK10 -> 0 | AC10: =SUMIFS(BalCom!M:M,BalCom!N:N,Used_before_Trf!A10,BalCom!C:C,Used_before_Trf!$AC$1) -> 0 | AD10: =IF(AC10=0,0,AE10/AC10) -> 0 | AE10: =SUMIFS(BalCom!P:P,BalCom!N:N,Used_before_Trf!A10,BalCom!C:C,Used_before_Trf!$AC$1) -> 0 | AF10: =SUMIFS(BalDis!I:I,BalDis!J:J,Used_before_Trf!A10) -> 0 | AG10: =IF(AF10=0,0,AH10/AF10) -> 0 | AH10: =SUMIFS(BalDis!L:L,BalDis!J:J,Used_before_Trf!A10) -> 0 | AI10: =SUMIFS(BalDip!$N$49:$N$75,BalDip!$C$49:$C$75,Used_before_Trf!A10)+SUMIFS(BalDip!$N$134:$N$157,BalDip!$C$134:$C$157,Used_before_Trf!A10) -> 0 | AJ10: =IF(AI10=0,0,AK10/AI10) -> 0 | AK10: =SUMIFS(BalDip!$N$80:$N$106,BalDip!$C$80:$C$106,Used_before_Trf!A10)+SUMIFS(BalDip!$N$161:$N$184,BalDip!$C$161:$C$184,Used_before_Trf!A10) -> 0 | AL10: =+T10+W10-Z10 -> 0 | AM10: =IF(AL10=0,0,AN10/AL10) -> 0 | AN10: =+V10+Y10-AB10 -> 0 | AO10: =AM10-U10 -> 0
A11: CH110 | B11: CS COAT T403 (1000 KG/TANK) | C11: =SUMIF('Che-Store'!A:A,Used_before_Trf!A11,'Che-Store'!AC:AC)+SUMIF('Che-Comp'!A:A,Used_before_Trf!A11,'Che-Comp'!AC:AC) -> 0 | D11: =IFERROR(E11/C11,0) -> 0 | E11: =SUMIF('Che-Store'!A:A,Used_before_Trf!A11,'Che-Store'!AE:AE)+SUMIF('Che-Comp'!A:A,Used_before_Trf!A11,'Che-Comp'!AE:AE) -> 0 | F11: =SUMIFS('Che-Comp'!F:F,'Che-Comp'!$A:$A,Used_before_Trf!$A11) -> 0 | G11: =SUMIFS('Che-Comp'!G:G,'Che-Comp'!$A:$A,Used_before_Trf!$A11) -> 0 | H11: =C11-F11 -> 0 | I11: =IFERROR(J11/H11,0) -> 0 | J11: =E11-G11 -> 0 | K11: =SUMIF('Che.-Prod'!A:A,Used_before_Trf!A11,'Che.-Prod'!D:D) -> 0 | L11: =IFERROR(M11/K11,0) -> 0 | M11: =SUMIF('Che.-Prod'!A:A,Used_before_Trf!A11,'Che.-Prod'!F:F) -> 0 | N11: =SUMIF('Che.-Prod'!A:A,Used_before_Trf!A11,'Che.-Prod'!G:G) -> 0 | O11: =IF(N11=0,0,P11/N11) -> 0 | P11: =SUMIF('Che.-Prod'!A:A,Used_before_Trf!A11,'Che.-Prod'!H:H) -> 0 | Q11: =SUMIF('Che.-Prod'!A:A,Used_before_Trf!A11,'Che.-Prod'!P:P) -> 0 | R11: =IF(Q11=0,0,S11/Q11) -> 0 | S11: =SUMIF('Che.-Prod'!A:A,Used_before_Trf!A11,'Che.-Prod'!R:R) -> 0 | T11: =H11+K11+N11-Q11 -> 0 | U11: =IF(T11=0,0,V11/T11) -> 0 | V11: =J11+M11+P11-S11 -> 0 | W11: =SUMIF('CHE-last month'!$A:$A,Used_before_Trf!A11,'CHE-last month'!C:C) -> 0 | X11: =IF(W11=0,0,Y11/W11) -> 0 | Y11: =SUMIF('CHE-last month'!$A:$A,Used_before_Trf!A11,'CHE-last month'!E:E) -> 0 | Z11: =+AC11+AF11+AI11 -> 0 | AA11: =IF(Z11=0,0,AB11/Z11) -> 0 | AB11: =+AE11+AH11+AK11 -> 0 | AC11: =SUMIFS(BalCom!M:M,BalCom!N:N,Used_before_Trf!A11,BalCom!C:C,Used_before_Trf!$AC$1) -> 0 | AD11: =IF(AC11=0,0,AE11/AC11) -> 0 | AE11: =SUMIFS(BalCom!P:P,BalCom!N:N,Used_before_Trf!A11,BalCom!C:C,Used_before_Trf!$AC$1) -> 0 | AF11: =SUMIFS(BalDis!I:I,BalDis!J:J,Used_before_Trf!A11) -> 0 | AG11: =IF(AF11=0,0,AH11/AF11) -> 0 | AH11: =SUMIFS(BalDis!L:L,BalDis!J:J,Used_before_Trf!A11) -> 0 | AI11: =SUMIFS(BalDip!$N$49:$N$75,BalDip!$C$49:$C$75,Used_before_Trf!A11)+SUMIFS(BalDip!$N$134:$N$157,BalDip!$C$134:$C$157,Used_before_Trf!A11) -> 0 | AJ11: =IF(AI11=0,0,AK11/AI11) -> 0 | AK11: =SUMIFS(BalDip!$N$80:$N$106,BalDip!$C$80:$C$106,Used_before_Trf!A11)+SUMIFS(BalDip!$N$161:$N$184,BalDip!$C$161:$C$184,Used_before_Trf!A11) -> 0 | AL11: =+T11+W11-Z11 -> 0 | AM11: =IF(AL11=0,0,AN11/AL11) -> 0 | AN11: =+V11+Y11-AB11 -> 0 | AO11: =AM11-U11 -> 0
A12: CH111 | B12: ALKALINE CLEAN S4 (1100 KG/TANK) | C12: =SUMIF('Che-Store'!A:A,Used_before_Trf!A12,'Che-Store'!AC:AC)+SUMIF('Che-Comp'!A:A,Used_before_Trf!A12,'Che-Comp'!AC:AC) -> 0 | D12: =IFERROR(E12/C12,0) -> 0 | E12: =SUMIF('Che-Store'!A:A,Used_before_Trf!A12,'Che-Store'!AE:AE)+SUMIF('Che-Comp'!A:A,Used_before_Trf!A12,'Che-Comp'!AE:AE) -> 0 | F12: =SUMIFS('Che-Comp'!F:F,'Che-Comp'!$A:$A,Used_before_Trf!$A12) -> 0 | G12: =SUMIFS('Che-Comp'!G:G,'Che-Comp'!$A:$A,Used_before_Trf!$A12) -> 0 | H12: =C12-F12 -> 0 | I12: =IFERROR(J12/H12,0) -> 0 | J12: =E12-G12 -> 0 | K12: =SUMIF('Che.-Prod'!A:A,Used_before_Trf!A12,'Che.-Prod'!D:D) -> 0 | L12: =IFERROR(M12/K12,0) -> 0 | M12: =SUMIF('Che.-Prod'!A:A,Used_before_Trf!A12,'Che.-Prod'!F:F) -> 0 | N12: =SUMIF('Che.-Prod'!A:A,Used_before_Trf!A12,'Che.-Prod'!G:G) -> 0 | O12: =IF(N12=0,0,P12/N12) -> 0 | P12: =SUMIF('Che.-Prod'!A:A,Used_before_Trf!A12,'Che.-Prod'!H:H) -> 0 | Q12: =SUMIF('Che.-Prod'!A:A,Used_before_Trf!A12,'Che.-Prod'!P:P) -> 0 | R12: =IF(Q12=0,0,S12/Q12) -> 0 | S12: =SUMIF('Che.-Prod'!A:A,Used_before_Trf!A12,'Che.-Prod'!R:R) -> 0 | T12: =H12+K12+N12-Q12 -> 0 | U12: =IF(T12=0,0,V12/T12) -> 0 | V12: =J12+M12+P12-S12 -> 0 | W12: =SUMIF('CHE-last month'!$A:$A,Used_before_Trf!A12,'CHE-last month'!C:C) -> 0 | X12: =IF(W12=0,0,Y12/W12) -> 0 | Y12: =SUMIF('CHE-last month'!$A:$A,Used_before_Trf!A12,'CHE-last month'!E:E) -> 0 | Z12: =+AC12+AF12+AI12 -> 0 | AA12: =IF(Z12=0,0,AB12/Z12) -> 0 | AB12: =+AE12+AH12+AK12 -> 0 | AC12: =SUMIFS(BalCom!M:M,BalCom!N:N,Used_before_Trf!A12,BalCom!C:C,Used_before_Trf!$AC$1) -> 0 | AD12: =IF(AC12=0,0,AE12/AC12) -> 0 | AE12: =SUMIFS(BalCom!P:P,BalCom!N:N,Used_before_Trf!A12,BalCom!C:C,Used_before_Trf!$AC$1) -> 0 | AF12: =SUMIFS(BalDis!I:I,BalDis!J:J,Used_before_Trf!A12) -> 0 | AG12: =IF(AF12=0,0,AH12/AF12) -> 0 | AH12: =SUMIFS(BalDis!L:L,BalDis!J:J,Used_before_Trf!A12) -> 0 | AI12: =SUMIFS(BalDip!$N$49:$N$75,BalDip!$C$49:$C$75,Used_before_Trf!A12)+SUMIFS(BalDip!$N$134:$N$157,BalDip!$C$134:$C$157,Used_before_Trf!A12) -> 0 | AJ12: =IF(AI12=0,0,AK12/AI12) -> 0 | AK12: =SUMIFS(BalDip!$N$80:$N$106,BalDip!$C$80:$C$106,Used_before_Trf!A12)+SUMIFS(BalDip!$N$161:$N$184,BalDip!$C$161:$C$184,Used_before_Trf!A12) -> 0 | AL12: =+T12+W12-Z12 -> 0 | AM12: =IF(AL12=0,0,AN12/AL12) -> 0 | AN12: =+V12+Y12-AB12 -> 0 | AO12: =AM12-U12 -> 0
A13: CH112 | B13: TRUCOAT NR 12 (200KG/DRUM) MOQ=16,000KG/TRIP | C13: =SUMIF('Che-Store'!A:A,Used_before_Trf!A13,'Che-Store'!AC:AC)+SUMIF('Che-Comp'!A:A,Used_before_Trf!A13,'Che-Comp'!AC:AC) -> 0 | D13: =IFERROR(E13/C13,0) -> 0 | E13: =SUMIF('Che-Store'!A:A,Used_before_Trf!A13,'Che-Store'!AE:AE)+SUMIF('Che-Comp'!A:A,Used_before_Trf!A13,'Che-Comp'!AE:AE) -> 0 | F13: =SUMIFS('Che-Comp'!F:F,'Che-Comp'!$A:$A,Used_before_Trf!$A13) -> 0 | G13: =SUMIFS('Che-Comp'!G:G,'Che-Comp'!$A:$A,Used_before_Trf!$A13) -> 0 | H13: =C13-F13 -> 0 | I13: =IFERROR(J13/H13,0) -> 0 | J13: =E13-G13 -> 0 | K13: =SUMIF('Che.-Prod'!A:A,Used_before_Trf!A13,'Che.-Prod'!D:D) -> 0 | L13: =IFERROR(M13/K13,0) -> 0 | M13: =SUMIF('Che.-Prod'!A:A,Used_before_Trf!A13,'Che.-Prod'!F:F) -> 0 | N13: =SUMIF('Che.-Prod'!A:A,Used_before_Trf!A13,'Che.-Prod'!G:G) -> 0 | O13: =IF(N13=0,0,P13/N13) -> 0 | P13: =SUMIF('Che.-Prod'!A:A,Used_before_Trf!A13,'Che.-Prod'!H:H) -> 0 | Q13: =SUMIF('Che.-Prod'!A:A,Used_before_Trf!A13,'Che.-Prod'!P:P) -> 0 | R13: =IF(Q13=0,0,S13/Q13) -> 0 | S13: =SUMIF('Che.-Prod'!A:A,Used_before_Trf!A13,'Che.-Prod'!R:R) -> 0 | T13: =H13+K13+N13-Q13 -> 0 | U13: =IF(T13=0,0,V13/T13) -> 0 | V13: =J13+M13+P13-S13 -> 0 | W13: =SUMIF('CHE-last month'!$A:$A,Used_before_Trf!A13,'CHE-last month'!C:C) -> 0 | X13: =IF(W13=0,0,Y13/W13) -> 0 | Y13: =SUMIF('CHE-last month'!$A:$A,Used_before_Trf!A13,'CHE-last month'!E:E) -> 0 | Z13: =+AC13+AF13+AI13 -> 0 | AA13: =IF(Z13=0,0,AB13/Z13) -> 0 | AB13: =+AE13+AH13+AK13 -> 0 | AC13: =SUMIFS(BalCom!M:M,BalCom!N:N,Used_before_Trf!A13,BalCom!C:C,Used_before_Trf!$AC$1) -> 0 | AD13: =IF(AC13=0,0,AE13/AC13) -> 0 | AE13: =SUMIFS(BalCom!P:P,BalCom!N:N,Used_before_Trf!A13,BalCom!C:C,Used_before_Trf!$AC$1) -> 0 | AF13: =SUMIFS(BalDis!I:I,BalDis!J:J,Used_before_Trf!A13) -> 0 | AG13: =IF(AF13=0,0,AH13/AF13) -> 0 | AH13: =SUMIFS(BalDis!L:L,BalDis!J:J,Used_before_Trf!A13) -> 0 | AI13: =SUMIFS(BalDip!$N$49:$N$75,BalDip!$C$49:$C$75,Used_before_Trf!A13)+SUMIFS(BalDip!$N$134:$N$157,BalDip!$C$134:$C$157,Used_before_Trf!A13) -> 0 | AJ13: =IF(AI13=0,0,AK13/AI13) -> 0 | AK13: =SUMIFS(BalDip!$N$80:$N$106,BalDip!$C$80:$C$106,Used_before_Trf!A13)+SUMIFS(BalDip!$N$161:$N$184,BalDip!$C$161:$C$184,Used_before_Trf!A13) -> 0 | AL13: =+T13+W13-Z13 -> 0 | AM13: =IF(AL13=0,0,AN13/AL13) -> 0 | AN13: =+V13+Y13-AB13 -> 0 | AO13: =AM13-U13 -> 0
A14: CH113 | B14: CALCIUM NITRATE LIQUOR 54- 56% (300KG/DRUM)-MEYCHERN | C14: =SUMIF('Che-Store'!A:A,Used_before_Trf!A14,'Che-Store'!AC:AC)+SUMIF('Che-Comp'!A:A,Used_before_Trf!A14,'Che-Comp'!AC:AC) -> 0 | D14: =IFERROR(E14/C14,0) -> 0 | E14: =SUMIF('Che-Store'!A:A,Used_before_Trf!A14,'Che-Store'!AE:AE)+SUMIF('Che-Comp'!A:A,Used_before_Trf!A14,'Che-Comp'!AE:AE) -> 0 | F14: =SUMIFS('Che-Comp'!F:F,'Che-Comp'!$A:$A,Used_before_Trf!$A14) -> 0 | G14: =SUMIFS('Che-Comp'!G:G,'Che-Comp'!$A:$A,Used_before_Trf!$A14) -> 0 | H14: =C14-F14 -> 0 | I14: =IFERROR(J14/H14,0) -> 0 | J14: =E14-G14 -> 0 | K14: =SUMIF('Che.-Prod'!A:A,Used_before_Trf!A14,'Che.-Prod'!D:D) -> 0 | L14: =IFERROR(M14/K14,0) -> 0 | M14: =SUMIF('Che.-Prod'!A:A,Used_before_Trf!A14,'Che.-Prod'!F:F) -> 0 | N14: =SUMIF('Che.-Prod'!A:A,Used_before_Trf!A14,'Che.-Prod'!G:G) -> 0 | O14: =IF(N14=0,0,P14/N14) -> 0 | P14: =SUMIF('Che.-Prod'!A:A,Used_before_Trf!A14,'Che.-Prod'!H:H) -> 0 | Q14: =SUMIF('Che.-Prod'!A:A,Used_before_Trf!A14,'Che.-Prod'!P:P) -> 0 | R14: =IF(Q14=0,0,S14/Q14) -> 0 | S14: =SUMIF('Che.-Prod'!A:A,Used_before_Trf!A14,'Che.-Prod'!R:R) -> 0 | T14: =H14+K14+N14-Q14 -> 0 | U14: =IF(T14=0,0,V14/T14) -> 0 | V14: =J14+M14+P14-S14 -> 0 | W14: =SUMIF('CHE-last month'!$A:$A,Used_before_Trf!A14,'CHE-last month'!C:C) -> 0 | X14: =IF(W14=0,0,Y14/W14) -> 0 | Y14: =SUMIF('CHE-last month'!$A:$A,Used_before_Trf!A14,'CHE-last month'!E:E) -> 0 | Z14: =+AC14+AF14+AI14 -> 0 | AA14: =IF(Z14=0,0,AB14/Z14) -> 0 | AB14: =+AE14+AH14+AK14 -> 0 | AC14: =SUMIFS(BalCom!M:M,BalCom!N:N,Used_before_Trf!A14,BalCom!C:C,Used_before_Trf!$AC$1) -> 0 | AD14: =IF(AC14=0,0,AE14/AC14) -> 0 | AE14: =SUMIFS(BalCom!P:P,BalCom!N:N,Used_before_Trf!A14,BalCom!C:C,Used_before_Trf!$AC$1) -> 0 | AF14: =SUMIFS(BalDis!I:I,BalDis!J:J,Used_before_Trf!A14) -> 0 | AG14: =IF(AF14=0,0,AH14/AF14) -> 0 | AH14: =SUMIFS(BalDis!L:L,BalDis!J:J,Used_before_Trf!A14) -> 0 | AI14: =SUMIFS(BalDip!$N$49:$N$75,BalDip!$C$49:$C$75,Used_before_Trf!A14)+SUMIFS(BalDip!$N$134:$N$157,BalDip!$C$134:$C$157,Used_before_Trf!A14) -> 0 | AJ14: =IF(AI14=0,0,AK14/AI14) -> 0 | AK14: =SUMIFS(BalDip!$N$80:$N$106,BalDip!$C$80:$C$106,Used_before_Trf!A14)+SUMIFS(BalDip!$N$161:$N$184,BalDip!$C$161:$C$184,Used_before_Trf!A14) -> 0 | AL14: =+T14+W14-Z14 -> 0 | AM14: =IF(AL14=0,0,AN14/AL14) -> 0 | AN14: =+V14+Y14-AB14 -> 0 | AO14: =AM14-U14 -> 0
A15: CH114 | B15: TRANSCURE ZDB50 (225KG/DRUM) | C15: =SUMIF('Che-Store'!A:A,Used_before_Trf!A15,'Che-Store'!AC:AC)+SUMIF('Che-Comp'!A:A,Used_before_Trf!A15,'Che-Comp'!AC:AC) -> 0 | D15: =IFERROR(E15/C15,0) -> 0 | E15: =SUMIF('Che-Store'!A:A,Used_before_Trf!A15,'Che-Store'!AE:AE)+SUMIF('Che-Comp'!A:A,Used_before_Trf!A15,'Che-Comp'!AE:AE) -> 0 | F15: =SUMIFS('Che-Comp'!F:F,'Che-Comp'!$A:$A,Used_before_Trf!$A15) -> 0 | G15: =SUMIFS('Che-Comp'!G:G,'Che-Comp'!$A:$A,Used_before_Trf!$A15) -> 0 | H15: =C15-F15 -> 0 | I15: =IFERROR(J15/H15,0) -> 0 | J15: =E15-G15 -> 0 | K15: =SUMIF('Che.-Prod'!A:A,Used_before_Trf!A15,'Che.-Prod'!D:D) -> 0 | L15: =IFERROR(M15/K15,0) -> 0 | M15: =SUMIF('Che.-Prod'!A:A,Used_before_Trf!A15,'Che.-Prod'!F:F) -> 0 | N15: =SUMIF('Che.-Prod'!A:A,Used_before_Trf!A15,'Che.-Prod'!G:G) -> 0 | O15: =IF(N15=0,0,P15/N15) -> 0 | P15: =SUMIF('Che.-Prod'!A:A,Used_before_Trf!A15,'Che.-Prod'!H:H) -> 0 | Q15: =SUMIF('Che.-Prod'!A:A,Used_before_Trf!A15,'Che.-Prod'!P:P) -> 0 | R15: =IF(Q15=0,0,S15/Q15) -> 0 | S15: =SUMIF('Che.-Prod'!A:A,Used_before_Trf!A15,'Che.-Prod'!R:R) -> 0 | T15: =H15+K15+N15-Q15 -> 0 | U15: =IF(T15=0,0,V15/T15) -> 0 | V15: =J15+M15+P15-S15 -> 0 | W15: =SUMIF('CHE-last month'!$A:$A,Used_before_Trf!A15,'CHE-last month'!C:C) -> 0 | X15: =IF(W15=0,0,Y15/W15) -> 0 | Y15: =SUMIF('CHE-last month'!$A:$A,Used_before_Trf!A15,'CHE-last month'!E:E) -> 0 | Z15: =+AC15+AF15+AI15 -> 0 | AA15: =IF(Z15=0,0,AB15/Z15) -> 0 | AB15: =+AE15+AH15+AK15 -> 0 | AC15: =SUMIFS(BalCom!M:M,BalCom!N:N,Used_before_Trf!A15,BalCom!C:C,Used_before_Trf!$AC$1) -> 0 | AD15: =IF(AC15=0,0,AE15/AC15) -> 0 | AE15: =SUMIFS(BalCom!P:P,BalCom!N:N,Used_before_Trf!A15,BalCom!C:C,Used_before_Trf!$AC$1) -> 0 | AF15: =SUMIFS(BalDis!I:I,BalDis!J:J,Used_before_Trf!A15) -> 0 | AG15: =IF(AF15=0,0,AH15/AF15) -> 0 | AH15: =SUMIFS(BalDis!L:L,BalDis!J:J,Used_before_Trf!A15) -> 0 | AI15: =SUMIFS(BalDip!$N$49:$N$75,BalDip!$C$49:$C$75,Used_before_Trf!A15)+SUMIFS(BalDip!$N$134:$N$157,BalDip!$C$134:$C$157,Used_before_Trf!A15) -> 0 | AJ15: =IF(AI15=0,0,AK15/AI15) -> 0 | AK15: =SUMIFS(BalDip!$N$80:$N$106,BalDip!$C$80:$C$106,Used_before_Trf!A15)+SUMIFS(BalDip!$N$161:$N$184,BalDip!$C$161:$C$184,Used_before_Trf!A15) -> 0 | AL15: =+T15+W15-Z15 -> 0 | AM15: =IF(AL15=0,0,AN15/AL15) -> 0 | AN15: =+V15+Y15-AB15 -> 0 | AO15: =AM15-U15 -> 0
A16: CH115 | B16: TRANSACT ZNO60 (250KG/DRUM) | C16: =SUMIF('Che-Store'!A:A,Used_before_Trf!A16,'Che-Store'!AC:AC)+SUMIF('Che-Comp'!A:A,Used_before_Trf!A16,'Che-Comp'!AC:AC) -> 0 | D16: =IFERROR(E16/C16,0) -> 0 | E16: =SUMIF('Che-Store'!A:A,Used_before_Trf!A16,'Che-Store'!AE:AE)+SUMIF('Che-Comp'!A:A,Used_before_Trf!A16,'Che-Comp'!AE:AE) -> 0 | F16: =SUMIFS('Che-Comp'!F:F,'Che-Comp'!$A:$A,Used_before_Trf!$A16) -> 0 | G16: =SUMIFS('Che-Comp'!G:G,'Che-Comp'!$A:$A,Used_before_Trf!$A16) -> 0 | H16: =C16-F16 -> 0 | I16: =IFERROR(J16/H16,0) -> 0 | J16: =E16-G16 -> 0 | K16: =SUMIF('Che.-Prod'!A:A,Used_before_Trf!A16,'Che.-Prod'!D:D) -> 0 | L16: =IFERROR(M16/K16,0) -> 0 | M16: =SUMIF('Che.-Prod'!A:A,Used_before_Trf!A16,'Che.-Prod'!F:F) -> 0 | N16: =SUMIF('Che.-Prod'!A:A,Used_before_Trf!A16,'Che.-Prod'!G:G) -> 0 | O16: =IF(N16=0,0,P16/N16) -> 0 | P16: =SUMIF('Che.-Prod'!A:A,Used_before_Trf!A16,'Che.-Prod'!H:H) -> 0 | Q16: =SUMIF('Che.-Prod'!A:A,Used_before_Trf!A16,'Che.-Prod'!P:P) -> 0 | R16: =IF(Q16=0,0,S16/Q16) -> 0 | S16: =SUMIF('Che.-Prod'!A:A,Used_before_Trf!A16,'Che.-Prod'!R:R) -> 0 | T16: =H16+K16+N16-Q16 -> 0 | U16: =IF(T16=0,0,V16/T16) -> 0 | V16: =J16+M16+P16-S16 -> 0 | W16: =SUMIF('CHE-last month'!$A:$A,Used_before_Trf!A16,'CHE-last month'!C:C) -> 0 | X16: =IF(W16=0,0,Y16/W16) -> 0 | Y16: =SUMIF('CHE-last month'!$A:$A,Used_before_Trf!A16,'CHE-last month'!E:E) -> 0 | Z16: =+AC16+AF16+AI16 -> 0 | AA16: =IF(Z16=0,0,AB16/Z16) -> 0 | AB16: =+AE16+AH16+AK16 -> 0 | AC16: =SUMIFS(BalCom!M:M,BalCom!N:N,Used_before_Trf!A16,BalCom!C:C,Used_before_Trf!$AC$1) -> 0 | AD16: =IF(AC16=0,0,AE16/AC16) -> 0 | AE16: =SUMIFS(BalCom!P:P,BalCom!N:N,Used_before_Trf!A16,BalCom!C:C,Used_before_Trf!$AC$1) -> 0 | AF16: =SUMIFS(BalDis!I:I,BalDis!J:J,Used_before_Trf!A16) -> 0 | AG16: =IF(AF16=0,0,AH16/AF16) -> 0 | AH16: =SUMIFS(BalDis!L:L,BalDis!J:J,Used_before_Trf!A16) -> 0 | AI16: =SUMIFS(BalDip!$N$49:$N$75,BalDip!$C$49:$C$75,Used_before_Trf!A16)+SUMIFS(BalDip!$N$134:$N$157,BalDip!$C$134:$C$157,Used_before_Trf!A16) -> 0 | AJ16: =IF(AI16=0,0,AK16/AI16) -> 0 | AK16: =SUMIFS(BalDip!$N$80:$N$106,BalDip!$C$80:$C$106,Used_before_Trf!A16)+SUMIFS(BalDip!$N$161:$N$184,BalDip!$C$161:$C$184,Used_before_Trf!A16) -> 0 | AL16: =+T16+W16-Z16 -> 0 | AM16: =IF(AL16=0,0,AN16/AL16) -> 0 | AN16: =+V16+Y16-AB16 -> 0 | AO16: =AM16-U16 -> 0
A17: CH116 | B17: TRANSCURE S60 (250KG/DRUM) | C17: =SUMIF('Che-Store'!A:A,Used_before_Trf!A17,'Che-Store'!AC:AC)+SUMIF('Che-Comp'!A:A,Used_before_Trf!A17,'Che-Comp'!AC:AC) -> 0 | D17: =IFERROR(E17/C17,0) -> 0 | E17: =SUMIF('Che-Store'!A:A,Used_before_Trf!A17,'Che-Store'!AE:AE)+SUMIF('Che-Comp'!A:A,Used_before_Trf!A17,'Che-Comp'!AE:AE) -> 0 | F17: =SUMIFS('Che-Comp'!F:F,'Che-Comp'!$A:$A,Used_before_Trf!$A17) -> 0 | G17: =SUMIFS('Che-Comp'!G:G,'Che-Comp'!$A:$A,Used_before_Trf!$A17) -> 0 | H17: =C17-F17 -> 0 | I17: =IFERROR(J17/H17,0) -> 0 | J17: =E17-G17 -> 0 | K17: =SUMIF('Che.-Prod'!A:A,Used_before_Trf!A17,'Che.-Prod'!D:D) -> 0 | L17: =IFERROR(M17/K17,0) -> 0 | M17: =SUMIF('Che.-Prod'!A:A,Used_before_Trf!A17,'Che.-Prod'!F:F) -> 0 | N17: =SUMIF('Che.-Prod'!A:A,Used_before_Trf!A17,'Che.-Prod'!G:G) -> 0 | O17: =IF(N17=0,0,P17/N17) -> 0 | P17: =SUMIF('Che.-Prod'!A:A,Used_before_Trf!A17,'Che.-Prod'!H:H) -> 0 | Q17: =SUMIF('Che.-Prod'!A:A,Used_before_Trf!A17,'Che.-Prod'!P:P) -> 0 | R17: =IF(Q17=0,0,S17/Q17) -> 0 | S17: =SUMIF('Che.-Prod'!A:A,Used_before_Trf!A17,'Che.-Prod'!R:R) -> 0 | T17: =H17+K17+N17-Q17 -> 0 | U17: =IF(T17=0,0,V17/T17) -> 0 | V17: =J17+M17+P17-S17 -> 0 | W17: =SUMIF('CHE-last month'!$A:$A,Used_before_Trf!A17,'CHE-last month'!C:C) -> 0 | X17: =IF(W17=0,0,Y17/W17) -> 0 | Y17: =SUMIF('CHE-last month'!$A:$A,Used_before_Trf!A17,'CHE-last month'!E:E) -> 0 | Z17: =+AC17+AF17+AI17 -> 0 | AA17: =IF(Z17=0,0,AB17/Z17) -> 0 | AB17: =+AE17+AH17+AK17 -> 0 | AC17: =SUMIFS(BalCom!M:M,BalCom!N:N,Used_before_Trf!A17,BalCom!C:C,Used_before_Trf!$AC$1) -> 0 | AD17: =IF(AC17=0,0,AE17/AC17) -> 0 | AE17: =SUMIFS(BalCom!P:P,BalCom!N:N,Used_before_Trf!A17,BalCom!C:C,Used_before_Trf!$AC$1) -> 0 | AF17: =SUMIFS(BalDis!I:I,BalDis!J:J,Used_before_Trf!A17) -> 0 | AG17: =IF(AF17=0,0,AH17/AF17) -> 0 | AH17: =SUMIFS(BalDis!L:L,BalDis!J:J,Used_before_Trf!A17) -> 0 | AI17: =SUMIFS(BalDip!$N$49:$N$75,BalDip!$C$49:$C$75,Used_before_Trf!A17)+SUMIFS(BalDip!$N$134:$N$157,BalDip!$C$134:$C$157,Used_before_Trf!A17) -> 0 | AJ17: =IF(AI17=0,0,AK17/AI17) -> 0 | AK17: =SUMIFS(BalDip!$N$80:$N$106,BalDip!$C$80:$C$106,Used_before_Trf!A17)+SUMIFS(BalDip!$N$161:$N$184,BalDip!$C$161:$C$184,Used_before_Trf!A17) -> 0 | AL17: =+T17+W17-Z17 -> 0 | AM17: =IF(AL17=0,0,AN17/AL17) -> 0 | AN17: =+V17+Y17-AB17 -> 0 | AO17: =AM17-U17 -> 0
A18: CH117 | B18: TRANSTINT TIO270(250KG/DRUM) | C18: =SUMIF('Che-Store'!A:A,Used_before_Trf!A18,'Che-Store'!AC:AC)+SUMIF('Che-Comp'!A:A,Used_before_Trf!A18,'Che-Comp'!AC:AC) -> 0 | D18: =IFERROR(E18/C18,0) -> 0 | E18: =SUMIF('Che-Store'!A:A,Used_before_Trf!A18,'Che-Store'!AE:AE)+SUMIF('Che-Comp'!A:A,Used_before_Trf!A18,'Che-Comp'!AE:AE) -> 0 | F18: =SUMIFS('Che-Comp'!F:F,'Che-Comp'!$A:$A,Used_before_Trf!$A18) -> 0 | G18: =SUMIFS('Che-Comp'!G:G,'Che-Comp'!$A:$A,Used_before_Trf!$A18) -> 0 | H18: =C18-F18 -> 0 | I18: =IFERROR(J18/H18,0) -> 0 | J18: =E18-G18 -> 0 | K18: =SUMIF('Che.-Prod'!A:A,Used_before_Trf!A18,'Che.-Prod'!D:D) -> 0 | L18: =IFERROR(M18/K18,0) -> 0 | M18: =SUMIF('Che.-Prod'!A:A,Used_before_Trf!A18,'Che.-Prod'!F:F) -> 0 | N18: =SUMIF('Che.-Prod'!A:A,Used_before_Trf!A18,'Che.-Prod'!G:G) -> 0 | O18: =IF(N18=0,0,P18/N18) -> 0 | P18: =SUMIF('Che.-Prod'!A:A,Used_before_Trf!A18,'Che.-Prod'!H:H) -> 0 | Q18: =SUMIF('Che.-Prod'!A:A,Used_before_Trf!A18,'Che.-Prod'!P:P) -> 0 | R18: =IF(Q18=0,0,S18/Q18) -> 0 | S18: =SUMIF('Che.-Prod'!A:A,Used_before_Trf!A18,'Che.-Prod'!R:R) -> 0 | T18: =H18+K18+N18-Q18 -> 0 | U18: =IF(T18=0,0,V18/T18) -> 0 | V18: =J18+M18+P18-S18 -> 0 | W18: =SUMIF('CHE-last month'!$A:$A,Used_before_Trf!A18,'CHE-last month'!C:C) -> 0 | X18: =IF(W18=0,0,Y18/W18) -> 0 | Y18: =SUMIF('CHE-last month'!$A:$A,Used_before_Trf!A18,'CHE-last month'!E:E) -> 0 | Z18: =+AC18+AF18+AI18 -> 0 | AA18: =IF(Z18=0,0,AB18/Z18) -> 0 | AB18: =+AE18+AH18+AK18 -> 0 | AC18: =SUMIFS(BalCom!M:M,BalCom!N:N,Used_before_Trf!A18,BalCom!C:C,Used_before_Trf!$AC$1) -> 0 | AD18: =IF(AC18=0,0,AE18/AC18) -> 0 | AE18: =SUMIFS(BalCom!P:P,BalCom!N:N,Used_before_Trf!A18,BalCom!C:C,Used_before_Trf!$AC$1) -> 0 | AF18: =SUMIFS(BalDis!I:I,BalDis!J:J,Used_before_Trf!A18) -> 0 | AG18: =IF(AF18=0,0,AH18/AF18) -> 0 | AH18: =SUMIFS(BalDis!L:L,BalDis!J:J,Used_before_Trf!A18) -> 0 | AI18: =SUMIFS(BalDip!$N$49:$N$75,BalDip!$C$49:$C$75,Used_before_Trf!A18)+SUMIFS(BalDip!$N$134:$N$157,BalDip!$C$134:$C$157,Used_before_Trf!A18) -> 0 | AJ18: =IF(AI18=0,0,AK18/AI18) -> 0 | AK18: =SUMIFS(BalDip!$N$80:$N$106,BalDip!$C$80:$C$106,Used_before_Trf!A18)+SUMIFS(BalDip!$N$161:$N$184,BalDip!$C$161:$C$184,Used_before_Trf!A18) -> 0 | AL18: =+T18+W18-Z18 -> 0 | AM18: =IF(AL18=0,0,AN18/AL18) -> 0 | AN18: =+V18+Y18-AB18 -> 0 | AO18: =AM18-U18 -> 0
A19: CH127 | B19: CALCIUM NITRATE LIQUOR 54- 56% (L- 089B) (25,000KG/TANK) | C19: =SUMIF('Che-Store'!A:A,Used_before_Trf!A19,'Che-Store'!AC:AC)+SUMIF('Che-Comp'!A:A,Used_before_Trf!A19,'Che-Comp'!AC:AC) -> 0 | D19: =IFERROR(E19/C19,0) -> 0 | E19: =SUMIF('Che-Store'!A:A,Used_before_Trf!A19,'Che-Store'!AE:AE)+SUMIF('Che-Comp'!A:A,Used_before_Trf!A19,'Che-Comp'!AE:AE) -> 0 | F19: =SUMIFS('Che-Comp'!F:F,'Che-Comp'!$A:$A,Used_before_Trf!$A19) -> 0 | G19: =SUMIFS('Che-Comp'!G:G,'Che-Comp'!$A:$A,Used_before_Trf!$A19) -> 0 | H19: =C19-F19 -> 0 | I19: =IFERROR(J19/H19,0) -> 0 | J19: =E19-G19 -> 0 | K19: =SUMIF('Che.-Prod'!A:A,Used_before_Trf!A19,'Che.-Prod'!D:D) -> 0 | L19: =IFERROR(M19/K19,0) -> 0 | M19: =SUMIF('Che.-Prod'!A:A,Used_before_Trf!A19,'Che.-Prod'!F:F) -> 0 | N19: =SUMIF('Che.-Prod'!A:A,Used_before_Trf!A19,'Che.-Prod'!G:G) -> 0 | O19: =IF(N19=0,0,P19/N19) -> 0 | P19: =SUMIF('Che.-Prod'!A:A,Used_before_Trf!A19,'Che.-Prod'!H:H) -> 0 | Q19: =SUMIF('Che.-Prod'!A:A,Used_before_Trf!A19,'Che.-Prod'!P:P) -> 0 | R19: =IF(Q19=0,0,S19/Q19) -> 0 | S19: =SUMIF('Che.-Prod'!A:A,Used_before_Trf!A19,'Che.-Prod'!R:R) -> 0 | T19: =H19+K19+N19-Q19 -> 0 | U19: =IF(T19=0,0,V19/T19) -> 0 | V19: =J19+M19+P19-S19 -> 0 | W19: =SUMIF('CHE-last month'!$A:$A,Used_before_Trf!A19,'CHE-last month'!C:C) -> 0 | X19: =IF(W19=0,0,Y19/W19) -> 0 | Y19: =SUMIF('CHE-last month'!$A:$A,Used_before_Trf!A19,'CHE-last month'!E:E) -> 0 | Z19: =+AC19+AF19+AI19 -> 0 | AA19: =IF(Z19=0,0,AB19/Z19) -> 0 | AB19: =+AE19+AH19+AK19 -> 0 | AC19: =SUMIFS(BalCom!M:M,BalCom!N:N,Used_before_Trf!A19,BalCom!C:C,Used_before_Trf!$AC$1) -> 0 | AD19: =IF(AC19=0,0,AE19/AC19) -> 0 | AE19: =SUMIFS(BalCom!P:P,BalCom!N:N,Used_before_Trf!A19,BalCom!C:C,Used_before_Trf!$AC$1) -> 0 | AF19: =SUMIFS(BalDis!I:I,BalDis!J:J,Used_before_Trf!A19) -> 0 | AG19: =IF(AF19=0,0,AH19/AF19) -> 0 | AH19: =SUMIFS(BalDis!L:L,BalDis!J:J,Used_before_Trf!A19) -> 0 | AI19: =SUMIFS(BalDip!$N$49:$N$75,BalDip!$C$49:$C$75,Used_before_Trf!A19)+SUMIFS(BalDip!$N$134:$N$157,BalDip!$C$134:$C$157,Used_before_Trf!A19) -> 0 | AJ19: =IF(AI19=0,0,AK19/AI19) -> 0 | AK19: =SUMIFS(BalDip!$N$80:$N$106,BalDip!$C$80:$C$106,Used_before_Trf!A19)+SUMIFS(BalDip!$N$161:$N$184,BalDip!$C$161:$C$184,Used_before_Trf!A19) -> 0 | AL19: =+T19+W19-Z19 -> 0 | AM19: =IF(AL19=0,0,AN19/AL19) -> 0 | AN19: =+V19+Y19-AB19 -> 0 | AO19: =AM19-U19 -> 0
A20: CH128 | B20: FARSPERSE BLUE MPL1523 (20 KGS/PAIL) | C20: =SUMIF('Che-Store'!A:A,Used_before_Trf!A20,'Che-Store'!AC:AC)+SUMIF('Che-Comp'!A:A,Used_before_Trf!A20,'Che-Comp'!AC:AC) -> 77.74 | D20: =IFERROR(E20/C20,0) -> 216.34127 | E20: =SUMIF('Che-Store'!A:A,Used_before_Trf!A20,'Che-Store'!AE:AE)+SUMIF('Che-Comp'!A:A,Used_before_Trf!A20,'Che-Comp'!AE:AE) -> 16818.37 | F20: =SUMIFS('Che-Comp'!F:F,'Che-Comp'!$A:$A,Used_before_Trf!$A20) -> 0 | G20: =SUMIFS('Che-Comp'!G:G,'Che-Comp'!$A:$A,Used_before_Trf!$A20) -> 0 | H20: =C20-F20 -> 77.74 | I20: =IFERROR(J20/H20,0) -> 216.34127 | J20: =E20-G20 -> 16818.37 | K20: =SUMIF('Che.-Prod'!A:A,Used_before_Trf!A20,'Che.-Prod'!D:D) -> 0 | L20: =IFERROR(M20/K20,0) -> 0 | M20: =SUMIF('Che.-Prod'!A:A,Used_before_Trf!A20,'Che.-Prod'!F:F) -> 0 | N20: =SUMIF('Che.-Prod'!A:A,Used_before_Trf!A20,'Che.-Prod'!G:G) -> 0 | O20: =IF(N20=0,0,P20/N20) -> 0 | P20: =SUMIF('Che.-Prod'!A:A,Used_before_Trf!A20,'Che.-Prod'!H:H) -> 0 | Q20: =SUMIF('Che.-Prod'!A:A,Used_before_Trf!A20,'Che.-Prod'!P:P) -> 0 | R20: =IF(Q20=0,0,S20/Q20) -> 0 | S20: =SUMIF('Che.-Prod'!A:A,Used_before_Trf!A20,'Che.-Prod'!R:R) -> 0 | T20: =H20+K20+N20-Q20 -> 77.74 | U20: =IF(T20=0,0,V20/T20) -> 216.34127 | V20: =J20+M20+P20-S20 -> 16818.37 | W20: =SUMIF('CHE-last month'!$A:$A,Used_before_Trf!A20,'CHE-last month'!C:C) -> 45.374652 | X20: =IF(W20=0,0,Y20/W20) -> 214.79063 | Y20: =SUMIF('CHE-last month'!$A:$A,Used_before_Trf!A20,'CHE-last month'!E:E) -> 9746.05 | Z20: =+AC20+AF20+AI20 -> 6.5014368 | AA20: =IF(Z20=0,0,AB20/Z20) -> 216.34295 | AB20: =+AE20+AH20+AK20 -> 1406.54 | AC20: =SUMIFS(BalCom!M:M,BalCom!N:N,Used_before_Trf!A20,BalCom!C:C,Used_before_Trf!$AC$1) -> 6.5014368 | AD20: =IF(AC20=0,0,AE20/AC20) -> 216.34295 | AE20: =SUMIFS(BalCom!P:P,BalCom!N:N,Used_before_Trf!A20,BalCom!C:C,Used_before_Trf!$AC$1) -> 1406.54 | AF20: =SUMIFS(BalDis!I:I,BalDis!J:J,Used_before_Trf!A20) -> 0 | AG20: =IF(AF20=0,0,AH20/AF20) -> 0 | AH20: =SUMIFS(BalDis!L:L,BalDis!J:J,Used_before_Trf!A20) -> 0 | AI20: =SUMIFS(BalDip!$N$49:$N$75,BalDip!$C$49:$C$75,Used_before_Trf!A20)+SUMIFS(BalDip!$N$134:$N$157,BalDip!$C$134:$C$157,Used_before_Trf!A20) -> 0 | AJ20: =IF(AI20=0,0,AK20/AI20) -> 0 | AK20: =SUMIFS(BalDip!$N$80:$N$106,BalDip!$C$80:$C$106,Used_before_Trf!A20)+SUMIFS(BalDip!$N$161:$N$184,BalDip!$C$161:$C$184,Used_before_Trf!A20) -> 0 | AL20: =+T20+W20-Z20 -> 116.61322 | AM20: =IF(AL20=0,0,AN20/AL20) -> 215.73781 | AN20: =+V20+Y20-AB20 -> 25157.88 | AO20: =AM20-U20 -> -0.60345263
A21: CH129 | B21: FARSPERSE BLACK PB-ZBX (20 KGS/PAIL) | C21: =SUMIF('Che-Store'!A:A,Used_before_Trf!A21,'Che-Store'!AC:AC)+SUMIF('Che-Comp'!A:A,Used_before_Trf!A21,'Che-Comp'!AC:AC) -> 0 | D21: =IFERROR(E21/C21,0) -> 0 | E21: =SUMIF('Che-Store'!A:A,Used_before_Trf!A21,'Che-Store'!AE:AE)+SUMIF('Che-Comp'!A:A,Used_before_Trf!A21,'Che-Comp'!AE:AE) -> 0 | F21: =SUMIFS('Che-Comp'!F:F,'Che-Comp'!$A:$A,Used_before_Trf!$A21) -> 0 | G21: =SUMIFS('Che-Comp'!G:G,'Che-Comp'!$A:$A,Used_before_Trf!$A21) -> 0 | H21: =C21-F21 -> 0 | I21: =IFERROR(J21/H21,0) -> 0 | J21: =E21-G21 -> 0 | K21: =SUMIF('Che.-Prod'!A:A,Used_before_Trf!A21,'Che.-Prod'!D:D) -> 0 | L21: =IFERROR(M21/K21,0) -> 0 | M21: =SUMIF('Che.-Prod'!A:A,Used_before_Trf!A21,'Che.-Prod'!F:F) -> 0 | N21: =SUMIF('Che.-Prod'!A:A,Used_before_Trf!A21,'Che.-Prod'!G:G) -> 0 | O21: =IF(N21=0,0,P21/N21) -> 0 | P21: =SUMIF('Che.-Prod'!A:A,Used_before_Trf!A21,'Che.-Prod'!H:H) -> 0 | Q21: =SUMIF('Che.-Prod'!A:A,Used_before_Trf!A21,'Che.-Prod'!P:P) -> 0 | R21: =IF(Q21=0,0,S21/Q21) -> 0 | S21: =SUMIF('Che.-Prod'!A:A,Used_before_Trf!A21,'Che.-Prod'!R:R) -> 0 | T21: =H21+K21+N21-Q21 -> 0 | U21: =IF(T21=0,0,V21/T21) -> 0 | V21: =J21+M21+P21-S21 -> 0 | W21: =SUMIF('CHE-last month'!$A:$A,Used_before_Trf!A21,'CHE-last month'!C:C) -> 0 | X21: =IF(W21=0,0,Y21/W21) -> 0 | Y21: =SUMIF('CHE-last month'!$A:$A,Used_before_Trf!A21,'CHE-last month'!E:E) -> 0 | Z21: =+AC21+AF21+AI21 -> 0 | AA21: =IF(Z21=0,0,AB21/Z21) -> 0 | AB21: =+AE21+AH21+AK21 -> 0 | AC21: =SUMIFS(BalCom!M:M,BalCom!N:N,Used_before_Trf!A21,BalCom!C:C,Used_before_Trf!$AC$1) -> 0 | AD21: =IF(AC21=0,0,AE21/AC21) -> 0 | AE21: =SUMIFS(BalCom!P:P,BalCom!N:N,Used_before_Trf!A21,BalCom!C:C,Used_before_Trf!$AC$1) -> 0 | AF21: =SUMIFS(BalDis!I:I,BalDis!J:J,Used_before_Trf!A21) -> 0 | AG21: =IF(AF21=0,0,AH21/AF21) -> 0 | AH21: =SUMIFS(BalDis!L:L,BalDis!J:J,Used_before_Trf!A21) -> 0 | AI21: =SUMIFS(BalDip!$N$49:$N$75,BalDip!$C$49:$C$75,Used_before_Trf!A21)+SUMIFS(BalDip!$N$134:$N$157,BalDip!$C$134:$C$157,Used_before_Trf!A21) -> 0 | AJ21: =IF(AI21=0,0,AK21/AI21) -> 0 | AK21: =SUMIFS(BalDip!$N$80:$N$106,BalDip!$C$80:$C$106,Used_before_Trf!A21)+SUMIFS(BalDip!$N$161:$N$184,BalDip!$C$161:$C$184,Used_before_Trf!A21) -> 0 | AL21: =+T21+W21-Z21 -> 0 | AM21: =IF(AL21=0,0,AN21/AL21) -> 0 | AN21: =+V21+Y21-AB21 -> 0 | AO21: =AM21-U21 -> 0
... A71: CH228 | B71: (TEST) MRA-N59 (200KG/DR) - ANTI TACK | C71: =SUMIF('Che-Store'!A:A,Used_before_Trf!A71,'Che-Store'!AC:AC)+SUMIF('Che-Comp'!A:A,Used_before_Trf!A71,'Che-Comp'!AC:AC) -> 0 | D71: =IFERROR(E71/C71,0) -> 0 | E71: =SUMIF('Che-Store'!A:A,Used_before_Trf!A71,'Che-Store'!AE:AE)+SUMIF('Che-Comp'!A:A,Used_before_Trf!A71,'Che-Comp'!AE:AE) -> 0 | F71: =SUMIFS('Che-Comp'!F:F,'Che-Comp'!$A:$A,Used_before_Trf!$A71) -> 0 | G71: =SUMIFS('Che-Comp'!G:G,'Che-Comp'!$A:$A,Used_before_Trf!$A71) -> 0 | H71: =C71-F71 -> 0 | I71: =IFERROR(J71/H71,0) -> 0 | J71: =E71-G71 -> 0 | K71: =SUMIF('Che.-Prod'!A:A,Used_before_Trf!A71,'Che.-Prod'!D:D) -> 0 | L71: =IFERROR(M71/K71,0) -> 0 | M71: =SUMIF('Che.-Prod'!A:A,Used_before_Trf!A71,'Che.-Prod'!F:F) -> 0 | N71: =SUMIF('Che.-Prod'!A:A,Used_before_Trf!A71,'Che.-Prod'!G:G) -> 0 | O71: =IF(N71=0,0,P71/N71) -> 0 | P71: =SUMIF('Che.-Prod'!A:A,Used_before_Trf!A71,'Che.-Prod'!H:H) -> 0 | Q71: =SUMIF('Che.-Prod'!A:A,Used_before_Trf!A71,'Che.-Prod'!P:P) -> 0 | R71: =IF(Q71=0,0,S71/Q71) -> 0 | S71: =SUMIF('Che.-Prod'!A:A,Used_before_Trf!A71,'Che.-Prod'!R:R) -> 0 | T71: =H71+K71+N71-Q71 -> 0 | U71: =IF(T71=0,0,V71/T71) -> 0 | V71: =J71+M71+P71-S71 -> 0 | W71: =SUMIF('CHE-last month'!$A:$A,Used_before_Trf!A71,'CHE-last month'!C:C) -> 0 | X71: =IF(W71=0,0,Y71/W71) -> 0 | Y71: =SUMIF('CHE-last month'!$A:$A,Used_before_Trf!A71,'CHE-last month'!E:E) -> 0 | Z71: =+AC71+AF71+AI71 -> 0 | AA71: =IF(Z71=0,0,AB71/Z71) -> 0 | AB71: =+AE71+AH71+AK71 -> 0 | AC71: =SUMIFS(BalCom!M:M,BalCom!N:N,Used_before_Trf!A71,BalCom!C:C,Used_before_Trf!$AC$1) -> 0 | AD71: =IF(AC71=0,0,AE71/AC71) -> 0 | AE71: =SUMIFS(BalCom!P:P,BalCom!N:N,Used_before_Trf!A71,BalCom!C:C,Used_before_Trf!$AC$1) -> 0 | AF71: =SUMIFS(BalDis!I:I,BalDis!J:J,Used_before_Trf!A71) -> 0 | AG71: =IF(AF71=0,0,AH71/AF71) -> 0 | AH71: =SUMIFS(BalDis!L:L,BalDis!J:J,Used_before_Trf!A71) -> 0 | AI71: =SUMIFS(BalDip!$N$49:$N$75,BalDip!$C$49:$C$75,Used_before_Trf!A71)+SUMIFS(BalDip!$N$134:$N$157,BalDip!$C$134:$C$157,Used_before_Trf!A71) -> 0 | AJ71: =IF(AI71=0,0,AK71/AI71) -> 0 | AK71: =SUMIFS(BalDip!$N$80:$N$106,BalDip!$C$80:$C$106,Used_before_Trf!A71)+SUMIFS(BalDip!$N$161:$N$184,BalDip!$C$161:$C$184,Used_before_Trf!A71) -> 0 | AL71: =+T71+W71-Z71 -> 0 | AM71: =IF(AL71=0,0,AN71/AL71) -> 0 | AN71: =+V71+Y71-AB71 -> 0 | AO71: =AM71-U71 -> 0
A72: CH229 | B72: (TEST) MRC600NB50(1400KG/IBC) MOQ: 23,800KG EXTENDER | C72: =SUMIF('Che-Store'!A:A,Used_before_Trf!A72,'Che-Store'!AC:AC)+SUMIF('Che-Comp'!A:A,Used_before_Trf!A72,'Che-Comp'!AC:AC) -> 0 | D72: =IFERROR(E72/C72,0) -> 0 | E72: =SUMIF('Che-Store'!A:A,Used_before_Trf!A72,'Che-Store'!AE:AE)+SUMIF('Che-Comp'!A:A,Used_before_Trf!A72,'Che-Comp'!AE:AE) -> 0 | F72: =SUMIFS('Che-Comp'!F:F,'Che-Comp'!$A:$A,Used_before_Trf!$A72) -> 0 | G72: =SUMIFS('Che-Comp'!G:G,'Che-Comp'!$A:$A,Used_before_Trf!$A72) -> 0 | H72: =C72-F72 -> 0 | I72: =IFERROR(J72/H72,0) -> 0 | J72: =E72-G72 -> 0 | K72: =SUMIF('Che.-Prod'!A:A,Used_before_Trf!A72,'Che.-Prod'!D:D) -> 0 | L72: =IFERROR(M72/K72,0) -> 0 | M72: =SUMIF('Che.-Prod'!A:A,Used_before_Trf!A72,'Che.-Prod'!F:F) -> 0 | N72: =SUMIF('Che.-Prod'!A:A,Used_before_Trf!A72,'Che.-Prod'!G:G) -> 0 | O72: =IF(N72=0,0,P72/N72) -> 0 | P72: =SUMIF('Che.-Prod'!A:A,Used_before_Trf!A72,'Che.-Prod'!H:H) -> 0 | Q72: =SUMIF('Che.-Prod'!A:A,Used_before_Trf!A72,'Che.-Prod'!P:P) -> 0 | R72: =IF(Q72=0,0,S72/Q72) -> 0 | S72: =SUMIF('Che.-Prod'!A:A,Used_before_Trf!A72,'Che.-Prod'!R:R) -> 0 | T72: =H72+K72+N72-Q72 -> 0 | U72: 13.07 | V72: =J72+M72+P72-S72 -> 0 | W72: =SUMIF('CHE-last month'!$A:$A,Used_before_Trf!A72,'CHE-last month'!C:C) -> 1534.4434 | X72: =IF(W72=0,0,Y72/W72) -> 13.074344 | Y72: =SUMIF('CHE-last month'!$A:$A,Used_before_Trf!A72,'CHE-last month'!E:E) -> 20061.84 | Z72: =+AC72+AF72+AI72 -> 1162.5154 | AA72: =IF(Z72=0,0,AB72/Z72) -> 13.069995 | AB72: =+AE72+AH72+AK72 -> 15194.07 | AC72: =SUMIFS(BalCom!M:M,BalCom!N:N,Used_before_Trf!A72,BalCom!C:C,Used_before_Trf!$AC$1) -> 1162.5154 | AD72: =IF(AC72=0,0,AE72/AC72) -> 13.069995 | AE72: =SUMIFS(BalCom!P:P,BalCom!N:N,Used_before_Trf!A72,BalCom!C:C,Used_before_Trf!$AC$1) -> 15194.07 | AF72: =SUMIFS(BalDis!I:I,BalDis!J:J,Used_before_Trf!A72) -> 0 | AG72: =IF(AF72=0,0,AH72/AF72) -> 0 | AH72: =SUMIFS(BalDis!L:L,BalDis!J:J,Used_before_Trf!A72) -> 0 | AI72: =SUMIFS(BalDip!$N$49:$N$75,BalDip!$C$49:$C$75,Used_before_Trf!A72)+SUMIFS(BalDip!$N$134:$N$157,BalDip!$C$134:$C$157,Used_before_Trf!A72) -> 0 | AJ72: =IF(AI72=0,0,AK72/AI72) -> 0 | AK72: =SUMIFS(BalDip!$N$80:$N$106,BalDip!$C$80:$C$106,Used_before_Trf!A72)+SUMIFS(BalDip!$N$161:$N$184,BalDip!$C$161:$C$184,Used_before_Trf!A72) -> 0 | AL72: =+T72+W72-Z72 -> 371.92799 | AM72: =IF(AL72=0,0,AN72/AL72) -> 13.087937 | AN72: =+V72+Y72-AB72 -> 4867.77 | AO72: =AM72-U72 -> 0.017936607
A73: CH23 | B73: AMMONIUM HYDROXIDE 180KGS /DRUM | C73: =SUMIF('Che-Store'!A:A,Used_before_Trf!A73,'Che-Store'!AC:AC)+SUMIF('Che-Comp'!A:A,Used_before_Trf!A73,'Che-Comp'!AC:AC) -> 492.8 | D73: =IFERROR(E73/C73,0) -> 15.839083 | E73: =SUMIF('Che-Store'!A:A,Used_before_Trf!A73,'Che-Store'!AE:AE)+SUMIF('Che-Comp'!A:A,Used_before_Trf!A73,'Che-Comp'!AE:AE) -> 7805.5 | F73: =SUMIFS('Che-Comp'!F:F,'Che-Comp'!$A:$A,Used_before_Trf!$A73) -> 0 | G73: =SUMIFS('Che-Comp'!G:G,'Che-Comp'!$A:$A,Used_before_Trf!$A73) -> 0 | H73: =C73-F73 -> 492.8 | I73: =IFERROR(J73/H73,0) -> 15.839083 | J73: =E73-G73 -> 7805.5 | K73: =SUMIF('Che.-Prod'!A:A,Used_before_Trf!A73,'Che.-Prod'!D:D) -> 720 | L73: =IFERROR(M73/K73,0) -> 16.2 | M73: =SUMIF('Che.-Prod'!A:A,Used_before_Trf!A73,'Che.-Prod'!F:F) -> 11664 | N73: =SUMIF('Che.-Prod'!A:A,Used_before_Trf!A73,'Che.-Prod'!G:G) -> 0 | O73: =IF(N73=0,0,P73/N73) -> 0 | P73: =SUMIF('Che.-Prod'!A:A,Used_before_Trf!A73,'Che.-Prod'!H:H) -> 0 | Q73: =SUMIF('Che.-Prod'!A:A,Used_before_Trf!A73,'Che.-Prod'!P:P) -> 720 | R73: =IF(Q73=0,0,S73/Q73) -> 16.2 | S73: =SUMIF('Che.-Prod'!A:A,Used_before_Trf!A73,'Che.-Prod'!R:R) -> 11664 | T73: =H73+K73+N73-Q73 -> 492.8 | U73: =IF(T73=0,0,V73/T73) -> 15.839083 | V73: =J73+M73+P73-S73 -> 7805.5 | W73: =SUMIF('CHE-last month'!$A:$A,Used_before_Trf!A73,'CHE-last month'!C:C) -> 32.201704 | X73: =IF(W73=0,0,Y73/W73) -> 10.826135 | Y73: =SUMIF('CHE-last month'!$A:$A,Used_before_Trf!A73,'CHE-last month'!E:E) -> 348.62 | Z73: =+AC73+AF73+AI73 -> 16.130464 | AA73: =IF(Z73=0,0,AB73/Z73) -> 15.838974 | AB73: =+AE73+AH73+AK73 -> 255.49 | AC73: =SUMIFS(BalCom!M:M,BalCom!N:N,Used_before_Trf!A73,BalCom!C:C,Used_before_Trf!$AC$1) -> 0 | AD73: =IF(AC73=0,0,AE73/AC73) -> 0 | AE73: =SUMIFS(BalCom!P:P,BalCom!N:N,Used_before_Trf!A73,BalCom!C:C,Used_before_Trf!$AC$1) -> 0 | AF73: =SUMIFS(BalDis!I:I,BalDis!J:J,Used_before_Trf!A73) -> 16.130464 | AG73: =IF(AF73=0,0,AH73/AF73) -> 15.838974 | AH73: =SUMIFS(BalDis!L:L,BalDis!J:J,Used_before_Trf!A73) -> 255.49 | AI73: =SUMIFS(BalDip!$N$49:$N$75,BalDip!$C$49:$C$75,Used_before_Trf!A73)+SUMIFS(BalDip!$N$134:$N$157,BalDip!$C$134:$C$157,Used_before_Trf!A73) -> 0 | AJ73: =IF(AI73=0,0,AK73/AI73) -> 0 | AK73: =SUMIFS(BalDip!$N$80:$N$106,BalDip!$C$80:$C$106,Used_before_Trf!A73)+SUMIFS(BalDip!$N$161:$N$184,BalDip!$C$161:$C$184,Used_before_Trf!A73) -> 0 | AL73: =+T73+W73-Z73 -> 508.87124 | AM73: =IF(AL73=0,0,AN73/AL73) -> 15.521864 | AN73: =+V73+Y73-AB73 -> 7898.63 | AO73: =AM73-U73 -> -0.31721915
A74: CH230 | B74: CALCIUM NITRATE LIQUOR 54- 56% (30,000KG/TANK)-MEY CHEMICAL | C74: =SUMIF('Che-Store'!A:A,Used_before_Trf!A74,'Che-Store'!AC:AC)+SUMIF('Che-Comp'!A:A,Used_before_Trf!A74,'Che-Comp'!AC:AC) -> 0 | D74: =IFERROR(E74/C74,0) -> 0 | E74: =SUMIF('Che-Store'!A:A,Used_before_Trf!A74,'Che-Store'!AE:AE)+SUMIF('Che-Comp'!A:A,Used_before_Trf!A74,'Che-Comp'!AE:AE) -> 0 | F74: =SUMIFS('Che-Comp'!F:F,'Che-Comp'!$A:$A,Used_before_Trf!$A74) -> 0 | G74: =SUMIFS('Che-Comp'!G:G,'Che-Comp'!$A:$A,Used_before_Trf!$A74) -> 0 | H74: =C74-F74 -> 0 | I74: =IFERROR(J74/H74,0) -> 0 | J74: =E74-G74 -> 0 | K74: =SUMIF('Che.-Prod'!A:A,Used_before_Trf!A74,'Che.-Prod'!D:D) -> 0 | L74: =IFERROR(M74/K74,0) -> 0 | M74: =SUMIF('Che.-Prod'!A:A,Used_before_Trf!A74,'Che.-Prod'!F:F) -> 0 | N74: =SUMIF('Che.-Prod'!A:A,Used_before_Trf!A74,'Che.-Prod'!G:G) -> 0 | O74: =IF(N74=0,0,P74/N74) -> 0 | P74: =SUMIF('Che.-Prod'!A:A,Used_before_Trf!A74,'Che.-Prod'!H:H) -> 0 | Q74: =SUMIF('Che.-Prod'!A:A,Used_before_Trf!A74,'Che.-Prod'!P:P) -> 0 | R74: =IF(Q74=0,0,S74/Q74) -> 0 | S74: =SUMIF('Che.-Prod'!A:A,Used_before_Trf!A74,'Che.-Prod'!R:R) -> 0 | T74: =H74+K74+N74-Q74 -> 0 | U74: =IF(T74=0,0,V74/T74) -> 0 | V74: =J74+M74+P74-S74 -> 0 | W74: =SUMIF('CHE-last month'!$A:$A,Used_before_Trf!A74,'CHE-last month'!C:C) -> 0 | X74: =IF(W74=0,0,Y74/W74) -> 0 | Y74: =SUMIF('CHE-last month'!$A:$A,Used_before_Trf!A74,'CHE-last month'!E:E) -> 0 | Z74: =+AC74+AF74+AI74 -> 0 | AA74: =IF(Z74=0,0,AB74/Z74) -> 0 | AB74: =+AE74+AH74+AK74 -> 0 | AC74: =SUMIFS(BalCom!M:M,BalCom!N:N,Used_before_Trf!A74,BalCom!C:C,Used_before_Trf!$AC$1) -> 0 | AD74: =IF(AC74=0,0,AE74/AC74) -> 0 | AE74: =SUMIFS(BalCom!P:P,BalCom!N:N,Used_before_Trf!A74,BalCom!C:C,Used_before_Trf!$AC$1) -> 0 | AF74: =SUMIFS(BalDis!I:I,BalDis!J:J,Used_before_Trf!A74) -> 0 | AG74: =IF(AF74=0,0,AH74/AF74) -> 0 | AH74: =SUMIFS(BalDis!L:L,BalDis!J:J,Used_before_Trf!A74) -> 0 | AI74: =SUMIFS(BalDip!$N$49:$N$75,BalDip!$C$49:$C$75,Used_before_Trf!A74)+SUMIFS(BalDip!$N$134:$N$157,BalDip!$C$134:$C$157,Used_before_Trf!A74) -> 0 | AJ74: =IF(AI74=0,0,AK74/AI74) -> 0 | AK74: =SUMIFS(BalDip!$N$80:$N$106,BalDip!$C$80:$C$106,Used_before_Trf!A74)+SUMIFS(BalDip!$N$161:$N$184,BalDip!$C$161:$C$184,Used_before_Trf!A74) -> 0 | AL74: =+T74+W74-Z74 -> 0 | AM74: =IF(AL74=0,0,AN74/AL74) -> 0 | AN74: =+V74+Y74-AB74 -> 0 | AO74: =AM74-U74 -> 0
A75: CH233 | B75: (TEST) MAXSIL B280M(200kg/DRUM) - NBR POLYMER | C75: =SUMIF('Che-Store'!A:A,Used_before_Trf!A75,'Che-Store'!AC:AC)+SUMIF('Che-Comp'!A:A,Used_before_Trf!A75,'Che-Comp'!AC:AC) -> 12494.7 | D75: =IFERROR(E75/C75,0) -> 62.807468 | E75: =SUMIF('Che-Store'!A:A,Used_before_Trf!A75,'Che-Store'!AE:AE)+SUMIF('Che-Comp'!A:A,Used_before_Trf!A75,'Che-Comp'!AE:AE) -> 784760.47 | F75: =SUMIFS('Che-Comp'!F:F,'Che-Comp'!$A:$A,Used_before_Trf!$A75) -> 0 | G75: =SUMIFS('Che-Comp'!G:G,'Che-Comp'!$A:$A,Used_before_Trf!$A75) -> 0 | H75: =C75-F75 -> 12494.7 | I75: =IFERROR(J75/H75,0) -> 62.807468 | J75: =E75-G75 -> 784760.47 | K75: =SUMIF('Che.-Prod'!A:A,Used_before_Trf!A75,'Che.-Prod'!D:D) -> 0 | L75: =IFERROR(M75/K75,0) -> 0 | M75: =SUMIF('Che.-Prod'!A:A,Used_before_Trf!A75,'Che.-Prod'!F:F) -> 0 | N75: =SUMIF('Che.-Prod'!A:A,Used_before_Trf!A75,'Che.-Prod'!G:G) -> 0 | O75: =IF(N75=0,0,P75/N75) -> 0 | P75: =SUMIF('Che.-Prod'!A:A,Used_before_Trf!A75,'Che.-Prod'!H:H) -> 0 | Q75: =SUMIF('Che.-Prod'!A:A,Used_before_Trf!A75,'Che.-Prod'!P:P) -> 0 | R75: =IF(Q75=0,0,S75/Q75) -> 0 | S75: =SUMIF('Che.-Prod'!A:A,Used_before_Trf!A75,'Che.-Prod'!R:R) -> 0 | T75: =H75+K75+N75-Q75 -> 12494.7 | U75: =IF(T75=0,0,V75/T75) -> 62.807468 | V75: =J75+M75+P75-S75 -> 784760.47 | W75: =SUMIF('CHE-last month'!$A:$A,Used_before_Trf!A75,'CHE-last month'!C:C) -> 1579.295 | X75: =IF(W75=0,0,Y75/W75) -> 62.664005 | Y75: =SUMIF('CHE-last month'!$A:$A,Used_before_Trf!A75,'CHE-last month'!E:E) -> 98964.95 | Z75: =+AC75+AF75+AI75 -> 1019.22 | AA75: =IF(Z75=0,0,AB75/Z75) -> 62.80747 | AB75: =+AE75+AH75+AK75 -> 64014.63 | AC75: =SUMIFS(BalCom!M:M,BalCom!N:N,Used_before_Trf!A75,BalCom!C:C,Used_before_Trf!$AC$1) -> 0 | AD75: =IF(AC75=0,0,AE75/AC75) -> 0 | AE75: =SUMIFS(BalCom!P:P,BalCom!N:N,Used_before_Trf!A75,BalCom!C:C,Used_before_Trf!$AC$1) -> 0 | AF75: =SUMIFS(BalDis!I:I,BalDis!J:J,Used_before_Trf!A75) -> 584.22 | AG75: =IF(AF75=0,0,AH75/AF75) -> 62.80747 | AH75: =SUMIFS(BalDis!L:L,BalDis!J:J,Used_before_Trf!A75) -> 36693.38 | AI75: =SUMIFS(BalDip!$N$49:$N$75,BalDip!$C$49:$C$75,Used_before_Trf!A75)+SUMIFS(BalDip!$N$134:$N$157,BalDip!$C$134:$C$157,Used_before_Trf!A75) -> 435 | AJ75: =IF(AI75=0,0,AK75/AI75) -> 62.807471 | AK75: =SUMIFS(BalDip!$N$80:$N$106,BalDip!$C$80:$C$106,Used_before_Trf!A75)+SUMIFS(BalDip!$N$161:$N$184,BalDip!$C$161:$C$184,Used_before_Trf!A75) -> 27321.25 | AL75: =+T75+W75-Z75 -> 13054.775 | AM75: =IF(AL75=0,0,AN75/AL75) -> 62.790112 | AN75: =+V75+Y75-AB75 -> 819710.79 | AO75: =AM75-U75 -> -0.017355536
A76: CH234 | B76: (TEST) MAXADD WT300(200KG/DRUM) - WETTING AGENT | C76: =SUMIF('Che-Store'!A:A,Used_before_Trf!A76,'Che-Store'!AC:AC)+SUMIF('Che-Comp'!A:A,Used_before_Trf!A76,'Che-Comp'!AC:AC) -> 0 | D76: =IFERROR(E76/C76,0) -> 0 | E76: =SUMIF('Che-Store'!A:A,Used_before_Trf!A76,'Che-Store'!AE:AE)+SUMIF('Che-Comp'!A:A,Used_before_Trf!A76,'Che-Comp'!AE:AE) -> 0 | F76: =SUMIFS('Che-Comp'!F:F,'Che-Comp'!$A:$A,Used_before_Trf!$A76) -> 0 | G76: =SUMIFS('Che-Comp'!G:G,'Che-Comp'!$A:$A,Used_before_Trf!$A76) -> 0 | H76: =C76-F76 -> 0 | I76: =IFERROR(J76/H76,0) -> 0 | J76: =E76-G76 -> 0 | K76: =SUMIF('Che.-Prod'!A:A,Used_before_Trf!A76,'Che.-Prod'!D:D) -> 0 | L76: =IFERROR(M76/K76,0) -> 0 | M76: =SUMIF('Che.-Prod'!A:A,Used_before_Trf!A76,'Che.-Prod'!F:F) -> 0 | N76: =SUMIF('Che.-Prod'!A:A,Used_before_Trf!A76,'Che.-Prod'!G:G) -> 0 | O76: =IF(N76=0,0,P76/N76) -> 0 | P76: =SUMIF('Che.-Prod'!A:A,Used_before_Trf!A76,'Che.-Prod'!H:H) -> 0 | Q76: =SUMIF('Che.-Prod'!A:A,Used_before_Trf!A76,'Che.-Prod'!P:P) -> 0 | R76: =IF(Q76=0,0,S76/Q76) -> 0 | S76: =SUMIF('Che.-Prod'!A:A,Used_before_Trf!A76,'Che.-Prod'!R:R) -> 0 | T76: =H76+K76+N76-Q76 -> 0 | U76: =IF(T76=0,0,V76/T76) -> 0 | V76: =J76+M76+P76-S76 -> 0 | W76: =SUMIF('CHE-last month'!$A:$A,Used_before_Trf!A76,'CHE-last month'!C:C) -> 0 | X76: =IF(W76=0,0,Y76/W76) -> 0 | Y76: =SUMIF('CHE-last month'!$A:$A,Used_before_Trf!A76,'CHE-last month'!E:E) -> 0 | Z76: =+AC76+AF76+AI76 -> 0 | AA76: =IF(Z76=0,0,AB76/Z76) -> 0 | AB76: =+AE76+AH76+AK76 -> 0 | AC76: =SUMIFS(BalCom!M:M,BalCom!N:N,Used_before_Trf!A76,BalCom!C:C,Used_before_Trf!$AC$1) -> 0 | AD76: =IF(AC76=0,0,AE76/AC76) -> 0 | AE76: =SUMIFS(BalCom!P:P,BalCom!N:N,Used_before_Trf!A76,BalCom!C:C,Used_before_Trf!$AC$1) -> 0 | AF76: =SUMIFS(BalDis!I:I,BalDis!J:J,Used_before_Trf!A76) -> 0 | AG76: =IF(AF76=0,0,AH76/AF76) -> 0 | AH76: =SUMIFS(BalDis!L:L,BalDis!J:J,Used_before_Trf!A76) -> 0 | AI76: =SUMIFS(BalDip!$N$49:$N$75,BalDip!$C$49:$C$75,Used_before_Trf!A76)+SUMIFS(BalDip!$N$134:$N$157,BalDip!$C$134:$C$157,Used_before_Trf!A76) -> 0 | AJ76: =IF(AI76=0,0,AK76/AI76) -> 0 | AK76: =SUMIFS(BalDip!$N$80:$N$106,BalDip!$C$80:$C$106,Used_before_Trf!A76)+SUMIFS(BalDip!$N$161:$N$184,BalDip!$C$161:$C$184,Used_before_Trf!A76) -> 0 | AL76: =+T76+W76-Z76 -> 0 | AM76: =IF(AL76=0,0,AN76/AL76) -> 0 | AN76: =+V76+Y76-AB76 -> 0 | AO76: =AM76-U76 -> 0
A77: CH235 | B77: (TEST) MAXCO B3108M (200KG/DRUM) - ANTI TACK | C77: =SUMIF('Che-Store'!A:A,Used_before_Trf!A77,'Che-Store'!AC:AC)+SUMIF('Che-Comp'!A:A,Used_before_Trf!A77,'Che-Comp'!AC:AC) -> 3130 | D77: =IFERROR(E77/C77,0) -> 51.835463 | E77: =SUMIF('Che-Store'!A:A,Used_before_Trf!A77,'Che-Store'!AE:AE)+SUMIF('Che-Comp'!A:A,Used_before_Trf!A77,'Che-Comp'!AE:AE) -> 162245 | F77: =SUMIFS('Che-Comp'!F:F,'Che-Comp'!$A:$A,Used_before_Trf!$A77) -> 0 | G77: =SUMIFS('Che-Comp'!G:G,'Che-Comp'!$A:$A,Used_before_Trf!$A77) -> 0 | H77: =C77-F77 -> 3130 | I77: =IFERROR(J77/H77,0) -> 51.835463 | J77: =E77-G77 -> 162245 | K77: =SUMIF('Che.-Prod'!A:A,Used_before_Trf!A77,'Che.-Prod'!D:D) -> 0 | L77: =IFERROR(M77/K77,0) -> 0 | M77: =SUMIF('Che.-Prod'!A:A,Used_before_Trf!A77,'Che.-Prod'!F:F) -> 0 | N77: =SUMIF('Che.-Prod'!A:A,Used_before_Trf!A77,'Che.-Prod'!G:G) -> 0 | O77: =IF(N77=0,0,P77/N77) -> 0 | P77: =SUMIF('Che.-Prod'!A:A,Used_before_Trf!A77,'Che.-Prod'!H:H) -> 0 | Q77: =SUMIF('Che.-Prod'!A:A,Used_before_Trf!A77,'Che.-Prod'!P:P) -> 0 | R77: =IF(Q77=0,0,S77/Q77) -> 0 | S77: =SUMIF('Che.-Prod'!A:A,Used_before_Trf!A77,'Che.-Prod'!R:R) -> 0 | T77: =H77+K77+N77-Q77 -> 3130 | U77: =IF(T77=0,0,V77/T77) -> 51.835463 | V77: =J77+M77+P77-S77 -> 162245 | W77: =SUMIF('CHE-last month'!$A:$A,Used_before_Trf!A77,'CHE-last month'!C:C) -> 473.45059 | X77: =IF(W77=0,0,Y77/W77) -> 51.855338 | Y77: =SUMIF('CHE-last month'!$A:$A,Used_before_Trf!A77,'CHE-last month'!E:E) -> 24550.94 | Z77: =+AC77+AF77+AI77 -> 378.5852 | AA77: =IF(Z77=0,0,AB77/Z77) -> 51.835465 | AB77: =+AE77+AH77+AK77 -> 19624.14 | AC77: =SUMIFS(BalCom!M:M,BalCom!N:N,Used_before_Trf!A77,BalCom!C:C,Used_before_Trf!$AC$1) -> 0 | AD77: =IF(AC77=0,0,AE77/AC77) -> 0 | AE77: =SUMIFS(BalCom!P:P,BalCom!N:N,Used_before_Trf!A77,BalCom!C:C,Used_before_Trf!$AC$1) -> 0 | AF77: =SUMIFS(BalDis!I:I,BalDis!J:J,Used_before_Trf!A77) -> 74.1552 | AG77: =IF(AF77=0,0,AH77/AF77) -> 51.835475 | AH77: =SUMIFS(BalDis!L:L,BalDis!J:J,Used_before_Trf!A77) -> 3843.87 | AI77: =SUMIFS(BalDip!$N$49:$N$75,BalDip!$C$49:$C$75,Used_before_Trf!A77)+SUMIFS(BalDip!$N$134:$N$157,BalDip!$C$134:$C$157,Used_before_Trf!A77) -> 304.43 | AJ77: =IF(AI77=0,0,AK77/AI77) -> 51.835463 | AK77: =SUMIFS(BalDip!$N$80:$N$106,BalDip!$C$80:$C$106,Used_before_Trf!A77)+SUMIFS(BalDip!$N$161:$N$184,BalDip!$C$161:$C$184,Used_before_Trf!A77) -> 15780.27 | AL77: =+T77+W77-Z77 -> 3224.8654 | AM77: =IF(AL77=0,0,AN77/AL77) -> 51.838381 | AN77: =+V77+Y77-AB77 -> 167171.8 | AO77: =AM77-U77 -> 0.002917547
A78: CH238 | B78: (TEST) OCTOWET LWA (200KG/DRUM)-WETTING AGENT | C78: =SUMIF('Che-Store'!A:A,Used_before_Trf!A78,'Che-Store'!AC:AC)+SUMIF('Che-Comp'!A:A,Used_before_Trf!A78,'Che-Comp'!AC:AC) -> 0 | D78: =IFERROR(E78/C78,0) -> 0 | E78: =SUMIF('Che-Store'!A:A,Used_before_Trf!A78,'Che-Store'!AE:AE)+SUMIF('Che-Comp'!A:A,Used_before_Trf!A78,'Che-Comp'!AE:AE) -> 0 | F78: =SUMIFS('Che-Comp'!F:F,'Che-Comp'!$A:$A,Used_before_Trf!$A78) -> 0 | G78: =SUMIFS('Che-Comp'!G:G,'Che-Comp'!$A:$A,Used_before_Trf!$A78) -> 0 | H78: =C78-F78 -> 0 | I78: =IFERROR(J78/H78,0) -> 0 | J78: =E78-G78 -> 0 | K78: =SUMIF('Che.-Prod'!A:A,Used_before_Trf!A78,'Che.-Prod'!D:D) -> 0 | L78: =IFERROR(M78/K78,0) -> 0 | M78: =SUMIF('Che.-Prod'!A:A,Used_before_Trf!A78,'Che.-Prod'!F:F) -> 0 | N78: =SUMIF('Che.-Prod'!A:A,Used_before_Trf!A78,'Che.-Prod'!G:G) -> 0 | O78: =IF(N78=0,0,P78/N78) -> 0 | P78: =SUMIF('Che.-Prod'!A:A,Used_before_Trf!A78,'Che.-Prod'!H:H) -> 0 | Q78: =SUMIF('Che.-Prod'!A:A,Used_before_Trf!A78,'Che.-Prod'!P:P) -> 0 | R78: =IF(Q78=0,0,S78/Q78) -> 0 | S78: =SUMIF('Che.-Prod'!A:A,Used_before_Trf!A78,'Che.-Prod'!R:R) -> 0 | T78: =H78+K78+N78-Q78 -> 0 | U78: =IF(T78=0,0,V78/T78) -> 0 | V78: =J78+M78+P78-S78 -> 0 | W78: =SUMIF('CHE-last month'!$A:$A,Used_before_Trf!A78,'CHE-last month'!C:C) -> 0 | X78: =IF(W78=0,0,Y78/W78) -> 0 | Y78: =SUMIF('CHE-last month'!$A:$A,Used_before_Trf!A78,'CHE-last month'!E:E) -> 0 | Z78: =+AC78+AF78+AI78 -> 0 | AA78: =IF(Z78=0,0,AB78/Z78) -> 0 | AB78: =+AE78+AH78+AK78 -> 0 | AC78: =SUMIFS(BalCom!M:M,BalCom!N:N,Used_before_Trf!A78,BalCom!C:C,Used_before_Trf!$AC$1) -> 0 | AD78: =IF(AC78=0,0,AE78/AC78) -> 0 | AE78: =SUMIFS(BalCom!P:P,BalCom!N:N,Used_before_Trf!A78,BalCom!C:C,Used_before_Trf!$AC$1) -> 0 | AF78: =SUMIFS(BalDis!I:I,BalDis!J:J,Used_before_Trf!A78) -> 0 | AG78: =IF(AF78=0,0,AH78/AF78) -> 0 | AH78: =SUMIFS(BalDis!L:L,BalDis!J:J,Used_before_Trf!A78) -> 0 | AI78: =SUMIFS(BalDip!$N$49:$N$75,BalDip!$C$49:$C$75,Used_before_Trf!A78)+SUMIFS(BalDip!$N$134:$N$157,BalDip!$C$134:$C$157,Used_before_Trf!A78) -> 0 | AJ78: =IF(AI78=0,0,AK78/AI78) -> 0 | AK78: =SUMIFS(BalDip!$N$80:$N$106,BalDip!$C$80:$C$106,Used_before_Trf!A78)+SUMIFS(BalDip!$N$161:$N$184,BalDip!$C$161:$C$184,Used_before_Trf!A78) -> 0 | AL78: =+T78+W78-Z78 -> 0 | AM78: =IF(AL78=0,0,AN78/AL78) -> 0 | AN78: =+V78+Y78-AB78 -> 0 | AO78: =AM78-U78 -> 0
A79: CH240 | B79: (TEST) ALPHALINK 50 (200KG/DRUM),(1000KG/IBC) - ACELERATOR FREE CROSSLINKER | C79: =SUMIF('Che-Store'!A:A,Used_before_Trf!A79,'Che-Store'!AC:AC)+SUMIF('Che-Comp'!A:A,Used_before_Trf!A79,'Che-Comp'!AC:AC) -> 407.34 | D79: =IFERROR(E79/C79,0) -> 77.639859 | E79: =SUMIF('Che-Store'!A:A,Used_before_Trf!A79,'Che-Store'!AE:AE)+SUMIF('Che-Comp'!A:A,Used_before_Trf!A79,'Che-Comp'!AE:AE) -> 31625.82 | F79: =SUMIFS('Che-Comp'!F:F,'Che-Comp'!$A:$A,Used_before_Trf!$A79) -> 0 | G79: =SUMIFS('Che-Comp'!G:G,'Che-Comp'!$A:$A,Used_before_Trf!$A79) -> 0 | H79: =C79-F79 -> 407.34 | I79: =IFERROR(J79/H79,0) -> 77.639859 | J79: =E79-G79 -> 31625.82 | K79: =SUMIF('Che.-Prod'!A:A,Used_before_Trf!A79,'Che.-Prod'!D:D) -> 0 | L79: =IFERROR(M79/K79,0) -> 0 | M79: =SUMIF('Che.-Prod'!A:A,Used_before_Trf!A79,'Che.-Prod'!F:F) -> 0 | N79: =SUMIF('Che.-Prod'!A:A,Used_before_Trf!A79,'Che.-Prod'!G:G) -> 0 | O79: =IF(N79=0,0,P79/N79) -> 0 | P79: =SUMIF('Che.-Prod'!A:A,Used_before_Trf!A79,'Che.-Prod'!H:H) -> 0 | Q79: =SUMIF('Che.-Prod'!A:A,Used_before_Trf!A79,'Che.-Prod'!P:P) -> 0 | R79: =IF(Q79=0,0,S79/Q79) -> 0 | S79: =SUMIF('Che.-Prod'!A:A,Used_before_Trf!A79,'Che.-Prod'!R:R) -> 0 | T79: =H79+K79+N79-Q79 -> 407.34 | U79: =IF(T79=0,0,V79/T79) -> 77.639859 | V79: =J79+M79+P79-S79 -> 31625.82 | W79: =SUMIF('CHE-last month'!$A:$A,Used_before_Trf!A79,'CHE-last month'!C:C) -> 265.6042 | X79: =IF(W79=0,0,Y79/W79) -> 77.640527 | Y79: =SUMIF('CHE-last month'!$A:$A,Used_before_Trf!A79,'CHE-last month'!E:E) -> 20621.65 | Z79: =+AC79+AF79+AI79 -> 36.47396 | AA79: =IF(Z79=0,0,AB79/Z79) -> 77.639775 | AB79: =+AE79+AH79+AK79 -> 2831.83 | AC79: =SUMIFS(BalCom!M:M,BalCom!N:N,Used_before_Trf!A79,BalCom!C:C,Used_before_Trf!$AC$1) -> 36.47396 | AD79: =IF(AC79=0,0,AE79/AC79) -> 77.639775 | AE79: =SUMIFS(BalCom!P:P,BalCom!N:N,Used_before_Trf!A79,BalCom!C:C,Used_before_Trf!$AC$1) -> 2831.83 | AF79: =SUMIFS(BalDis!I:I,BalDis!J:J,Used_before_Trf!A79) -> 0 | AG79: =IF(AF79=0,0,AH79/AF79) -> 0 | AH79: =SUMIFS(BalDis!L:L,BalDis!J:J,Used_before_Trf!A79) -> 0 | AI79: =SUMIFS(BalDip!$N$49:$N$75,BalDip!$C$49:$C$75,Used_before_Trf!A79)+SUMIFS(BalDip!$N$134:$N$157,BalDip!$C$134:$C$157,Used_before_Trf!A79) -> 0 | AJ79: =IF(AI79=0,0,AK79/AI79) -> 0 | AK79: =SUMIFS(BalDip!$N$80:$N$106,BalDip!$C$80:$C$106,Used_before_Trf!A79)+SUMIFS(BalDip!$N$161:$N$184,BalDip!$C$161:$C$184,Used_before_Trf!A79) -> 0 | AL79: =+T79+W79-Z79 -> 636.47024 | AM79: =IF(AL79=0,0,AN79/AL79) -> 77.640143 | AN79: =+V79+Y79-AB79 -> 49415.64 | AO79: =AM79-U79 -> 0.0002839056
A80: CH245 | B80: (TEST) SPECLEAN 10 (230KG/DRUM) - ALKALINE CLEANER | C80: =SUMIF('Che-Store'!A:A,Used_before_Trf!A80,'Che-Store'!AC:AC)+SUMIF('Che-Comp'!A:A,Used_before_Trf!A80,'Che-Comp'!AC:AC) -> 8280 | D80: =IFERROR(E80/C80,0) -> 9.5761546 | E80: =SUMIF('Che-Store'!A:A,Used_before_Trf!A80,'Che-Store'!AE:AE)+SUMIF('Che-Comp'!A:A,Used_before_Trf!A80,'Che-Comp'!AE:AE) -> 79290.56 | F80: =SUMIFS('Che-Comp'!F:F,'Che-Comp'!$A:$A,Used_before_Trf!$A80) -> 0 | G80: =SUMIFS('Che-Comp'!G:G,'Che-Comp'!$A:$A,Used_before_Trf!$A80) -> 0 | H80: =C80-F80 -> 8280 | I80: =IFERROR(J80/H80,0) -> 9.5761546 | J80: =E80-G80 -> 79290.56 | K80: =SUMIF('Che.-Prod'!A:A,Used_before_Trf!A80,'Che.-Prod'!D:D) -> 0 | L80: =IFERROR(M80/K80,0) -> 0 | M80: =SUMIF('Che.-Prod'!A:A,Used_before_Trf!A80,'Che.-Prod'!F:F) -> 0 | N80: =SUMIF('Che.-Prod'!A:A,Used_before_Trf!A80,'Che.-Prod'!G:G) -> 0 | O80: =IF(N80=0,0,P80/N80) -> 0 | P80: =SUMIF('Che.-Prod'!A:A,Used_before_Trf!A80,'Che.-Prod'!H:H) -> 0 | Q80: =SUMIF('Che.-Prod'!A:A,Used_before_Trf!A80,'Che.-Prod'!P:P) -> 1150 | R80: =IF(Q80=0,0,S80/Q80) -> 9.58 | S80: =SUMIF('Che.-Prod'!A:A,Used_before_Trf!A80,'Che.-Prod'!R:R) -> 11017 | T80: =H80+K80+N80-Q80 -> 7130 | U80: =IF(T80=0,0,V80/T80) -> 9.5755344 | V80: =J80+M80+P80-S80 -> 68273.56 | W80: =SUMIF('CHE-last month'!$A:$A,Used_before_Trf!A80,'CHE-last month'!C:C) -> 0 | X80: =IF(W80=0,0,Y80/W80) -> 0 | Y80: =SUMIF('CHE-last month'!$A:$A,Used_before_Trf!A80,'CHE-last month'!E:E) -> 0 | Z80: =+AC80+AF80+AI80 -> 225.11 | AA80: =IF(Z80=0,0,AB80/Z80) -> 9.5755408 | AB80: =+AE80+AH80+AK80 -> 2155.55 | AC80: =SUMIFS(BalCom!M:M,BalCom!N:N,Used_before_Trf!A80,BalCom!C:C,Used_before_Trf!$AC$1) -> 0 | AD80: =IF(AC80=0,0,AE80/AC80) -> 0 | AE80: =SUMIFS(BalCom!P:P,BalCom!N:N,Used_before_Trf!A80,BalCom!C:C,Used_before_Trf!$AC$1) -> 0 | AF80: =SUMIFS(BalDis!I:I,BalDis!J:J,Used_before_Trf!A80) -> 0 | AG80: =IF(AF80=0,0,AH80/AF80) -> 0 | AH80: =SUMIFS(BalDis!L:L,BalDis!J:J,Used_before_Trf!A80) -> 0 | AI80: =SUMIFS(BalDip!$N$49:$N$75,BalDip!$C$49:$C$75,Used_before_Trf!A80)+SUMIFS(BalDip!$N$134:$N$157,BalDip!$C$134:$C$157,Used_before_Trf!A80) -> 225.11 | AJ80: =IF(AI80=0,0,AK80/AI80) -> 9.5755408 | AK80: =SUMIFS(BalDip!$N$80:$N$106,BalDip!$C$80:$C$106,Used_before_Trf!A80)+SUMIFS(BalDip!$N$161:$N$184,BalDip!$C$161:$C$184,Used_before_Trf!A80) -> 2155.55 | AL80: =+T80+W80-Z80 -> 6904.89 | AM80: =IF(AL80=0,0,AN80/AL80) -> 9.5755342 | AN80: =+V80+Y80-AB80 -> 66118.01
A81: CH249 | B81: (TEST) SULPHUR 60% 1200 KGS/IBC | C81: =SUMIF('Che-Store'!A:A,Used_before_Trf!A81,'Che-Store'!AC:AC)+SUMIF('Che-Comp'!A:A,Used_before_Trf!A81,'Che-Comp'!AC:AC) -> 0 | D81: =IFERROR(E81/C81,0) -> 0 | E81: =SUMIF('Che-Store'!A:A,Used_before_Trf!A81,'Che-Store'!AE:AE)+SUMIF('Che-Comp'!A:A,Used_before_Trf!A81,'Che-Comp'!AE:AE) -> 0 | F81: =SUMIFS('Che-Comp'!F:F,'Che-Comp'!$A:$A,Used_before_Trf!$A81) -> 0 | G81: =SUMIFS('Che-Comp'!G:G,'Che-Comp'!$A:$A,Used_before_Trf!$A81) -> 0 | H81: =C81-F81 -> 0 | I81: =IFERROR(J81/H81,0) -> 0 | J81: =E81-G81 -> 0 | K81: =SUMIF('Che.-Prod'!A:A,Used_before_Trf!A81,'Che.-Prod'!D:D) -> 0 | L81: =IFERROR(M81/K81,0) -> 0 | M81: =SUMIF('Che.-Prod'!A:A,Used_before_Trf!A81,'Che.-Prod'!F:F) -> 0 | N81: =SUMIF('Che.-Prod'!A:A,Used_before_Trf!A81,'Che.-Prod'!G:G) -> 0 | O81: =IF(N81=0,0,P81/N81) -> 0 | P81: =SUMIF('Che.-Prod'!A:A,Used_before_Trf!A81,'Che.-Prod'!H:H) -> 0 | Q81: =SUMIF('Che.-Prod'!A:A,Used_before_Trf!A81,'Che.-Prod'!P:P) -> 0 | R81: =IF(Q81=0,0,S81/Q81) -> 0 | S81: =SUMIF('Che.-Prod'!A:A,Used_before_Trf!A81,'Che.-Prod'!R:R) -> 0 | T81: =H81+K81+N81-Q81 -> 0 | U81: =IF(T81=0,0,V81/T81) -> 0 | V81: =J81+M81+P81-S81 -> 0 | W81: =SUMIF('CHE-last month'!$A:$A,Used_before_Trf!A81,'CHE-last month'!C:C) -> 0 | X81: =IF(W81=0,0,Y81/W81) -> 0 | Y81: =SUMIF('CHE-last month'!$A:$A,Used_before_Trf!A81,'CHE-last month'!E:E) -> 0 | Z81: =+AC81+AF81+AI81 -> 0 | AA81: =IF(Z81=0,0,AB81/Z81) -> 0 | AB81: =+AE81+AH81+AK81 -> 0 | AC81: =SUMIFS(BalCom!M:M,BalCom!N:N,Used_before_Trf!A81,BalCom!C:C,Used_before_Trf!$AC$1) -> 0 | AD81: =IF(AC81=0,0,AE81/AC81) -> 0 | AE81: =SUMIFS(BalCom!P:P,BalCom!N:N,Used_before_Trf!A81,BalCom!C:C,Used_before_Trf!$AC$1) -> 0 | AF81: =SUMIFS(BalDis!I:I,BalDis!J:J,Used_before_Trf!A81) -> 0 | AG81: =IF(AF81=0,0,AH81/AF81) -> 0 | AH81: =SUMIFS(BalDis!L:L,BalDis!J:J,Used_before_Trf!A81) -> 0 | AI81: =SUMIFS(BalDip!$N$49:$N$75,BalDip!$C$49:$C$75,Used_before_Trf!A81)+SUMIFS(BalDip!$N$134:$N$157,BalDip!$C$134:$C$157,Used_before_Trf!A81) -> 0 | AJ81: =IF(AI81=0,0,AK81/AI81) -> 0 | AK81: =SUMIFS(BalDip!$N$80:$N$106,BalDip!$C$80:$C$106,Used_before_Trf!A81)+SUMIFS(BalDip!$N$161:$N$184,BalDip!$C$161:$C$184,Used_before_Trf!A81) -> 0 | AL81: =+T81+W81-Z81 -> 0 | AM81: =IF(AL81=0,0,AN81/AL81) -> 0 | AN81: =+V81+Y81-AB81 -> 0 | AO81: =AM81-U81 -> 0
A82: CH250 | B82: (TEST) ZINC OXIDE 60% (1400KG/IBC) | C82: =SUMIF('Che-Store'!A:A,Used_before_Trf!A82,'Che-Store'!AC:AC)+SUMIF('Che-Comp'!A:A,Used_before_Trf!A82,'Che-Comp'!AC:AC) -> 0 | D82: =IFERROR(E82/C82,0) -> 0 | E82: =SUMIF('Che-Store'!A:A,Used_before_Trf!A82,'Che-Store'!AE:AE)+SUMIF('Che-Comp'!A:A,Used_before_Trf!A82,'Che-Comp'!AE:AE) -> 0 | F82: =SUMIFS('Che-Comp'!F:F,'Che-Comp'!$A:$A,Used_before_Trf!$A82) -> 0 | G82: =SUMIFS('Che-Comp'!G:G,'Che-Comp'!$A:$A,Used_before_Trf!$A82) -> 0 | H82: =C82-F82 -> 0 | I82: =IFERROR(J82/H82,0) -> 0 | J82: =E82-G82 -> 0 | K82: =SUMIF('Che.-Prod'!A:A,Used_before_Trf!A82,'Che.-Prod'!D:D) -> 0 | L82: =IFERROR(M82/K82,0) -> 0 | M82: =SUMIF('Che.-Prod'!A:A,Used_before_Trf!A82,'Che.-Prod'!F:F) -> 0 | N82: =SUMIF('Che.-Prod'!A:A,Used_before_Trf!A82,'Che.-Prod'!G:G) -> 0 | O82: =IF(N82=0,0,P82/N82) -> 0 | P82: =SUMIF('Che.-Prod'!A:A,Used_before_Trf!A82,'Che.-Prod'!H:H) -> 0 | Q82: =SUMIF('Che.-Prod'!A:A,Used_before_Trf!A82,'Che.-Prod'!P:P) -> 0 | R82: =IF(Q82=0,0,S82/Q82) -> 0 | S82: =SUMIF('Che.-Prod'!A:A,Used_before_Trf!A82,'Che.-Prod'!R:R) -> 0 | T82: =H82+K82+N82-Q82 -> 0 | U82: =IF(T82=0,0,V82/T82) -> 0 | V82: =J82+M82+P82-S82 -> 0 | W82: =SUMIF('CHE-last month'!$A:$A,Used_before_Trf!A82,'CHE-last month'!C:C) -> 0 | X82: =IF(W82=0,0,Y82/W82) -> 0 | Y82: =SUMIF('CHE-last month'!$A:$A,Used_before_Trf!A82,'CHE-last month'!E:E) -> 0 | Z82: =+AC82+AF82+AI82 -> 0 | AA82: =IF(Z82=0,0,AB82/Z82) -> 0 | AB82: =+AE82+AH82+AK82 -> 0 | AC82: =SUMIFS(BalCom!M:M,BalCom!N:N,Used_before_Trf!A82,BalCom!C:C,Used_before_Trf!$AC$1) -> 0 | AD82: =IF(AC82=0,0,AE82/AC82) -> 0 | AE82: =SUMIFS(BalCom!P:P,BalCom!N:N,Used_before_Trf!A82,BalCom!C:C,Used_before_Trf!$AC$1) -> 0 | AF82: =SUMIFS(BalDis!I:I,BalDis!J:J,Used_before_Trf!A82) -> 0 | AG82: =IF(AF82=0,0,AH82/AF82) -> 0 | AH82: =SUMIFS(BalDis!L:L,BalDis!J:J,Used_before_Trf!A82) -> 0 | AI82: =SUMIFS(BalDip!$N$49:$N$75,BalDip!$C$49:$C$75,Used_before_Trf!A82)+SUMIFS(BalDip!$N$134:$N$157,BalDip!$C$134:$C$157,Used_before_Trf!A82) -> 0 | AJ82: =IF(AI82=0,0,AK82/AI82) -> 0 | AK82: =SUMIFS(BalDip!$N$80:$N$106,BalDip!$C$80:$C$106,Used_before_Trf!A82)+SUMIFS(BalDip!$N$161:$N$184,BalDip!$C$161:$C$184,Used_before_Trf!A82) -> 0 | AL82: =+T82+W82-Z82 -> 0 | AM82: =IF(AL82=0,0,AN82/AL82) -> 0 | AN82: =+V82+Y82-AB82 -> 0 | AO82: =AM82-U82 -> 0
A83: CH251 | B83: (TEST) TITANIUM DIOXIDE 70% (TIO2 70%) (1400KG/IBC) | C83: =SUMIF('Che-Store'!A:A,Used_before_Trf!A83,'Che-Store'!AC:AC)+SUMIF('Che-Comp'!A:A,Used_before_Trf!A83,'Che-Comp'!AC:AC) -> 0 | D83: =IFERROR(E83/C83,0) -> 0 | E83: =SUMIF('Che-Store'!A:A,Used_before_Trf!A83,'Che-Store'!AE:AE)+SUMIF('Che-Comp'!A:A,Used_before_Trf!A83,'Che-Comp'!AE:AE) -> 0 | F83: =SUMIFS('Che-Comp'!F:F,'Che-Comp'!$A:$A,Used_before_Trf!$A83) -> 0 | G83: =SUMIFS('Che-Comp'!G:G,'Che-Comp'!$A:$A,Used_before_Trf!$A83) -> 0 | H83: =C83-F83 -> 0 | I83: =IFERROR(J83/H83,0) -> 0 | J83: =E83-G83 -> 0 | K83: =SUMIF('Che.-Prod'!A:A,Used_before_Trf!A83,'Che.-Prod'!D:D) -> 0 | L83: =IFERROR(M83/K83,0) -> 0 | M83: =SUMIF('Che.-Prod'!A:A,Used_before_Trf!A83,'Che.-Prod'!F:F) -> 0 | N83: =SUMIF('Che.-Prod'!A:A,Used_before_Trf!A83,'Che.-Prod'!G:G) -> 0 | O83: =IF(N83=0,0,P83/N83) -> 0 | P83: =SUMIF('Che.-Prod'!A:A,Used_before_Trf!A83,'Che.-Prod'!H:H) -> 0 | Q83: =SUMIF('Che.-Prod'!A:A,Used_before_Trf!A83,'Che.-Prod'!P:P) -> 0 | R83: =IF(Q83=0,0,S83/Q83) -> 0 | S83: =SUMIF('Che.-Prod'!A:A,Used_before_Trf!A83,'Che.-Prod'!R:R) -> 0 | T83: =H83+K83+N83-Q83 -> 0 | U83: =IF(T83=0,0,V83/T83) -> 0 | V83: =J83+M83+P83-S83 -> 0 | W83: =SUMIF('CHE-last month'!$A:$A,Used_before_Trf!A83,'CHE-last month'!C:C) -> 0 | X83: =IF(W83=0,0,Y83/W83) -> 0 | Y83: =SUMIF('CHE-last month'!$A:$A,Used_before_Trf!A83,'CHE-last month'!E:E) -> 0 | Z83: =+AC83+AF83+AI83 -> 0 | AA83: =IF(Z83=0,0,AB83/Z83) -> 0 | AB83: =+AE83+AH83+AK83 -> 0 | AC83: =SUMIFS(BalCom!M:M,BalCom!N:N,Used_before_Trf!A83,BalCom!C:C,Used_before_Trf!$AC$1) -> 0 | AD83: =IF(AC83=0,0,AE83/AC83) -> 0 | AE83: =SUMIFS(BalCom!P:P,BalCom!N:N,Used_before_Trf!A83,BalCom!C:C,Used_before_Trf!$AC$1) -> 0 | AF83: =SUMIFS(BalDis!I:I,BalDis!J:J,Used_before_Trf!A83) -> 0 | AG83: =IF(AF83=0,0,AH83/AF83) -> 0 | AH83: =SUMIFS(BalDis!L:L,BalDis!J:J,Used_before_Trf!A83) -> 0 | AI83: =SUMIFS(BalDip!$N$49:$N$75,BalDip!$C$49:$C$75,Used_before_Trf!A83)+SUMIFS(BalDip!$N$134:$N$157,BalDip!$C$134:$C$157,Used_before_Trf!A83) -> 0 | AJ83: =IF(AI83=0,0,AK83/AI83) -> 0 | AK83: =SUMIFS(BalDip!$N$80:$N$106,BalDip!$C$80:$C$106,Used_before_Trf!A83)+SUMIFS(BalDip!$N$161:$N$184,BalDip!$C$161:$C$184,Used_before_Trf!A83) -> 0 | AL83: =+T83+W83-Z83 -> 0 | AM83: =IF(AL83=0,0,AN83/AL83) -> 0 | AN83: =+V83+Y83-AB83 -> 0 | AO83: =AM83-U83 -> 0
A84: CH252 | B84: (TEST) KLEEN S21 (225KG/DRUM) (ALAKLINE CLEANNER) | C84: =SUMIF('Che-Store'!A:A,Used_before_Trf!A84,'Che-Store'!AC:AC)+SUMIF('Che-Comp'!A:A,Used_before_Trf!A84,'Che-Comp'!AC:AC) -> 900 | D84: =IFERROR(E84/C84,0) -> 9.5 | E84: =SUMIF('Che-Store'!A:A,Used_before_Trf!A84,'Che-Store'!AE:AE)+SUMIF('Che-Comp'!A:A,Used_before_Trf!A84,'Che-Comp'!AE:AE) -> 8550 | F84: =SUMIFS('Che-Comp'!F:F,'Che-Comp'!$A:$A,Used_before_Trf!$A84) -> 0 | G84: =SUMIFS('Che-Comp'!G:G,'Che-Comp'!$A:$A,Used_before_Trf!$A84) -> 0 | H84: =C84-F84 -> 900 | I84: =IFERROR(J84/H84,0) -> 9.5 | J84: =E84-G84 -> 8550 | K84: =SUMIF('Che.-Prod'!A:A,Used_before_Trf!A84,'Che.-Prod'!D:D) -> 1125 | L84: =IFERROR(M84/K84,0) -> 10.35 | M84: =SUMIF('Che.-Prod'!A:A,Used_before_Trf!A84,'Che.-Prod'!F:F) -> 11643.75 | N84: =SUMIF('Che.-Prod'!A:A,Used_before_Trf!A84,'Che.-Prod'!G:G) -> 0 | O84: =IF(N84=0,0,P84/N84) -> 0 | P84: =SUMIF('Che.-Prod'!A:A,Used_before_Trf!A84,'Che.-Prod'!H:H) -> 0 | Q84: =SUMIF('Che.-Prod'!A:A,Used_before_Trf!A84,'Che.-Prod'!P:P) -> 0 | R84: =IF(Q84=0,0,S84/Q84) -> 0 | S84: =SUMIF('Che.-Prod'!A:A,Used_before_Trf!A84,'Che.-Prod'!R:R) -> 0 | T84: =H84+K84+N84-Q84 -> 2025 | U84: =IF(T84=0,0,V84/T84) -> 9.9722222 | V84: =J84+M84+P84-S84 -> 20193.75 | W84: =SUMIF('CHE-last month'!$A:$A,Used_before_Trf!A84,'CHE-last month'!C:C) -> 107.01 | X84: =IF(W84=0,0,Y84/W84) -> 10.121297 | Y84: =SUMIF('CHE-last month'!$A:$A,Used_before_Trf!A84,'CHE-last month'!E:E) -> 1083.08 | Z84: =+AC84+AF84+AI84 -> 0 | AA84: =IF(Z84=0,0,AB84/Z84) -> 0 | AB84: =+AE84+AH84+AK84 -> 0 | AC84: =SUMIFS(BalCom!M:M,BalCom!N:N,Used_before_Trf!A84,BalCom!C:C,Used_before_Trf!$AC$1) -> 0 | AD84: =IF(AC84=0,0,AE84/AC84) -> 0 | AE84: =SUMIFS(BalCom!P:P,BalCom!N:N,Used_before_Trf!A84,BalCom!C:C,Used_before_Trf!$AC$1) -> 0 | AF84: =SUMIFS(BalDis!I:I,BalDis!J:J,Used_before_Trf!A84) -> 0 | AG84: =IF(AF84=0,0,AH84/AF84) -> 0 | AH84: =SUMIFS(BalDis!L:L,BalDis!J:J,Used_before_Trf!A84) -> 0 | AI84: =SUMIFS(BalDip!$N$49:$N$75,BalDip!$C$49:$C$75,Used_before_Trf!A84)+SUMIFS(BalDip!$N$134:$N$157,BalDip!$C$134:$C$157,Used_before_Trf!A84) -> 0 | AJ84: =IF(AI84=0,0,AK84/AI84) -> 0 | AK84: =SUMIFS(BalDip!$N$80:$N$106,BalDip!$C$80:$C$106,Used_before_Trf!A84)+SUMIFS(BalDip!$N$161:$N$184,BalDip!$C$161:$C$184,Used_before_Trf!A84) -> 0 | AL84: =+T84+W84-Z84 -> 2132.01 | AM84: =IF(AL84=0,0,AN84/AL84) -> 9.9797046 | AN84: =+V84+Y84-AB84 -> 21276.83 | AO84: =AM84-U84 -> 0.0074823758
A85: CH26 | B85: NITRIC ACID 68% (280 KGS/DRUM ) | C85: =SUMIF('Che-Store'!A:A,Used_before_Trf!A85,'Che-Store'!AC:AC)+SUMIF('Che-Comp'!A:A,Used_before_Trf!A85,'Che-Comp'!AC:AC) -> 3360 | D85: =IFERROR(E85/C85,0) -> 15.5 | E85: =SUMIF('Che-Store'!A:A,Used_before_Trf!A85,'Che-Store'!AE:AE)+SUMIF('Che-Comp'!A:A,Used_before_Trf!A85,'Che-Comp'!AE:AE) -> 52080 | F85: =SUMIFS('Che-Comp'!F:F,'Che-Comp'!$A:$A,Used_before_Trf!$A85) -> 0 | G85: =SUMIFS('Che-Comp'!G:G,'Che-Comp'!$A:$A,Used_before_Trf!$A85) -> 0 | H85: =C85-F85 -> 3360 | I85: =IFERROR(J85/H85,0) -> 15.5 | J85: =E85-G85 -> 52080 | K85: =SUMIF('Che.-Prod'!A:A,Used_before_Trf!A85,'Che.-Prod'!D:D) -> 1960 | L85: =IFERROR(M85/K85,0) -> 13 | M85: =SUMIF('Che.-Prod'!A:A,Used_before_Trf!A85,'Che.-Prod'!F:F) -> 25480 | N85: =SUMIF('Che.-Prod'!A:A,Used_before_Trf!A85,'Che.-Prod'!G:G) -> 0 | O85: =IF(N85=0,0,P85/N85) -> 0 | P85: =SUMIF('Che.-Prod'!A:A,Used_before_Trf!A85,'Che.-Prod'!H:H) -> 0 | Q85: =SUMIF('Che.-Prod'!A:A,Used_before_Trf!A85,'Che.-Prod'!P:P) -> 1120 | R85: =IF(Q85=0,0,S85/Q85) -> 13 | S85: =SUMIF('Che.-Prod'!A:A,Used_before_Trf!A85,'Che.-Prod'!R:R) -> 14560 | T85: =H85+K85+N85-Q85 -> 4200 | U85: =IF(T85=0,0,V85/T85) -> 15 | V85: =J85+M85+P85-S85 -> 63000 | W85: =SUMIF('CHE-last month'!$A:$A,Used_before_Trf!A85,'CHE-last month'!C:C) -> 87.62 | X85: =IF(W85=0,0,Y85/W85) -> 13.088907 | Y85: =SUMIF('CHE-last month'!$A:$A,Used_before_Trf!A85,'CHE-last month'!E:E) -> 1146.85 | Z85: =+AC85+AF85+AI85 -> 51.61 | AA85: =IF(Z85=0,0,AB85/Z85) -> 15 | AB85: =+AE85+AH85+AK85 -> 774.15 | AC85: =SUMIFS(BalCom!M:M,BalCom!N:N,Used_before_Trf!A85,BalCom!C:C,Used_before_Trf!$AC$1) -> 0 | AD85: =IF(AC85=0,0,AE85/AC85) -> 0 | AE85: =SUMIFS(BalCom!P:P,BalCom!N:N,Used_before_Trf!A85,BalCom!C:C,Used_before_Trf!$AC$1) -> 0 | AF85: =SUMIFS(BalDis!I:I,BalDis!J:J,Used_before_Trf!A85) -> 0 | AG85: =IF(AF85=0,0,AH85/AF85) -> 0 | AH85: =SUMIFS(BalDis!L:L,BalDis!J:J,Used_before_Trf!A85) -> 0 | AI85: =SUMIFS(BalDip!$N$49:$N$75,BalDip!$C$49:$C$75,Used_before_Trf!A85)+SUMIFS(BalDip!$N$134:$N$157,BalDip!$C$134:$C$157,Used_before_Trf!A85) -> 51.61 | AJ85: =IF(AI85=0,0,AK85/AI85) -> 15 | AK85: =SUMIFS(BalDip!$N$80:$N$106,BalDip!$C$80:$C$106,Used_before_Trf!A85)+SUMIFS(BalDip!$N$161:$N$184,BalDip!$C$161:$C$184,Used_before_Trf!A85) -> 774.15 | AL85: =+T85+W85-Z85 -> 4236.01 | AM85: =IF(AL85=0,0,AN85/AL85) -> 14.96047 | AN85: =+V85+Y85-AB85 -> 63372.7 | AO85: =AM85-U85 -> -0.039530124
A86: CH45 | B86: CALCIUM NITRATE, SOLUTION 54-54% (310/DRUM),(25000KG/TANK) | C86: =SUMIF('Che-Store'!A:A,Used_before_Trf!A86,'Che-Store'!AC:AC)+SUMIF('Che-Comp'!A:A,Used_before_Trf!A86,'Che-Comp'!AC:AC) -> 0 | D86: =IFERROR(E86/C86,0) -> 0 | E86: =SUMIF('Che-Store'!A:A,Used_before_Trf!A86,'Che-Store'!AE:AE)+SUMIF('Che-Comp'!A:A,Used_before_Trf!A86,'Che-Comp'!AE:AE) -> 0 | F86: =SUMIFS('Che-Comp'!F:F,'Che-Comp'!$A:$A,Used_before_Trf!$A86) -> 0 | G86: =SUMIFS('Che-Comp'!G:G,'Che-Comp'!$A:$A,Used_before_Trf!$A86) -> 0 | H86: =C86-F86 -> 0 | I86: =IFERROR(J86/H86,0) -> 0 | J86: =E86-G86 -> 0 | K86: =SUMIF('Che.-Prod'!A:A,Used_before_Trf!A86,'Che.-Prod'!D:D) -> 0 | L86: =IFERROR(M86/K86,0) -> 0 | M86: =SUMIF('Che.-Prod'!A:A,Used_before_Trf!A86,'Che.-Prod'!F:F) -> 0 | N86: =SUMIF('Che.-Prod'!A:A,Used_before_Trf!A86,'Che.-Prod'!G:G) -> 0 | O86: =IF(N86=0,0,P86/N86) -> 0 | P86: =SUMIF('Che.-Prod'!A:A,Used_before_Trf!A86,'Che.-Prod'!H:H) -> 0 | Q86: =SUMIF('Che.-Prod'!A:A,Used_before_Trf!A86,'Che.-Prod'!P:P) -> 0 | R86: =IF(Q86=0,0,S86/Q86) -> 0 | S86: =SUMIF('Che.-Prod'!A:A,Used_before_Trf!A86,'Che.-Prod'!R:R) -> 0 | T86: =H86+K86+N86-Q86 -> 0 | U86: =IF(T86=0,0,V86/T86) -> 0 | V86: =J86+M86+P86-S86 -> 0 | W86: =SUMIF('CHE-last month'!$A:$A,Used_before_Trf!A86,'CHE-last month'!C:C) -> 0 | X86: =IF(W86=0,0,Y86/W86) -> 0 | Y86: =SUMIF('CHE-last month'!$A:$A,Used_before_Trf!A86,'CHE-last month'!E:E) -> 0 | Z86: =+AC86+AF86+AI86 -> 0 | AA86: =IF(Z86=0,0,AB86/Z86) -> 0 | AB86: =+AE86+AH86+AK86 -> 0 | AC86: =SUMIFS(BalCom!M:M,BalCom!N:N,Used_before_Trf!A86,BalCom!C:C,Used_before_Trf!$AC$1) -> 0 | AD86: =IF(AC86=0,0,AE86/AC86) -> 0 | AE86: =SUMIFS(BalCom!P:P,BalCom!N:N,Used_before_Trf!A86,BalCom!C:C,Used_before_Trf!$AC$1) -> 0 | AF86: =SUMIFS(BalDis!I:I,BalDis!J:J,Used_before_Trf!A86) -> 0 | AG86: =IF(AF86=0,0,AH86/AF86) -> 0 | AH86: =SUMIFS(BalDis!L:L,BalDis!J:J,Used_before_Trf!A86) -> 0 | AI86: =SUMIFS(BalDip!$N$49:$N$75,BalDip!$C$49:$C$75,Used_before_Trf!A86)+SUMIFS(BalDip!$N$134:$N$157,BalDip!$C$134:$C$157,Used_before_Trf!A86) -> 0 | AJ86: =IF(AI86=0,0,AK86/AI86) -> 0 | AK86: =SUMIFS(BalDip!$N$80:$N$106,BalDip!$C$80:$C$106,Used_before_Trf!A86)+SUMIFS(BalDip!$N$161:$N$184,BalDip!$C$161:$C$184,Used_before_Trf!A86) -> 0 | AL86: =+T86+W86-Z86 -> 0 | AM86: =IF(AL86=0,0,AN86/AL86) -> 0 | AN86: =+V86+Y86-AB86 -> 0 | AO86: =AM86-U86 -> 0
A87: CH57 | B87: CARBOWET LSF ( 213 KGS / DRUM ) | C87: =SUMIF('Che-Store'!A:A,Used_before_Trf!A87,'Che-Store'!AC:AC)+SUMIF('Che-Comp'!A:A,Used_before_Trf!A87,'Che-Comp'!AC:AC) -> 0 | D87: =IFERROR(E87/C87,0) -> 0 | E87: =SUMIF('Che-Store'!A:A,Used_before_Trf!A87,'Che-Store'!AE:AE)+SUMIF('Che-Comp'!A:A,Used_before_Trf!A87,'Che-Comp'!AE:AE) -> 0 | F87: =SUMIFS('Che-Comp'!F:F,'Che-Comp'!$A:$A,Used_before_Trf!$A87) -> 0 | G87: =SUMIFS('Che-Comp'!G:G,'Che-Comp'!$A:$A,Used_before_Trf!$A87) -> 0 | H87: =C87-F87 -> 0 | I87: =IFERROR(J87/H87,0) -> 0 | J87: =E87-G87 -> 0 | K87: =SUMIF('Che.-Prod'!A:A,Used_before_Trf!A87,'Che.-Prod'!D:D) -> 0 | L87: =IFERROR(M87/K87,0) -> 0 | M87: =SUMIF('Che.-Prod'!A:A,Used_before_Trf!A87,'Che.-Prod'!F:F) -> 0 | N87: =SUMIF('Che.-Prod'!A:A,Used_before_Trf!A87,'Che.-Prod'!G:G) -> 0 | O87: =IF(N87=0,0,P87/N87) -> 0 | P87: =SUMIF('Che.-Prod'!A:A,Used_before_Trf!A87,'Che.-Prod'!H:H) -> 0 | Q87: =SUMIF('Che.-Prod'!A:A,Used_before_Trf!A87,'Che.-Prod'!P:P) -> 0 | R87: =IF(Q87=0,0,S87/Q87) -> 0 | S87: =SUMIF('Che.-Prod'!A:A,Used_before_Trf!A87,'Che.-Prod'!R:R) -> 0 | T87: =H87+K87+N87-Q87 -> 0 | U87: =IF(T87=0,0,V87/T87) -> 0 | V87: =J87+M87+P87-S87 -> 0 | W87: =SUMIF('CHE-last month'!$A:$A,Used_before_Trf!A87,'CHE-last month'!C:C) -> 0 | X87: =IF(W87=0,0,Y87/W87) -> 0 | Y87: =SUMIF('CHE-last month'!$A:$A,Used_before_Trf!A87,'CHE-last month'!E:E) -> 0 | Z87: =+AC87+AF87+AI87 -> 0 | AA87: =IF(Z87=0,0,AB87/Z87) -> 0 | AB87: =+AE87+AH87+AK87 -> 0 | AC87: =SUMIFS(BalCom!M:M,BalCom!N:N,Used_before_Trf!A87,BalCom!C:C,Used_before_Trf!$AC$1) -> 0 | AD87: =IF(AC87=0,0,AE87/AC87) -> 0 | AE87: =SUMIFS(BalCom!P:P,BalCom!N:N,Used_before_Trf!A87,BalCom!C:C,Used_before_Trf!$AC$1) -> 0 | AF87: =SUMIFS(BalDis!I:I,BalDis!J:J,Used_before_Trf!A87) -> 0 | AG87: =IF(AF87=0,0,AH87/AF87) -> 0 | AH87: =SUMIFS(BalDis!L:L,BalDis!J:J,Used_before_Trf!A87) -> 0 | AI87: =SUMIFS(BalDip!$N$49:$N$75,BalDip!$C$49:$C$75,Used_before_Trf!A87)+SUMIFS(BalDip!$N$134:$N$157,BalDip!$C$134:$C$157,Used_before_Trf!A87) -> 0 | AJ87: =IF(AI87=0,0,AK87/AI87) -> 0 | AK87: =SUMIFS(BalDip!$N$80:$N$106,BalDip!$C$80:$C$106,Used_before_Trf!A87)+SUMIFS(BalDip!$N$161:$N$184,BalDip!$C$161:$C$184,Used_before_Trf!A87) -> 0 | AL87: =+T87+W87-Z87 -> 0 | AM87: =IF(AL87=0,0,AN87/AL87) -> 0 | AN87: =+V87+Y87-AB87 -> 0 | AO87: =AM87-U87 -> 0
A88: CH60 | B88: RHODOLINE DF642 18KGS/DRUM | C88: =SUMIF('Che-Store'!A:A,Used_before_Trf!A88,'Che-Store'!AC:AC)+SUMIF('Che-Comp'!A:A,Used_before_Trf!A88,'Che-Comp'!AC:AC) -> 0 | D88: =IFERROR(E88/C88,0) -> 0 | E88: =SUMIF('Che-Store'!A:A,Used_before_Trf!A88,'Che-Store'!AE:AE)+SUMIF('Che-Comp'!A:A,Used_before_Trf!A88,'Che-Comp'!AE:AE) -> 0 | F88: =SUMIFS('Che-Comp'!F:F,'Che-Comp'!$A:$A,Used_before_Trf!$A88) -> 0 | G88: =SUMIFS('Che-Comp'!G:G,'Che-Comp'!$A:$A,Used_before_Trf!$A88) -> 0 | H88: =C88-F88 -> 0 | I88: =IFERROR(J88/H88,0) -> 0 | J88: =E88-G88 -> 0 | K88: =SUMIF('Che.-Prod'!A:A,Used_before_Trf!A88,'Che.-Prod'!D:D) -> 0 | L88: =IFERROR(M88/K88,0) -> 0 | M88: =SUMIF('Che.-Prod'!A:A,Used_before_Trf!A88,'Che.-Prod'!F:F) -> 0 | N88: =SUMIF('Che.-Prod'!A:A,Used_before_Trf!A88,'Che.-Prod'!G:G) -> 0 | O88: =IF(N88=0,0,P88/N88) -> 0 | P88: =SUMIF('Che.-Prod'!A:A,Used_before_Trf!A88,'Che.-Prod'!H:H) -> 0 | Q88: =SUMIF('Che.-Prod'!A:A,Used_before_Trf!A88,'Che.-Prod'!P:P) -> 0 | R88: =IF(Q88=0,0,S88/Q88) -> 0 | S88: =SUMIF('Che.-Prod'!A:A,Used_before_Trf!A88,'Che.-Prod'!R:R) -> 0 | T88: =H88+K88+N88-Q88 -> 0 | U88: =IF(T88=0,0,V88/T88) -> 0 | V88: =J88+M88+P88-S88 -> 0 | W88: =SUMIF('CHE-last month'!$A:$A,Used_before_Trf!A88,'CHE-last month'!C:C) -> 0 | X88: =IF(W88=0,0,Y88/W88) -> 0 | Y88: =SUMIF('CHE-last month'!$A:$A,Used_before_Trf!A88,'CHE-last month'!E:E) -> 0 | Z88: =+AC88+AF88+AI88 -> 0 | AA88: =IF(Z88=0,0,AB88/Z88) -> 0 | AB88: =+AE88+AH88+AK88 -> 0 | AC88: =SUMIFS(BalCom!M:M,BalCom!N:N,Used_before_Trf!A88,BalCom!C:C,Used_before_Trf!$AC$1) -> 0 | AD88: =IF(AC88=0,0,AE88/AC88) -> 0 | AE88: =SUMIFS(BalCom!P:P,BalCom!N:N,Used_before_Trf!A88,BalCom!C:C,Used_before_Trf!$AC$1) -> 0 | AF88: =SUMIFS(BalDis!I:I,BalDis!J:J,Used_before_Trf!A88) -> 0 | AG88: =IF(AF88=0,0,AH88/AF88) -> 0 | AH88: =SUMIFS(BalDis!L:L,BalDis!J:J,Used_before_Trf!A88) -> 0 | AI88: =SUMIFS(BalDip!$N$49:$N$75,BalDip!$C$49:$C$75,Used_before_Trf!A88)+SUMIFS(BalDip!$N$134:$N$157,BalDip!$C$134:$C$157,Used_before_Trf!A88) -> 0 | AJ88: =IF(AI88=0,0,AK88/AI88) -> 0 | AK88: =SUMIFS(BalDip!$N$80:$N$106,BalDip!$C$80:$C$106,Used_before_Trf!A88)+SUMIFS(BalDip!$N$161:$N$184,BalDip!$C$161:$C$184,Used_before_Trf!A88) -> 0 | AL88: =+T88+W88-Z88 -> 0 | AM88: =IF(AL88=0,0,AN88/AL88) -> 0 | AN88: =+V88+Y88-AB88 -> 0 | AO88: =AM88-U88 -> 0
A89: CH88 | B89: SURFYNOL DF 37 (DEFORMER) 20KGS./DRUM | C89: =SUMIF('Che-Store'!A:A,Used_before_Trf!A89,'Che-Store'!AC:AC)+SUMIF('Che-Comp'!A:A,Used_before_Trf!A89,'Che-Comp'!AC:AC) -> 0 | D89: =IFERROR(E89/C89,0) -> 0 | E89: =SUMIF('Che-Store'!A:A,Used_before_Trf!A89,'Che-Store'!AE:AE)+SUMIF('Che-Comp'!A:A,Used_before_Trf!A89,'Che-Comp'!AE:AE) -> 0 | F89: =SUMIFS('Che-Comp'!F:F,'Che-Comp'!$A:$A,Used_before_Trf!$A89) -> 0 | G89: =SUMIFS('Che-Comp'!G:G,'Che-Comp'!$A:$A,Used_before_Trf!$A89) -> 0 | H89: =C89-F89 -> 0 | I89: =IFERROR(J89/H89,0) -> 0 | J89: =E89-G89 -> 0 | K89: =SUMIF('Che.-Prod'!A:A,Used_before_Trf!A89,'Che.-Prod'!D:D) -> 0 | L89: =IFERROR(M89/K89,0) -> 0 | M89: =SUMIF('Che.-Prod'!A:A,Used_before_Trf!A89,'Che.-Prod'!F:F) -> 0 | N89: =SUMIF('Che.-Prod'!A:A,Used_before_Trf!A89,'Che.-Prod'!G:G) -> 0 | O89: =IF(N89=0,0,P89/N89) -> 0 | P89: =SUMIF('Che.-Prod'!A:A,Used_before_Trf!A89,'Che.-Prod'!H:H) -> 0 | Q89: =SUMIF('Che.-Prod'!A:A,Used_before_Trf!A89,'Che.-Prod'!P:P) -> 0 | R89: =IF(Q89=0,0,S89/Q89) -> 0 | S89: =SUMIF('Che.-Prod'!A:A,Used_before_Trf!A89,'Che.-Prod'!R:R) -> 0 | T89: =H89+K89+N89-Q89 -> 0 | U89: =IF(T89=0,0,V89/T89) -> 0 | V89: =J89+M89+P89-S89 -> 0 | W89: =SUMIF('CHE-last month'!$A:$A,Used_before_Trf!A89,'CHE-last month'!C:C) -> 0 | X89: =IF(W89=0,0,Y89/W89) -> 0 | Y89: =SUMIF('CHE-last month'!$A:$A,Used_before_Trf!A89,'CHE-last month'!E:E) -> 0 | Z89: =+AC89+AF89+AI89 -> 0 | AA89: =IF(Z89=0,0,AB89/Z89) -> 0 | AB89: =+AE89+AH89+AK89 -> 0 | AC89: =SUMIFS(BalCom!M:M,BalCom!N:N,Used_before_Trf!A89,BalCom!C:C,Used_before_Trf!$AC$1) -> 0 | AD89: =IF(AC89=0,0,AE89/AC89) -> 0 | AE89: =SUMIFS(BalCom!P:P,BalCom!N:N,Used_before_Trf!A89,BalCom!C:C,Used_before_Trf!$AC$1) -> 0 | AF89: =SUMIFS(BalDis!I:I,BalDis!J:J,Used_before_Trf!A89) -> 0 | AG89: =IF(AF89=0,0,AH89/AF89) -> 0 | AH89: =SUMIFS(BalDis!L:L,BalDis!J:J,Used_before_Trf!A89) -> 0 | AI89: =SUMIFS(BalDip!$N$49:$N$75,BalDip!$C$49:$C$75,Used_before_Trf!A89)+SUMIFS(BalDip!$N$134:$N$157,BalDip!$C$134:$C$157,Used_before_Trf!A89) -> 0 | AJ89: =IF(AI89=0,0,AK89/AI89) -> 0 | AK89: =SUMIFS(BalDip!$N$80:$N$106,BalDip!$C$80:$C$106,Used_before_Trf!A89)+SUMIFS(BalDip!$N$161:$N$184,BalDip!$C$161:$C$184,Used_before_Trf!A89) -> 0 | AL89: =+T89+W89-Z89 -> 0 | AM89: =IF(AL89=0,0,AN89/AL89) -> 0 | AN89: =+V89+Y89-AB89 -> 0 | AO89: =AM89-U89 -> 0
A90: CH89 | B90: SURFYNOL TG (SURFACTANT) 204.1 KGS./DRUM | C90: =SUMIF('Che-Store'!A:A,Used_before_Trf!A90,'Che-Store'!AC:AC)+SUMIF('Che-Comp'!A:A,Used_before_Trf!A90,'Che-Comp'!AC:AC) -> 0 | D90: =IFERROR(E90/C90,0) -> 0 | E90: =SUMIF('Che-Store'!A:A,Used_before_Trf!A90,'Che-Store'!AE:AE)+SUMIF('Che-Comp'!A:A,Used_before_Trf!A90,'Che-Comp'!AE:AE) -> 0 | F90: =SUMIFS('Che-Comp'!F:F,'Che-Comp'!$A:$A,Used_before_Trf!$A90) -> 0 | G90: =SUMIFS('Che-Comp'!G:G,'Che-Comp'!$A:$A,Used_before_Trf!$A90) -> 0 | H90: =C90-F90 -> 0 | I90: =IFERROR(J90/H90,0) -> 0 | J90: =E90-G90 -> 0 | K90: =SUMIF('Che.-Prod'!A:A,Used_before_Trf!A90,'Che.-Prod'!D:D) -> 0 | L90: =IFERROR(M90/K90,0) -> 0 | M90: =SUMIF('Che.-Prod'!A:A,Used_before_Trf!A90,'Che.-Prod'!F:F) -> 0 | N90: =SUMIF('Che.-Prod'!A:A,Used_before_Trf!A90,'Che.-Prod'!G:G) -> 0 | O90: =IF(N90=0,0,P90/N90) -> 0 | P90: =SUMIF('Che.-Prod'!A:A,Used_before_Trf!A90,'Che.-Prod'!H:H) -> 0 | Q90: =SUMIF('Che.-Prod'!A:A,Used_before_Trf!A90,'Che.-Prod'!P:P) -> 0 | R90: =IF(Q90=0,0,S90/Q90) -> 0 | S90: =SUMIF('Che.-Prod'!A:A,Used_before_Trf!A90,'Che.-Prod'!R:R) -> 0 | T90: =H90+K90+N90-Q90 -> 0 | U90: =IF(T90=0,0,V90/T90) -> 0 | V90: =J90+M90+P90-S90 -> 0 | W90: =SUMIF('CHE-last month'!$A:$A,Used_before_Trf!A90,'CHE-last month'!C:C) -> 0 | X90: =IF(W90=0,0,Y90/W90) -> 0 | Y90: =SUMIF('CHE-last month'!$A:$A,Used_before_Trf!A90,'CHE-last month'!E:E) -> 0 | Z90: =+AC90+AF90+AI90 -> 0 | AA90: =IF(Z90=0,0,AB90/Z90) -> 0 | AB90: =+AE90+AH90+AK90 -> 0 | AC90: =SUMIFS(BalCom!M:M,BalCom!N:N,Used_before_Trf!A90,BalCom!C:C,Used_before_Trf!$AC$1) -> 0 | AD90: =IF(AC90=0,0,AE90/AC90) -> 0 | AE90: =SUMIFS(BalCom!P:P,BalCom!N:N,Used_before_Trf!A90,BalCom!C:C,Used_before_Trf!$AC$1) -> 0 | AF90: =SUMIFS(BalDis!I:I,BalDis!J:J,Used_before_Trf!A90) -> 0 | AG90: =IF(AF90=0,0,AH90/AF90) -> 0 | AH90: =SUMIFS(BalDis!L:L,BalDis!J:J,Used_before_Trf!A90) -> 0 | AI90: =SUMIFS(BalDip!$N$49:$N$75,BalDip!$C$49:$C$75,Used_before_Trf!A90)+SUMIFS(BalDip!$N$134:$N$157,BalDip!$C$134:$C$157,Used_before_Trf!A90) -> 0 | AJ90: =IF(AI90=0,0,AK90/AI90) -> 0 | AK90: =SUMIFS(BalDip!$N$80:$N$106,BalDip!$C$80:$C$106,Used_before_Trf!A90)+SUMIFS(BalDip!$N$161:$N$184,BalDip!$C$161:$C$184,Used_before_Trf!A90) -> 0 | AL90: =+T90+W90-Z90 -> 0 | AM90: =IF(AL90=0,0,AN90/AL90) -> 0 | AN90: =+V90+Y90-AB90 -> 0 | AO90: =AM90-U90 -> 0
A91: CH90 | B91: ZDEC 50% 225 KGS/DRUM | C91: =SUMIF('Che-Store'!A:A,Used_before_Trf!A91,'Che-Store'!AC:AC)+SUMIF('Che-Comp'!A:A,Used_before_Trf!A91,'Che-Comp'!AC:AC) -> 0 | D91: =IFERROR(E91/C91,0) -> 0 | E91: =SUMIF('Che-Store'!A:A,Used_before_Trf!A91,'Che-Store'!AE:AE)+SUMIF('Che-Comp'!A:A,Used_before_Trf!A91,'Che-Comp'!AE:AE) -> 0 | F91: =SUMIFS('Che-Comp'!F:F,'Che-Comp'!$A:$A,Used_before_Trf!$A91) -> 0 | G91: =SUMIFS('Che-Comp'!G:G,'Che-Comp'!$A:$A,Used_before_Trf!$A91) -> 0 | H91: =C91-F91 -> 0 | I91: =IFERROR(J91/H91,0) -> 0 | J91: =E91-G91 -> 0 | K91: =SUMIF('Che.-Prod'!A:A,Used_before_Trf!A91,'Che.-Prod'!D:D) -> 0 | L91: =IFERROR(M91/K91,0) -> 0 | M91: =SUMIF('Che.-Prod'!A:A,Used_before_Trf!A91,'Che.-Prod'!F:F) -> 0 | N91: =SUMIF('Che.-Prod'!A:A,Used_before_Trf!A91,'Che.-Prod'!G:G) -> 0 | O91: =IF(N91=0,0,P91/N91) -> 0 | P91: =SUMIF('Che.-Prod'!A:A,Used_before_Trf!A91,'Che.-Prod'!H:H) -> 0 | Q91: =SUMIF('Che.-Prod'!A:A,Used_before_Trf!A91,'Che.-Prod'!P:P) -> 0 | R91: =IF(Q91=0,0,S91/Q91) -> 0 | S91: =SUMIF('Che.-Prod'!A:A,Used_before_Trf!A91,'Che.-Prod'!R:R) -> 0 | T91: =H91+K91+N91-Q91 -> 0 | U91: =IF(T91=0,0,V91/T91) -> 0 | V91: =J91+M91+P91-S91 -> 0 | W91: =SUMIF('CHE-last month'!$A:$A,Used_before_Trf!A91,'CHE-last month'!C:C) -> 0 | X91: =IF(W91=0,0,Y91/W91) -> 0 | Y91: =SUMIF('CHE-last month'!$A:$A,Used_before_Trf!A91,'CHE-last month'!E:E) -> 0 | Z91: =+AC91+AF91+AI91 -> 0 | AA91: =IF(Z91=0,0,AB91/Z91) -> 0 | AB91: =+AE91+AH91+AK91 -> 0 | AC91: =SUMIFS(BalCom!M:M,BalCom!N:N,Used_before_Trf!A91,BalCom!C:C,Used_before_Trf!$AC$1) -> 0 | AD91: =IF(AC91=0,0,AE91/AC91) -> 0 | AE91: =SUMIFS(BalCom!P:P,BalCom!N:N,Used_before_Trf!A91,BalCom!C:C,Used_before_Trf!$AC$1) -> 0 | AF91: =SUMIFS(BalDis!I:I,BalDis!J:J,Used_before_Trf!A91) -> 0 | AG91: =IF(AF91=0,0,AH91/AF91) -> 0 | AH91: =SUMIFS(BalDis!L:L,BalDis!J:J,Used_before_Trf!A91) -> 0 | AI91: =SUMIFS(BalDip!$N$49:$N$75,BalDip!$C$49:$C$75,Used_before_Trf!A91)+SUMIFS(BalDip!$N$134:$N$157,BalDip!$C$134:$C$157,Used_before_Trf!A91) -> 0 | AJ91: =IF(AI91=0,0,AK91/AI91) -> 0 | AK91: =SUMIFS(BalDip!$N$80:$N$106,BalDip!$C$80:$C$106,Used_before_Trf!A91)+SUMIFS(BalDip!$N$161:$N$184,BalDip!$C$161:$C$184,Used_before_Trf!A91) -> 0 | AL91: =+T91+W91-Z91 -> 0 | AM91: =IF(AL91=0,0,AN91/AL91) -> 0 | AN91: =+V91+Y91-AB91 -> 0 | AO91: =AM91-U91 -> 0
A92: CH91 | B92: ZDBC 50% 225 KGS/DRUM | C92: =SUMIF('Che-Store'!A:A,Used_before_Trf!A92,'Che-Store'!AC:AC)+SUMIF('Che-Comp'!A:A,Used_before_Trf!A92,'Che-Comp'!AC:AC) -> 1090.7 | D92: =IFERROR(E92/C92,0) -> 50.317319 | E92: =SUMIF('Che-Store'!A:A,Used_before_Trf!A92,'Che-Store'!AE:AE)+SUMIF('Che-Comp'!A:A,Used_before_Trf!A92,'Che-Comp'!AE:AE) -> 54881.1 | F92: =SUMIFS('Che-Comp'!F:F,'Che-Comp'!$A:$A,Used_before_Trf!$A92) -> 0 | G92: =SUMIFS('Che-Comp'!G:G,'Che-Comp'!$A:$A,Used_before_Trf!$A92) -> 0 | H92: =C92-F92 -> 1090.7 | I92: =IFERROR(J92/H92,0) -> 50.317319 | J92: =E92-G92 -> 54881.1 | K92: =SUMIF('Che.-Prod'!A:A,Used_before_Trf!A92,'Che.-Prod'!D:D) -> 0 | L92: =IFERROR(M92/K92,0) -> 0 | M92: =SUMIF('Che.-Prod'!A:A,Used_before_Trf!A92,'Che.-Prod'!F:F) -> 0 | N92: =SUMIF('Che.-Prod'!A:A,Used_before_Trf!A92,'Che.-Prod'!G:G) -> 0 | O92: =IF(N92=0,0,P92/N92) -> 0 | P92: =SUMIF('Che.-Prod'!A:A,Used_before_Trf!A92,'Che.-Prod'!H:H) -> 0 | Q92: =SUMIF('Che.-Prod'!A:A,Used_before_Trf!A92,'Che.-Prod'!P:P) -> 0 | R92: =IF(Q92=0,0,S92/Q92) -> 0 | S92: =SUMIF('Che.-Prod'!A:A,Used_before_Trf!A92,'Che.-Prod'!R:R) -> 0 | T92: =H92+K92+N92-Q92 -> 1090.7 | U92: =IF(T92=0,0,V92/T92) -> 50.317319 | V92: =J92+M92+P92-S92 -> 54881.1 | W92: =SUMIF('CHE-last month'!$A:$A,Used_before_Trf!A92,'CHE-last month'!C:C) -> 119.11671 | X92: =IF(W92=0,0,Y92/W92) -> 48.444587 | Y92: =SUMIF('CHE-last month'!$A:$A,Used_before_Trf!A92,'CHE-last month'!E:E) -> 5770.56 | Z92: =+AC92+AF92+AI92 -> 224.76312 | AA92: =IF(Z92=0,0,AB92/Z92) -> 50.317241 | AB92: =+AE92+AH92+AK92 -> 11309.46 | AC92: =SUMIFS(BalCom!M:M,BalCom!N:N,Used_before_Trf!A92,BalCom!C:C,Used_before_Trf!$AC$1) -> 185.13243 | AD92: =IF(AC92=0,0,AE92/AC92) -> 50.317224 | AE92: =SUMIFS(BalCom!P:P,BalCom!N:N,Used_before_Trf!A92,BalCom!C:C,Used_before_Trf!$AC$1) -> 9315.35 | AF92: =SUMIFS(BalDis!I:I,BalDis!J:J,Used_before_Trf!A92) -> 0 | AG92: =IF(AF92=0,0,AH92/AF92) -> 0 | AH92: =SUMIFS(BalDis!L:L,BalDis!J:J,Used_before_Trf!A92) -> 0 | AI92: =SUMIFS(BalDip!$N$49:$N$75,BalDip!$C$49:$C$75,Used_before_Trf!A92)+SUMIFS(BalDip!$N$134:$N$157,BalDip!$C$134:$C$157,Used_before_Trf!A92) -> 39.630688 | AJ92: =IF(AI92=0,0,AK92/AI92) -> 50.31732 | AK92: =SUMIFS(BalDip!$N$80:$N$106,BalDip!$C$80:$C$106,Used_before_Trf!A92)+SUMIFS(BalDip!$N$161:$N$184,BalDip!$C$161:$C$184,Used_before_Trf!A92) -> 1994.11 | AL92: =+T92+W92-Z92 -> 985.0536 | AM92: =IF(AL92=0,0,AN92/AL92) -> 50.090878 | AN92: =+V92+Y92-AB92 -> 49342.2 | AO92: =AM92-U92 -> -0.22644072
... A96: CH95 | B96: 56% FARSPERSE BLUE PL-SRB 20 KGS / PAIL | C96: =SUMIF('Che-Store'!A:A,Used_before_Trf!A96,'Che-Store'!AC:AC)+SUMIF('Che-Comp'!A:A,Used_before_Trf!A96,'Che-Comp'!AC:AC) -> 0 | D96: =IFERROR(E96/C96,0) -> 0 | E96: =SUMIF('Che-Store'!A:A,Used_before_Trf!A96,'Che-Store'!AE:AE)+SUMIF('Che-Comp'!A:A,Used_before_Trf!A96,'Che-Comp'!AE:AE) -> 0 | F96: =SUMIFS('Che-Comp'!F:F,'Che-Comp'!$A:$A,Used_before_Trf!$A96) -> 0 | G96: =SUMIFS('Che-Comp'!G:G,'Che-Comp'!$A:$A,Used_before_Trf!$A96) -> 0 | H96: =C96-F96 -> 0 | I96: =IFERROR(J96/H96,0) -> 0 | J96: =E96-G96 -> 0 | K96: =SUMIF('Che.-Prod'!A:A,Used_before_Trf!A96,'Che.-Prod'!D:D) -> 0 | L96: =IFERROR(M96/K96,0) -> 0 | M96: =SUMIF('Che.-Prod'!A:A,Used_before_Trf!A96,'Che.-Prod'!F:F) -> 0 | N96: =SUMIF('Che.-Prod'!A:A,Used_before_Trf!A96,'Che.-Prod'!G:G) -> 0 | O96: =IF(N96=0,0,P96/N96) -> 0 | P96: =SUMIF('Che.-Prod'!A:A,Used_before_Trf!A96,'Che.-Prod'!H:H) -> 0 | Q96: =SUMIF('Che.-Prod'!A:A,Used_before_Trf!A96,'Che.-Prod'!P:P) -> 0 | R96: =IF(Q96=0,0,S96/Q96) -> 0 | S96: =SUMIF('Che.-Prod'!A:A,Used_before_Trf!A96,'Che.-Prod'!R:R) -> 0 | T96: =H96+K96+N96-Q96 -> 0 | U96: =IF(T96=0,0,V96/T96) -> 0 | V96: =J96+M96+P96-S96 -> 0 | W96: =SUMIF('CHE-last month'!$A:$A,Used_before_Trf!A96,'CHE-last month'!C:C) -> 0 | X96: =IF(W96=0,0,Y96/W96) -> 0 | Y96: =SUMIF('CHE-last month'!$A:$A,Used_before_Trf!A96,'CHE-last month'!E:E) -> 0 | Z96: =+AC96+AF96+AI96 -> 0 | AA96: =IF(Z96=0,0,AB96/Z96) -> 0 | AB96: =+AE96+AH96+AK96 -> 0 | AC96: =SUMIFS(BalCom!M:M,BalCom!N:N,Used_before_Trf!A96,BalCom!C:C,Used_before_Trf!$AC$1) -> 0 | AD96: =IF(AC96=0,0,AE96/AC96) -> 0 | AE96: =SUMIFS(BalCom!P:P,BalCom!N:N,Used_before_Trf!A96,BalCom!C:C,Used_before_Trf!$AC$1) -> 0 | AF96: =SUMIFS(BalDis!I:I,BalDis!J:J,Used_before_Trf!A96) -> 0 | AG96: =IF(AF96=0,0,AH96/AF96) -> 0 | AH96: =SUMIFS(BalDis!L:L,BalDis!J:J,Used_before_Trf!A96) -> 0 | AI96: =SUMIFS(BalDip!$N$49:$N$75,BalDip!$C$49:$C$75,Used_before_Trf!A96)+SUMIFS(BalDip!$N$134:$N$157,BalDip!$C$134:$C$157,Used_before_Trf!A96) -> 0 | AJ96: =IF(AI96=0,0,AK96/AI96) -> 0 | AK96: =SUMIFS(BalDip!$N$80:$N$106,BalDip!$C$80:$C$106,Used_before_Trf!A96)+SUMIFS(BalDip!$N$161:$N$184,BalDip!$C$161:$C$184,Used_before_Trf!A96) -> 0 | AL96: =+T96+W96-Z96 -> 0 | AM96: =IF(AL96=0,0,AN96/AL96) -> 0 | AN96: =+V96+Y96-AB96 -> 0 | AO96: =AM96-U96 -> 0
